Workbook
Name AbraSG: 'inventory 5-6'!$B$63:$B$110
Name AbraSG: 'Inventory of Positions'!$B$63:$B$109
Name age: 'staffing plan'!$BA$12:$BA$241
Name agegroup: 'staffing plan'!$BB$12:$BB$242
Name ApayaoSG: 'inventory 5-6'!$B$113:$B$135
Name ApayaoSG: 'Inventory of Positions'!$B$112:$B$133
Name BaguioSG: 'inventory 5-6'!$B$138:$B$144
Name BaguioSG: 'Inventory of Positions'!$B$136:$B$142
Name BARNACHEA: '[1]salary grade'!$B$2:$I$29
Name barnachea: 'salary grade'!$B$2:$I$29
Name BARNACHEA1: 'salary grade'!$M$2:$T$29
Name barnachea18: #REF!
Name barnachea18: #REF!
Name barnachea18: #REF!
Name barnachea18: #REF!
Name barnachea18: #REF!
Name BenguetSG: 'inventory 5-6'!$B$147:$B$176
Name BenguetSG: 'Inventory of Positions'!$B$145:$B$173
Name gender: 'staffing plan'!$AY$12:$AY$241
Name genderagegroupstation: 'staffing plan'!$BD$12:$BD$242
Name GENDERSTATION: 'staffing plan'!$L$12:$L$241
Name GRACE: '[1]salary grade'!$B$1:$I$1
Name grace: 'salary grade'!$B$1:$I$1
Name gRACE1: 'salary grade'!$M$1:$T$1
Name IDICA: '[1]salary grade'!$A$2:$I$29
Name idica: 'salary grade'!$A$2:$I$29
Name IDICA1: 'salary grade'!$L$2:$S$29
Name idica18: #REF!
Name idica18: #REF!
Name idica18: #REF!
Name idica18: #REF!
Name idica18: #REF!
Name IfugaoSG: 'inventory 5-6'!$B$179:$B$203
Name IfugaoSG: 'Inventory of Positions'!$B$176:$B$200
Name KalingaSG: 'inventory 5-6'!$B$206:$B$228
Name KalingaSG: 'Inventory of Positions'!$B$203:$B$225
Name Level: 'staffing plan'!$AM$12:$AM$240
Name leveljo: 'COS in CO'!#REF!
Name leveljo: #REF!
Name leveljo: 'JO inventory'!$J$9:$J$64
Name leveljo18: '[2]JO inventory'!$J$9:$J$66
Name MtProvinceSG: 'inventory 5-6'!$B$231:$B$254
Name MtProvinceSG: 'Inventory of Positions'!$B$228:$B$251
Name nORMAN: '[1]salary grade'!$A$2:$A$29
Name norman: 'salary grade'!$A$2:$A$29
Name NORMAN1: 'salary grade'!$L$2:$L$29
Name Norman18: #REF!
Name Norman18: #REF!
Name Norman18: #REF!
Name Norman18: #REF!
Name Norman18: #REF!
Name positiontitle: 'staffing plan'!#REF!
Name PosStSex: 'staffing plan'!$K$12:$K$240
Name PTSexCat: 'staffing plan'!$BE$12:$BE$240
Name PTStation: 'staffing plan'!$J$12:$J$240
Name sexjo: 'COS in CO'!#REF!
Name sexjo: #REF!
Name sexjo: 'JO inventory'!$G$9:$G$64
Name sexjo18: '[2]JO inventory'!$G$9:$G$66
Name sexlevel: 'JO inventory'!#REF!

Sheet RatPlan Strat
A1: PLANTILLA OF PERSONNEL
A2: as of August 5, 2010
A3: LIST OF VACANT POSITIONS
A5: DEPARTMENT: Department of the Interior and Local Government, CORDILLERA ADMINISTRATIVE REGION
A6: ITEM NUMBER | B6: Plantilla location (1998) | C6: POSITION TITLE | D6: S G | E6: A N N U A L S A L A R Y | H6: STEP | I6: A R E A | L6: P/P/A/ ATTRI-BUTION | U6: I N C U M B E N T | V6: GENDER | W6: DATE OF BIRTH | Y6: Tax Identification Number (TIN) | AA6: DATE OF ORIGINAL APPT | AB6: DATE OF LAST PROMO-TION | AC6: STATUS | AD6: ELIGIBILITY | AE6: REMARK | AM6: ITEM NUMBER | AN6: NEW POSITION TITLE | AO6: S G | AP6: STEP | AR6: I N C U M B E N T
A7: E X I S T I N G | AL7: DBM ACTION | AM7: A P P R O V E D | AT7: OPTION | AU7: QUALIFICATION STANDARDS | AY7: PERSONNEL ACTION
A8: ITEM NUMBER | B8: Plantilla location (1998) | C8: POSITION TITLE | D8: S G | E8: A U T H O - R I Z E D | F8: A C T U A L | G8: a c t u a l (dec 31, '07) | H8: STEP | I8: CODE | J8: TYPE | K8: LEVEL | L8: P/P/A/ ATTRI-BUTION | M8: Present Station of Incumbent | T8: Monthly Salary (6/29/10) | U8: I N C U M B E N T | X8: age | Z8: date of tranfer to DILG | AM8: POSITION TITLE | AN8: NEW POSITION TITLE | AO8: S G | AP8: STEP | AQ8: Monthly Salary (6/29/10) | AR8: I N C U M B E N T | AS8: I N C U M B E N T | AU8: EDUCATION | AV8: EXPERIENCE | AW8: TRAINING | AX8: ELIGIBILITY
A9: 1 | C9: 2 | E9: 3 | F9: 4 | H9: 5 | I9: 6 | J9: 7 | K9: 8 | L9: 9 | U9: 10 | V9: 11 | W9: 12 | Y9: 13 | AA9: 14 | AB9: 15 | AC9: 16 | AD9: 17 | AH9: 2ND TRANCHE | AP9: 5 | AR9: 10
A10: Office of the Regional Director | B10: . | AF10: authorized | AG10: previous | AH10: new | AI10: as dec 31 | AJ10: difference | AL10: Office of the Regional Director
A11: OSEC-DILGB-DIR 4-18-1998 | B11: Regional Office | C11: Director IV | D11: 28 | E11: =AF11*12 -> 582948 | F11: =+AH11*12 -> 610092 | G11: 346262 | H11: 4 | I11: 011 | J11: R | K11: K | L11: A.03.a.01.c | M11: Regional Office | N11: ONUS | O11: Patrick | P11: =UPPER(O11) -> PATRICK | R11: D | S11: =P11&" "&R11&"."&" "&N11&" "&Q11 -> PATRICK D. ONUS | T11: 50841 | U11: ONUS, Patrick Damoking | V11: M | W11: 16644 | X11: =(NOW()-W11) -> 29461.538 | Y11: 127-933-059 | AA11: 25345 | AB11: 39398 | AC11: P | AD11: CESO IV | AF11: 48579 | AG11: 41291 | AH11: 50841 | AJ11: =AH11-AG11 -> 9550 | AL11: Retained | AM11: OSEC-DILGB-DIR 4-18-1998 | AN11: Director IV | AO11: 28 | AP11: 4 | AQ11: 50841 | AR11: ONUS, Patrick Damoking | AS11: =IF(AR11="(Vacant)",AR11,IF(AR11="",AR11,"With Incumbent")) -> With Incumbent
A12: OSEC-DILGB-DIR 3-4-1998 | B12: Regional Office | C12: Director III | D12: 27 | E12: =AF12*12 -> 546060 | F12: =+AH12*12 -> 608088 | G12: =29878*12 -> 358536 | H12: 8 | I12: 011 | J12: R | K12: K | L12: A.03.a.01.c | M12: Regional Office | N12: MANGANGEY | O12: Robert | P12: =UPPER(O12) -> ROBERT | Q12: Sr. | R12: L | S12: =P12&" "&R12&"."&" "&N12&" "&Q12 -> ROBERT L. MANGANGEY Sr. | T12: =608088/12 -> 50674 | U12: MANGANGEY, Robert Sr. Loyosen | V12: M | W12: 16870 | X12: =(NOW()-W12) -> 29235.538 | Y12: 127-934-019 | Z12: 27204 | AA12: 27204 | AB12: 39979 | AC12: P | AD12: CESO IV | AF12: 45505 | AG12: =506172/12 -> 42181 | AH12: =608088/12 -> 50674 | AJ12: =AH12-AG12 -> 8493 | AL12: Retained | AM12: OSEC-DILGB-DIR 3-4-1998 | AN12: Director III | AO12: 27 | AP12: 8 | AQ12: =608088/12 -> 50674 | AR12: MANGANGEY, Robert Sr. Loyosen | AS12: =IF(AR12="(Vacant)",AR12,IF(AR12="",AR12,"With Incumbent")) -> With Incumbent
A13: OSEC-DILGB-ATTY 4-9-1998 | B13: Regional Office | C13: Attorney IV | D13: 23 | E13: =AF13*12 -> 421728 | F13: =+AH13*12 -> 442140 | G13: 277668 | H13: 4 | I13: 011 | J13: R | K13: S | L13: A.03.a.01.c | M13: Regional Office | N13: KIWANG | O13: Tomas | P13: =UPPER(O13) -> TOMAS | Q13: Jr. | R13: A | S13: =P13&" "&R13&"."&" "&N13&" "&Q13 -> TOMAS A. KIWANG Jr. | T13: 36845 | U13: KIWANG, Tomas Jr. Amindalan | V13: M | W13: 26444 | X13: =(NOW()-W13) -> 19661.538 | Y13: 166-271-358 | Z13: 35916 | AA13: 35262 | AB13: 37039 | AC13: P | AD13: RA 1080 | AF13: 35144 | AG13: 31467 | AH13: 36845 | AJ13: =AH13-AG13 -> 5378 | AL13: Retained | AM13: OSEC-DILGB-ATTY 4-9-1998 | AN13: Attorney IV | AO13: 23 | AP13: 4 | AQ13: 36845 | AR13: KIWANG, Tomas Jr. Amindalan | AS13: =IF(AR13="(Vacant)",AR13,IF(AR13="",AR13,"With Incumbent")) -> With Incumbent
AL14: New Position | AM14: New | AN14: Planning Officer III | AO14: 18 | AP14: 1 | AQ14: 25259 | AR14: (Vacant) | AS14: =IF(AR14="(Vacant)",AR14,IF(AR14="",AR14,"With Incumbent")) -> (Vacant) | AU14: Bachelor' Degree Relevant ot the Job | AV14: 2 years of Relevant Experience | AW14: 8 Hours of Relevant Training | AX14: CSP / Second Level Eligibility | AY14: FOR ASSESSMENT
AL15: New Position | AM15: New | AN15: Information Technology Officer I | AO15: 19 | AP15: 1 | AQ15: 27088 | AR15: (Vacant) | AS15: =IF(AR15="(Vacant)",AR15,IF(AR15="",AR15,"With Incumbent")) -> (Vacant) | AU15: Bachelor' Degree Relevant ot the Job | AV15: 2 years of Relevant Experience | AW15: 8 Hours of Relevant Training | AX15: CSP / Second Level Eligibility | AY15: FOR ASSESSMENT
A16: OSEC-DILGB-ADOF4-69-2005 | B16: Regional Office | C16: Administrative Officer IV (Information Officer II) | D16: 15 | E16: =AF16*12 -> 245880 | F16: =+AH16*12 -> 254064 | G16: 179940 | H16: 3 | I16: 011 | J16: R | K16: A | L16: A.03.a.01.c | M16: Regional Office | N16: RIMANDO | O16: Marie Cris | P16: =UPPER(O16) -> MARIE CRIS | R16: L | S16: =P16&" "&R16&"."&" "&N16&" "&Q16 -> MARIE CRIS L. RIMANDO | T16: 21172 | U16: RIMANDO, Marie Cris Lim | V16: F | W16: 24278 | X16: =(NOW()-W16) -> 21827.538 | Y16: 129-983-169 | AA16: 36374 | AB16: 37809 | AC16: P | AD16: CSP | AF16: 20490 | AG16: 19040 | AH16: 21172 | AJ16: =AH16-AG16 -> 2132 | AL16: To FAD (1)
A17: OSEC-DILGB-COMPRO2-9-1998 | B17: Regional Office | C17: Computer Programmer II | D17: 15 | E17: =AF17*12 -> 245880 | F17: =+AH17*12 -> 254064 | G17: 179940 | H17: 3 | I17: 011 | J17: R | K17: S | L17: A.03.a.01.c | M17: Regional Office | N17: WALANG | O17: Marlon | P17: =UPPER(O17) -> MARLON | R17: S | S17: =P17&" "&R17&"."&" "&N17&" "&Q17 -> MARLON S. WALANG | T17: 21172 | U17: WALANG, Marlon Silvada | V17: M | W17: 27738 | X17: =(NOW()-W17) -> 18367.538 | Y17: 190-830-006 | AA17: 36461 | AB17: 37355 | AC17: P | AD17: RA 1080 | AF17: 20490 | AG17: 19040 | AH17: 21172 | AJ17: =AH17-AG17 -> 2132 | AL17: To MED/Reclass (2)
A18: OSEC-DILGB-ADAS3-64-2005 | B18: Regional Office | C18: Administrative Assistant III (Secretary II) | D18: 9 | E18: =AF18*12 -> 163956 | F18: =+AH18*12 -> 172080 | G18: 132468 | H18: 4 | I18: 011 | J18: R | K18: A | L18: A.03.a.01.c | M18: Regional Office | N18: DAOAS | O18: Marian | P18: =UPPER(O18) -> MARIAN | R18: B | S18: =P18&" "&R18&"."&" "&N18&" "&Q18 -> MARIAN B. DAOAS | T18: 14340 | U18: DAOAS, Marian Bigsang | V18: F | W18: 23697 | X18: =(NOW()-W18) -> 22408.538 | Y18: 185-738-006 | AA18: 35037 | AB18: 36069 | AC18: P | AD18: CSP | AF18: 13663 | AG18: 13242 | AH18: 14340 | AJ18: =AH18-AG18 -> 1098 | AL18: Retained | AM18: OSEC-DILGB-ADAS3-64-2005 | AN18: Administrative Assistant III (Secretary II) | AO18: 9 | AP18: 4 | AQ18: 14340 | AR18: DAOAS, Marian Bigsang | AS18: =IF(AR18="(Vacant)",AR18,IF(AR18="",AR18,"With Incumbent")) -> With Incumbent
A19: OSEC-DILGB-ADA6-92-2005 | B19: Regional Office | C19: Administrative Aide VI (CEO II) | D19: 6 | E19: =AF19*12 -> 132744 | F19: =+AH19*12 -> 148764 | G19: 116436 | H19: 8 | I19: 011 | J19: R | K19: A | L19: A.03.a.01.c | M19: Regional Office | N19: GONZALES | O19: Marlene | P19: =UPPER(O19) -> MARLENE | R19: C | S19: =P19&" "&R19&"."&" "&N19&" "&Q19 -> MARLENE C. GONZALES | T19: 12397 | U19: GONZALES, Marlene Castro | V19: F | W19: 25348 | X19: =(NOW()-W19) -> 20757.538 | Y19: 127-933-034 | AA19: 32672 | AB19: 32672 | AC19: P | AD19: RES 435 | AF19: 11062 | AG19: 11669 | AH19: 12397 | AJ19: =AH19-AG19 -> 728 | AL19: Abolished | AT19: Remain in the Service | AY19: to ADA6-95 PO
A20: OSEC-DILGB-ADA6-93-2005 | B20: Regional Office | C20: Administrative Aide VI (Steno II) | D20: 6 | E20: =AF20*12 -> 132744 | F20: =+AH20*12 -> 132744 | G20: vacant | H20: 1 | I20: 011 | J20: R | K20: A | L20: A.03.a.01.c | P20: =UPPER(O20) | S20: =P20&" "&R20&"."&" "&N20&" "&Q20 -> . | T20: 11062 | U20: (Vacant) | AF20: 11062 | AG20: 10133 | AH20: 11062 | AJ20: =AH20-AG20 -> 929 | AL20: Abolished
A21: OSEC-DILGB-ADA4-83-2005 | B21: Regional Office | C21: Administrative Aide IV (Driver II) | D21: 4 | E21: =AF21*12 -> 114432 | F21: =+AH21*12 -> 120096 | G21: 90432 | H21: 4 | I21: 011 | J21: R | K21: A | L21: A.03.a.01.c | M21: Regional Office | N21: TICBAEN | O21: Mark Anthony | P21: =UPPER(O21) -> MARK ANTHONY | R21: D | S21: =P21&" "&R21&"."&" "&N21&" "&Q21 -> MARK ANTHONY D. TICBAEN | T21: 10008 | U21: TICBAEN, Mark Anthony Duquil | V21: M | W21: 27822 | X21: =(NOW()-W21) -> 18283.538 | Y21: 914-805-353 | AA21: 36168 | AB21: 36168 | AC21: P | AD21: MC 11 | AF21: 9536 | AG21: 9252 | AH21: 10008 | AJ21: =AH21-AG21 -> 756 | AL21: Retained | AM21: OSEC-DILGB-ADA4-83-2005 | AN21: Administrative Aide IV (Driver II) | AO21: 4 | AP21: 4 | AQ21: 10008 | AR21: TICBAEN, Mark Anthony Duquil | AS21: =IF(AR21="(Vacant)",AR21,IF(AR21="",AR21,"With Incumbent")) -> With Incumbent
A22: OSEC-DILGB-ADA3-61-2005 | B22: Regional Office | C22: Administrative Aide III (Driver I) | D22: 3 | E22: =AF22*12 -> 106248 | F22: =+AH22*12 -> 111504 | G22: 85836 | H22: 4 | I22: 011 | J22: R | K22: A | L22: A.03.a.01.c | M22: Regional Office | N22: TAMONDONG | O22: Jonathan | P22: =UPPER(O22) -> JONATHAN | R22: A | S22: =P22&" "&R22&"."&" "&N22&" "&Q22 -> JONATHAN A. TAMONDONG | T22: 9292 | U22: TAMONDONG, Jonathan Ambat | V22: M | W22: 24419 | X22: =(NOW()-W22) -> 21686.538 | Y22: 175-568-367 | AA22: 34808 | AB22: 36054 | AC22: P | AD22: MC 11 | AF22: 8854 | AG22: 8580 | AH22: 9292 | AJ22: =AH22-AG22 -> 712 | AL22: To FAD / Retained(3)
A23: Sub-Total | D23: =COUNTIF(D11:D22,">.01") -> 10 | AM23: Sub-Total | AO23: =COUNTIF(AO11:AO22,">.01") -> 7 | AR23: =COUNTIF(AR11:AR22,">.01") -> 0
A24: 62,000000000 Technical Services Division | AL24: Capability Development Division
A25: OSEC-DILGB-LGOO7-37-1998 | B25: Regional Office | C25: Local Government Operations Officer VII | D25: 24 | E25: =AF25*12 -> 449676 | F25: =+AH25*12 -> 449676 | G25: 274860 | H25: 1 | I25: 011 | J25: P | K25: K | L25: A.03.a.01.c | M25: Regional Office | N25: DUMELOD | O25: Rosario | P25: =UPPER(O25) -> ROSARIO | R25: B | S25: =P25&" "&R25&"."&" "&N25&" "&Q25 -> ROSARIO B. DUMELOD | T25: 37473 | U25: DUMELOD, Rosario BUMINAANG | V25: F | W25: 23285 | X25: =(NOW()-W25) -> 22820.538 | Y25: 127-934-454 | AA25: 32687 | AB25: 40261 | AC25: P | AD25: CSP | AF25: 37473 | AG25: 31334 | AH25: 37473 | AJ25: =AH25-AG25 -> 6139 | AL25: Retained | AM25: OSEC-DILGB-LGOO7-37-1998 | AN25: Local Government Operations Officer VII | AO25: 24 | AP25: 1 | AQ25: 37473 | AR25: DUMELOD, Rosario BUMINAANG | AS25: =IF(AR25="(Vacant)",AR25,IF(AR25="",AR25,"With Incumbent")) -> With Incumbent
A26: OSEC-DILGB-LGOO6-12-1998 | B26: Regional Office | C26: Local Government Operations Officer VI | D26: 22 | E26: =AF26*12 -> 395676 | F26: =+AH26*12 -> 395676 | G26: vacant | H26: 1 | I26: 011 | J26: R | K26: T | L26: A.03.a.01.c | M26: Regional Office | N26: CLAUDIO | O26: Ofelia | P26: =UPPER(O26) -> OFELIA | R26: O | S26: =P26&" "&R26&"."&" "&N26&" "&Q26 -> OFELIA O. CLAUDIO | T26: 32973 | U26: CLAUDIO, Ofelia Linggon | V26: F | W26: 21997 | X26: =(NOW()-W26) -> 24108.538 | Y26: 127-934-210 | AA26: 32687 | AB26: 39510 | AC26: P | AD26: CSP | AF26: 32973 | AG26: 28134 | AH26: 32973 | AJ26: =AH26-AG26 -> 4839 | AL26: Retained | AM26: OSEC-DILGB-LGOO6-12-1998 | AN26: Local Government Operations Officer VI | AO26: 22 | AP26: 1 | AQ26: 32973 | AR26: CLAUDIO, Ofelia Linggon | AS26: =IF(AR26="(Vacant)",AR26,IF(AR26="",AR26,"With Incumbent")) -> With Incumbent
A27: OSEC-DILGB-LGOO5-791-1998 | B27: Regional Office | C27: Local Government Operations Officer V | D27: 20 | E27: =AF27*12 -> 348624 | F27: =+AH27*12 -> 360012 | G27: 240816 | H27: 3 | I27: 0540 | J27: M | K27: T | L27: A.03.a.01.c | M27: Benguet | N27: BALLUG | O27: Rene Vincent | P27: =UPPER(O27) -> RENE VINCENT | R27: I | S27: =P27&" "&R27&"."&" "&N27&" "&Q27 -> RENE VINCENT I. BALLUG | T27: 30001 | U27: BALLUG, Rene Vincent Ilacad | V27: M | W27: 25501 | X27: =(NOW()-W27) -> 20604.538 | Y27: 185-969-809 | AA27: 35487 | AB27: 37561 | AC27: P | AD27: CSP | AF27: 29052 | AG27: 26314 | AH27: 30001 | AJ27: =AH27-AG27 -> 3687 | AL27: Retained | AM27: OSEC-DILGB-LGOO5-791-1998 | AN27: Local Government Operations Officer V | AO27: 20 | AP27: 3 | AQ27: 30001 | AR27: BALLUG, Rene Vincent Ilacad | AS27: =IF(AR27="(Vacant)",AR27,IF(AR27="",AR27,"With Incumbent")) -> With Incumbent
A28: OSEC-DILGB-LGOO5-802-1998 | B28: Regional Office | C28: Local Government Operations Officer V | D28: 20 | E28: =AF28*12 -> 348624 | F28: =+AH28*12 -> 354264 | G28: 240816 | H28: 2 | I28: 011 | J28: R | K28: T | L28: A.03.a.01.c | M28: Ifugao | N28: CORTEZ | O28: Melchor Anthony | P28: =UPPER(O28) -> MELCHOR ANTHONY | R28: G | S28: =P28&" "&R28&"."&" "&N28&" "&Q28 -> MELCHOR ANTHONY G. CORTEZ | T28: 29522 | U28: CORTEZ, Melchor Anthony Guimbatan | V28: M | W28: 25574 | X28: =(NOW()-W28) -> 20531.538 | Y28: 173-594-522 | AA28: 35100 | AB28: 38322 | AC28: P | AD28: CSP | AF28: 29052 | AG28: 25799 | AH28: 29522 | AJ28: =AH28-AG28 -> 3723 | AL28: Retained | AM28: OSEC-DILGB-LGOO5-802-1998 | AN28: Local Government Operations Officer V | AO28: 20 | AP28: 2 | AQ28: 29522 | AR28: CORTEZ, Melchor Anthony Guimbatan | AS28: =IF(AR28="(Vacant)",AR28,IF(AR28="",AR28,"With Incumbent")) -> With Incumbent
A29: OSEC-DILGB-LGOO5-813-1998 | B29: Regional Office | C29: Local Government Operations Officer V | D29: 20 | E29: =AF29*12 -> 348624 | F29: =+AH29*12 -> 348624 | G29: vacant | H29: 1 | I29: 011 | J29: R | K29: T | L29: A.03.a.01.c | M29: Apayao | N29: CENU | O29: Merina | P29: =UPPER(O29) -> MERINA | R29: B | S29: =P29&" "&R29&"."&" "&N29&" "&Q29 -> MERINA B. CENU | T29: 29052 | U29: CENU. Merina Bagasol | V29: F | W29: 28132 | X29: =(NOW()-W29) -> 17973.538 | Y29: 905-486-436 | AA29: 36299 | AB29: 39510 | AC29: P | AD29: CSP | AF29: 29052 | AG29: 25295 | AH29: 29052 | AJ29: =AH29-AG29 -> 3757 | AL29: Retained | AM29: OSEC-DILGB-LGOO5-813-1998 | AN29: Local Government Operations Officer V | AO29: 20 | AP29: 1 | AQ29: 29052 | AR29: CENU. Merina Bagasol | AS29: =IF(AR29="(Vacant)",AR29,IF(AR29="",AR29,"With Incumbent")) -> With Incumbent
A30: OSEC-DILGB-LGOO4-160-1998 | B30: Regional Office | C30: Local Government Operations Officer IV | D30: 18 | E30: =AF30*12 -> 303108 | F30: =+AH30*12 -> 313092 | G30: 219684 | H30: 3 | I30: 0537 | J30: M | K30: T | L30: A.03.a.01.c | M30: Baguio City | N30: MALIG | O30: Julie | P30: =UPPER(O30) -> JULIE | R30: C | S30: =P30&" "&R30&"."&" "&N30&" "&Q30 -> JULIE C. MALIG | T30: 26091 | U30: MALIG, Julie Capiato | V30: F | W30: 25394 | X30: =(NOW()-W30) -> 20711.538 | Y30: 154-221-422 | AA30: 35107 | AB30: 37235 | AC30: P | AD30: CSP | AF30: 25259 | AG30: 23115 | AH30: 26091 | AJ30: =AH30-AG30 -> 2976 | AL30: To PO/Reclass
A31: OSEC-DILGB-LGOO4-161-1998 | B31: Regional Office | C31: Local Government Operations Officer IV | D31: 18 | E31: =AF31*12 -> 303108 | F31: =+AH31*12 -> 303108 | G31: vacant | H31: 1 | I31: 06 | J31: R | K31: A | L31: A.03.a.01.c | M31: Regional Office | N31: CAWIS | O31: Odemar | P31: =UPPER(O31) -> ODEMAR | R31: M | S31: =P31&" "&R31&"."&" "&N31&" "&Q31 -> ODEMAR M. CAWIS | T31: 25259 | U31: CAWIS, Odemar Mendoza | V31: M | W31: 25761 | X31: =(NOW()-W31) -> 20344.538 | Y31: 144-070234 | AA31: 36434 | AB31: 40262 | AC31: P | AD31: CSP | AF31: 25259 | AG31: 22214 | AH31: 25259 | AJ31: =AH31-AG31 -> 3045 | AL31: Retained | AM31: OSEC-DILGB-LGOO4-161-1998 | AN31: Local Government Operations Officer IV | AO31: 18 | AP31: 1 | AQ31: 25259 | AR31: CAWIS, Odemar Mendoza | AS31: =IF(AR31="(Vacant)",AR31,IF(AR31="",AR31,"With Incumbent")) -> With Incumbent
A32: OSEC-DILGB-LGOO4-162-1998 | B32: Regional Office | C32: Local Government Operations Officer IV | D32: 18 | E32: =AF32*12 -> 303108 | F32: =+AH32*12 -> 303108 | G32: 214332 | H32: 1 | I32: 011 | J32: R | K32: A | L32: A.03.a.01.c | S32: Vacant PALENG, Mory D. | T32: 25259 | U32: (Vacant) | AF32: 25259 | AG32: 22214 | AH32: 25259 | AJ32: =AH32-AG32 -> 3045 | AL32: To PO/Reclass
A33: OSEC-DILGB-LGOO4-164-1998 | B33: Regional Office | C33: Local Government Operations Officer IV | D33: 18 | E33: =AF33*12 -> 303108 | F33: =+AH33*12 -> 303108 | G33: 214332 | H33: 1 | I33: 011 | J33: R | K33: A | L33: A.03.a.01.c | M33: Regional Office | N33: GARCIA | O33: Florinda | P33: =UPPER(O33) -> FLORINDA | R33: M | S33: =P33&" "&R33&"."&" "&N33&" "&Q33 -> FLORINDA M. GARCIA | T33: 25259 | U33: GARCIA, Florinda Manuyag | V33: F | W33: 22504 | X33: =(NOW()-W33) -> 23601.538 | Y33: 122-174-963 | AA33: 36100 | AB33: 40262 | AC33: P | AD33: CSP | AF33: 25259 | AG33: 22214 | AH33: 25259 | AJ33: =AH33-AG33 -> 3045 | AL33: Retained | AM33: OSEC-DILGB-LGOO4-164-1998 | AN33: Local Government Operations Officer IV | AO33: 18 | AP33: 1 | AQ33: 25259 | AR33: GARCIA, Florinda Manuyag | AS33: =IF(AR33="(Vacant)",AR33,IF(AR33="",AR33,"With Incumbent")) -> With Incumbent
A34: OSEC-DILGB-ADAS1-24-2005 | B34: Regional Office | C34: Administrative Assistant I (CO I) | D34: 7 | E34: =AF34*12 -> 130296 | F34: =+AH34*12 -> 142428 | G34: vacant | H34: 1 | I34: 011 | J34: R | K34: A | L34: A.03.a.01.c | P34: =UPPER(O34) | S34: =P34&" "&R34&"."&" "&N34&" "&Q34 -> . | T34: 11869 | U34: (Vacant) | AF34: 10858 | AG34: 10858 | AH34: 11869 | AJ34: =AH34-AG34 -> 1011 | AL34: Abolished
E35: =AF35*12 -> 132744 | F35: =+AH35*12 -> 137100 | G35: 102912 | I35: 011 | J35: R | K35: A | L35: A.03.a.01.c | M35: Kalinga | N35: MAGO | O35: Carmelita | P35: =UPPER(O35) -> CARMELITA | R35: C | S35: =P35&" "&R35&"."&" "&N35&" "&Q35 -> CARMELITA C. MAGO | V35: F | W35: 20401 | X35: =(NOW()-W35) -> 25704.538 | Y35: 127-934-872 | AA35: 30769 | AB35: 37288 | AC35: P | AD35: CSSP | AF35: 11062 | AG35: 10548 | AH35: 11425 | AJ35: =AH35-AG35 -> 877 | AL35: Retained Fr FAD 4 | AM35: OSEC-DILGB-ADA6-97-2005 | AN35: Administrative Aide VI (Clerk III) | AO35: 6 | AP35: 3 | AQ35: 11425 | AR35: MAGO, Carmelita Cenabre | AS35: =IF(AR35="(Vacant)",AR35,IF(AR35="",AR35,"With Incumbent")) -> With Incumbent
A36: Sub-Total | D36: =COUNTIF(D25:D35,">.01") -> 10 | AM36: Sub-Total | AO36: =COUNTIF(AO25:AO35,">.01") -> 8
A37: 63,000000000 Operations Division | AL37: Monitoring and Evaluation Division
A38: OSEC-DILGB-LGOO7-38-1998 | B38: Regional Office | C38: Local Government Operations Officer VII | D38: 24 | E38: =AF38*12 -> 449676 | F38: =+AH38*12 -> 449676 | G38: vacant | H38: 1 | I38: 08 | J38: P | K38: K | L38: A.03.a.01.c | M38: Regional Office | N38: MADARIAGA | O38: Benjamin | P38: =UPPER(O38) -> BENJAMIN | R38: A | S38: =P38&" "&R38&"."&" "&N38&" "&Q38 -> BENJAMIN A. MADARIAGA | T38: 37473 | U38: MADARIAGA, Benjamin Acio | V38: M | W38: 16816 | X38: =(NOW()-W38) -> 29289.538 | Y38: 135-562-718 | AA38: 25520 | AB38: 39525 | AC38: P | AD38: CDO | AF38: 37473 | AG38: 31334 | AH38: 37473 | AJ38: =AH38-AG38 -> 6139 | AL38: Retained | AM38: OSEC-DILGB-LGOO7-38-1998 | AN38: Local Government Operations Officer VII | AO38: 24 | AP38: 1 | AQ38: 37473 | AR38: MADARIAGA, Benjamin Acio | AS38: =IF(AR38="(Vacant)",AR38,IF(AR38="",AR38,"With Incumbent")) -> With Incumbent
A39: OSEC-DILGB-LGOO6-14-1998 | B39: Regional Office | C39: Local Government Operations Officer VI | D39: 22 | E39: =23294*12 -> 279528 | F39: =+AH39*12 -> 395676 | G39: 260460 | H39: 1 | I39: 011 | J39: R | K39: T | L39: A.03.a.01.c | M39: Regional Office | N39: ADNOL | O39: Bable | P39: =UPPER(O39) -> BABLE | R39: G | S39: =P39&" "&R39&"."&" "&N39&" "&Q39 -> BABLE G. ADNOL | T39: 32973 | U39: ADNOL, Bable Ged-ang | V39: F | W39: 25374 | X39: =(NOW()-W39) -> 20731.538 | Y39: 185-743-190 | AA39: 34808 | AB39: 40262 | AC39: P | AD39: CSP | AF39: 32973 | AG39: 28134 | AH39: 32973 | AJ39: =AH39-AG39 -> 4839 | AL39: Retained | AM39: OSEC-DILGB-LGOO6-14-1998 | AN39: Local Government Operations Officer VI | AO39: 22 | AP39: 1 | AQ39: 32973 | AR39: ADNOL, Bable Ged-ang | AS39: =IF(AR39="(Vacant)",AR39,IF(AR39="",AR39,"With Incumbent")) -> With Incumbent
A40: OSEC-DILGB-LGOO5-824-1998 | B40: Regional Office | C40: Local Government Operations Officer V | D40: 20 | E40: =21537*12 -> 258444 | F40: =+AH40*12 -> 348624 | G40: 253020 | H40: 1 | I40: 011 | J40: R | K40: T | L40: A.03.a.01.c | M40: Apayao | N40: ACERET | O40: Wilnelia | P40: =UPPER(O40) -> WILNELIA | R40: M | S40: =P40&" "&R40&"."&" "&N40&" "&Q40 -> WILNELIA M. ACERET | T40: 29052 | U40: ACERET, Wilnelia Martinez | V40: F | W40: 28103 | X40: =(NOW()-W40) -> 18002.538 | Y40: 905-491-788 | AA40: 36024 | AB40: 39874 | AC40: P | AD40: CSP | AF40: 29052 | AG40: 25295 | AH40: 29052 | AJ40: =AH40-AG40 -> 3757 | AL40: Retained | AM40: OSEC-DILGB-LGOO5-824-1998 | AN40: Local Government Operations Officer V | AO40: 20 | AP40: 1 | AQ40: 29052 | AR40: ACERET, Wilnelia Martinez | AS40: =IF(AR40="(Vacant)",AR40,IF(AR40="",AR40,"With Incumbent")) -> With Incumbent
A41: OSEC-DILGB-LGOO5-835-1998 | B41: Regional Office | C41: Local Government Operations Officer V | D41: 20 | E41: =AF41*12 -> 348624 | F41: =+AH41*12 -> 360012 | G41: 240816 | H41: 3 | I41: 011 | J41: R | K41: T | L41: A.03.a.01.c | M41: Apayao | N41: BALDERAMA | O41: Antonio | P41: =UPPER(O41) -> ANTONIO | R41: C | S41: =P41&" "&R41&"."&" "&N41&" "&Q41 -> ANTONIO C. BALDERAMA | T41: 30001 | U41: BALDERAMA, Antonio Carbonel | V41: M | W41: 17986 | X41: =(NOW()-W41) -> 28119.538 | Y41: 127-934-972 | Z41: 31371 | AA41: 25385 | AB41: 37987 | AC41: P | AD41: CSP | AF41: 29052 | AG41: 26314 | AH41: 30001 | AJ41: =AH41-AG41 -> 3687 | AL41: Retained | AM41: OSEC-DILGB-LGOO5-835-1998 | AN41: Local Government Operations Officer V | AO41: 20 | AP41: 3 | AQ41: 30001 | AR41: BALDERAMA, Antonio Carbonel | AS41: =IF(AR41="(Vacant)",AR41,IF(AR41="",AR41,"With Incumbent")) -> With Incumbent
A42: OSEC-DILGB-LGOO4-165-1998 | B42: Regional Office | C42: Local Government Operations Officer IV | D42: 18 | E42: =AF42*12 -> 303108 | F42: =+AH42*12 -> 303108 | G42: vacant | H42: 1 | I42: 011 | J42: R | K42: T | L42: A.03.a.01.c | P42: =UPPER(O42) | S42: =P42&" "&R42&"."&" "&N42&" "&Q42 -> . | T42: 25259 | U42: (Vacant) | AF42: 25259 | AG42: 22214 | AH42: 25259 | AJ42: =AH42-AG42 -> 3045 | AL42: Reclass | AM42: OSEC-DILGB-LGOO4-165-1998 | AN42: Local Government Operations Officer V | AO42: 20 | AP42: 1 | AQ42: 29052 | AR42: (Vacant) | AS42: =IF(AR42="(Vacant)",AR42,IF(AR42="",AR42,"With Incumbent")) -> (Vacant) | AU42: Bachelor' Degree | AV42: 2 years of Relevant Experience | AW42: Completion of Training Course for LGOOs | AX42: CSP / Second Level Eligibility | AY42: FOR ASSESSMENT
A43: OSEC-DILGB-LGOO4-166-1998 | B43: Regional Office | C43: Local Government Operations Officer IV | D43: 18 | E43: =AF43*12 -> 303108 | F43: =+AH43*12 -> 303108 | G43: vacant | H43: 1 | I43: 011 | J43: R | K43: T | L43: A.03.a.01.c | M43: Regional Office | N43: GRIBA | O43: Mary Ann | P43: =UPPER(O43) -> MARY ANN | R43: J | S43: =P43&" "&R43&"."&" "&N43&" "&Q43 -> MARY ANN J. GRIBA | T43: 25259 | U43: GRIBA, Mary Ann Javier | V43: F | W43: 25230 | X43: =(NOW()-W43) -> 20875.538 | Y43: 106-630-476 | AA43: 36074 | AB43: 40262 | AC43: P | AD43: CSP | AF43: 25259 | AG43: 22214 | AH43: 25259 | AJ43: =AH43-AG43 -> 3045 | AL43: Retained | AM43: OSEC-DILGB-LGOO4-166-1998 | AN43: Local Government Operations Officer IV | AO43: 18 | AP43: 1 | AQ43: 25259 | AR43: GRIBA, Mary Ann Javier | AS43: =IF(AR43="(Vacant)",AR43,IF(AR43="",AR43,"With Incumbent")) -> With Incumbent
A44: OSEC-DILGB-LGOO4-167-1998 | B44: Regional Office | C44: Local Government Operations Officer IV | D44: 18 | E44: =AF44*12 -> 303108 | F44: =+AH44*12 -> 303108 | G44: vacant | H44: 1 | I44: 011 | J44: R | K44: T | L44: A.03.a.01.c | M44: Regional Office | N44: CARDENAS | O44: Cheryl Rose | P44: =UPPER(O44) -> CHERYL ROSE | R44: F | S44: =P44&" "&R44&"."&" "&N44&" "&Q44 -> CHERYL ROSE F. CARDENAS | T44: 25259 | U44: CARDENAS, Cheryl Rose Flores | V44: F | W44: 22338 | X44: =(NOW()-W44) -> 23767.538 | Y44: 129-990-193 | Z44: 35096 | AA44: 31719 | AB44: 40262 | AC44: P | AD44: CSP | AF44: 25259 | AG44: 22214 | AH44: 25259 | AJ44: =AH44-AG44 -> 3045 | AL44: Retained | AM44: OSEC-DILGB-LGOO4-167-1998 | AN44: Local Government Operations Officer IV | AO44: 18 | AP44: 1 | AQ44: 25259 | AR44: CARDENAS, Cheryl Rose Flores | AS44: =IF(AR44="(Vacant)",AR44,IF(AR44="",AR44,"With Incumbent")) -> With Incumbent
A45: OSEC-DILGB-LGOO4-168-1998 | B45: Regional Office | C45: Local Government Operations Officer IV | D45: 18 | E45: =AF45*12 -> 303108 | F45: =+AH45*12 -> 303108 | G45: vacant | H45: 1 | I45: 0666 | J45: M | K45: T | L45: A.03.a.01.c | P45: =UPPER(O45) | S45: =P45&" "&R45&"."&" "&N45&" "&Q45 -> . | T45: 25259 | U45: (Vacant) | AF45: 25259 | AG45: 22214 | AH45: 25259 | AJ45: =AH45-AG45 -> 3045 | AL45: Abolished
E46: =AF46*12 -> 245880 | F46: =+AH46*12 -> 254064 | G46: 179940 | I46: 011 | J46: R | K46: S | L46: A.03.a.01.c | M46: Regional Office | N46: WALANG | O46: Marlon | P46: =UPPER(O46) -> MARLON | R46: S | S46: =P46&" "&R46&"."&" "&N46&" "&Q46 -> MARLON S. WALANG | V46: M | W46: 27738 | X46: =(NOW()-W46) -> 18367.538 | Y46: 190-830-006 | AA46: 36461 | AB46: 37355 | AC46: P | AD46: RA 1080 | AF46: 20490 | AG46: 19040 | AH46: 21172 | AJ46: =AH46-AG46 -> 2132 | AL46: Reclass/Fr. ORD 2 | AM46: OSEC-DILGB-COMPRO2-9-1998 | AN46: Statistician II | AO46: 15 | AP46: 3 | AQ46: 21172 | AR46: WALANG, Marlon Silvada | AS46: =IF(AR46="(Vacant)",AR46,IF(AR46="",AR46,"With Incumbent")) -> With Incumbent
A47: OSEC-DILGB-STAT1-3-1998 | B47: Regional Office | C47: Statistician I | D47: 11 | E47: =AF47*12 -> 187788 | F47: =+AH47*12 -> 187788 | G47: vacant | H47: 1 | I47: 011 | J47: R | K47: S | L47: A.03.a.01.c | P47: =UPPER(O47) | S47: =P47&" "&R47&"."&" "&N47&" "&Q47 -> . | T47: 15649 | U47: (Vacant) | AF47: 15649 | AG47: 14198 | AH47: 15649 | AJ47: =AH47-AG47 -> 1451 | AL47: Retained | AM47: OSEC-DILGB-STAT1-3-1998 | AN47: Statistician I | AO47: 11 | AP47: 1 | AQ47: 15649 | AR47: (Vacant) | AS47: =IF(AR47="(Vacant)",AR47,IF(AR47="",AR47,"With Incumbent")) -> (Vacant) | AU47: Bachelor' Degree Relevant ot the Job | AV47: None Required | AW47: None Required | AX47: CSP / Second Level Eligibility | AY47: FOR ASSESSMENT
A48: OSEC-DILGB-ADA4-84-2005 | B48: Regional Office | C48: Administrative Aide IV (Clerk II) | D48: 4 | E48: =AF48*12 -> 114432 | F48: =+AH48*12 -> 116280 | G48: 88224 | H48: 2 | I48: 011 | J48: R | K48: A | L48: A.03.a.01.c | M48: Mt. Province | N48: BASCO | O48: Raymundo Jacinto | P48: =UPPER(O48) -> RAYMUNDO JACINTO | R48: P | S48: =P48&" "&R48&"."&" "&N48&" "&Q48 -> RAYMUNDO JACINTO P. BASCO | T48: 9690 | U48: BASCO, Raymundo Jacinto Pandoyos | V48: M | W48: 28517 | X48: =(NOW()-W48) -> 17588.538 | Y48: 917-012-523 | AA48: 38231 | AB48: 38231 | AC48: P | AD48: CSP | AF48: 9536 | AG48: 8888 | AH48: 9690 | AJ48: =AH48-AG48 -> 802 | AL48: Reclass | AM48: OSEC-DILGB-ADA4-84-2005 | AN48: Administrative Aide VI | AO48: 6 | AP48: 1 | AQ48: 11062 | AR48: BASCO, Raymundo Jacinto Pandoyos | AS48: =IF(AR48="(Vacant)",AR48,IF(AR48="",AR48,"With Incumbent")) -> With Incumbent
A49: Sub-Total | D49: =COUNTIF(D38:D48,">.01") -> 10 | AM49: Sub-Total | AO49: =COUNTIF(AO38:AO48,">.01") -> 10
A50: 64,000000000 Administrative Services Division | AL50: Finance and Administrative Division
A51: OSEC-DILGB-CADOF-19-2005 | B51: Regional Office | C51: Chief Administrative Officer (AO V) | D51: 24 | E51: =AF51*12 -> 449676 | F51: =+AH51*12 -> 449676 | G51: vacant | H51: 1 | I51: 011 | J51: R | K51: K | L51: A.03.a.01.c | P51: =UPPER(O51) | S51: Capulong | T51: 37473 | U51: (Vacant) | AF51: 37473 | AG51: 31334 | AH51: 37473 | AJ51: =AH51-AG51 -> 6139 | AL51: Retained | AM51: OSEC-DILGB-CADOF-19-2005 | AN51: Chief Administrative Officer (AO V) | AO51: 24 | AP51: 1 | AQ51: 37473 | AR51: (Vacant) | AS51: =IF(AR51="(Vacant)",AR51,IF(AR51="",AR51,"With Incumbent")) -> (Vacant) | AU51: Masteral Degree | AV51: 4 years in position/s involving management and supervision | AW51: 24 hours of training in management and supervision | AX51: CSP / Second Level Eligibility | AY51: FOR ASSESSMENT
A52: OSEC-DILGB-SAD0F-34-2005 | B52: Regional Office | C52: Supervising Administrative Officer (AO IV) | D52: 22 | E52: =AF52*12 -> 395676 | F52: =+AH52*12 -> 408408 | G52: 260460 | H52: 3 | I52: 011 | J52: R | K52: K | L52: A.03.a.01.c | M52: Regional Office | N52: MON | O52: Shirley | P52: =UPPER(O52) -> SHIRLEY | R52: V | S52: =P52&" "&R52&"."&" "&N52&" "&Q52 -> SHIRLEY V. MON | T52: 34034 | U52: MON, Shirley Vergara | V52: F | W52: 23201 | X52: =(NOW()-W52) -> 22904.538 | Y52: 127-933-188 | Z52: 32629 | AA52: 31719 | AB52: 37834 | AC52: P | AD52: CSP | AF52: 32973 | AG52: 29254 | AH52: 34034 | AJ52: =AH52-AG52 -> 4780 | AL52: Retained | AM52: OSEC-DILGB-SAD0F-34-2005 | AN52: Supervising Administrative Officer (AO IV) | AO52: 22 | AP52: 3 | AQ52: 34034 | AR52: MON, Shirley Vergara | AS52: =IF(AR52="(Vacant)",AR52,IF(AR52="",AR52,"With Incumbent")) -> With Incumbent
A53: OSEC-DILGB-A3-16-1998 | B53: Regional Office | C53: Accountant III | D53: 19 | E53: =AF53*12 -> 325056 | F53: =+AH53*12 -> 325056 | G53: 219684 | H53: 1 | I53: 011 | J53: R | K53: S | L53: A.03.a.01.c | M53: Regional Office | N53: CHAOKAS | O53: Jennifer | P53: =UPPER(O53) -> JENNIFER | R53: S | S53: =P53&" "&R53&"."&" "&N53&" "&Q53 -> JENNIFER S. CHAOKAS | T53: 27088 | U53: CHAOKAS, Jeniifer Sokoken | V53: F | W53: 28334 | X53: =(NOW()-W53) -> 17771.538 | Y53: 919-344-911 | Z53: 40256 | AA53: 36955 | AB53: 40256 | AC53: P | AD53: CSP | AF53: 27088 | AG53: 23703 | AH53: 27088 | AJ53: =AH53-AG53 -> 3385 | AL53: Retained | AM53: OSEC-DILGB-A3-16-1998 | AN53: Accountant III | AO53: 19 | AP53: 1 | AQ53: 27088 | AR53: CHAOKAS, Jeniifer Sokoken | AS53: =IF(AR53="(Vacant)",AR53,IF(AR53="",AR53,"With Incumbent")) -> With Incumbent
A54: OSEC-DILGB-ADOF5-52-2005 | B54: Regional Office | C54: Administrative Officer V (AO III) | D54: 18 | E54: =AF54*12 -> 303108 | F54: =+AH54*12 -> 313092 | G54: 214332 | H54: 3 | I54: 011 | J54: R | K54: S | L54: A.03.a.01.c | M54: Regional Office | N54: BALANG | O54: Gerry | P54: =UPPER(O54) -> GERRY | R54: C | S54: =P54&" "&R54&"."&" "&N54&" "&Q54 -> GERRY C. BALANG | T54: 26091 | U54: BALANG, Gerry Cobcobo | V54: M | W54: 25301 | X54: =(NOW()-W54) -> 20804.538 | Y54: 196-011-963 | Z54: 36632 | AA54: 35515 | AB54: 37834 | AC54: P | AD54: CSP | AF54: 25259 | AG54: 23115 | AH54: 26091 | AJ54: =AH54-AG54 -> 2976 | AL54: Retained | AM54: OSEC-DILGB-ADOF5-52-2005 | AN54: Administrative Officer V (AO III) | AO54: 18 | AP54: 3 | AQ54: 26091 | AR54: BALANG, Gerry Cobcobo | AS54: =IF(AR54="(Vacant)",AR54,IF(AR54="",AR54,"With Incumbent")) -> With Incumbent
A55: OSEC-DILGB-ADOF5-53-2005 | B55: Regional Office | C55: Administrative Officer V (BO III) | D55: 18 | E55: =AF55*12 -> 303108 | F55: =+AH55*12 -> 313092 | G55: 214332 | H55: 3 | I55: 011 | J55: R | K55: A | L55: A.03.a.01.c | M55: Regional Office | N55: SAINGAN | O55: Evelyn | P55: =UPPER(O55) -> EVELYN | R55: M | S55: =P55&" "&R55&"."&" "&N55&" "&Q55 -> EVELYN M. SAINGAN | T55: 26091 | U55: SAINGAN, Evelyn Mensi | V55: F | W55: 23843 | X55: =(NOW()-W55) -> 22262.538 | Y55: 127-933-113 | AA55: 33233 | AB55: 37293 | AC55: P | AD55: CSP | AF55: 25259 | AG55: 23115 | AH55: 26091 | AJ55: =AH55-AG55 -> 2976 | AL55: Retained | AM55: OSEC-DILGB-ADOF5-53-2005 | AN55: Administrative Officer V (BO III) | AO55: 18 | AP55: 3 | AQ55: 26091 | AR55: SAINGAN, Evelyn Mensi | AS55: =IF(AR55="(Vacant)",AR55,IF(AR55="",AR55,"With Incumbent")) -> With Incumbent
A56: OSEC-DILGB-ADOF5-54-2005 | B56: Regional Office | C56: Administrative Officer V (HRMO III) | D56: 18 | E56: =AF56*12 -> 303108 | F56: =+AH56*12 -> 308052 | G56: 209100 | H56: 2 | I56: 011 | J56: R | K56: A | L56: A.03.a.01.c | M56: Regional Office | N56: BARNACHEA | O56: Norman | P56: =UPPER(O56) -> NORMAN | R56: I | S56: =P56&" "&R56&"."&" "&N56&" "&Q56 -> NORMAN I. BARNACHEA | T56: 25671 | U56: BARNACHEA, Norman Idica | V56: M | W56: 27936 | X56: =(NOW()-W56) -> 18169.538 | Y56: 927-988-540 | Z56: 37956 | AA56: 37375 | AB56: 38607 | AC56: P | AD56: CSP | AF56: 25259 | AG56: 22659 | AH56: 25671 | AJ56: =AH56-AG56 -> 3012 | AL56: Retained | AM56: OSEC-DILGB-ADOF5-54-2005 | AN56: Administrative Officer V (HRMO III) | AO56: 18 | AP56: 2 | AQ56: 25671 | AR56: BARNACHEA, Norman Idica | AS56: =IF(AR56="(Vacant)",AR56,IF(AR56="",AR56,"With Incumbent")) -> With Incumbent
A57: OSEC-DILGB-A2-6-1998 | B57: Regional Office | C57: Accountant II | D57: 16 | E57: =AF57*12 -> 234168 | F57: =+AH57*12 -> 263628 | G57: vacant | H57: 1 | I57: 011 | J57: R | K57: A | L57: A.03.a.01.c | M57: Regional Office | N57: BALABAG | O57: Iris | P57: =UPPER(O57) -> IRIS | R57: L | S57: =P57&" "&R57&"."&" "&N57&" "&Q57 -> IRIS L. BALABAG | T57: 21969 | U57: BALABAG, Iris Lami-ing | V57: F | W57: 29897 | X57: =(NOW()-W57) -> 16208.538 | Y57: 934-223-875 | AA57: 40252 | AB57: 40252 | AC57: P | AD57: RA 1080 | AF57: 19514 | AG57: 19514 | AH57: 21969 | AJ57: =AH57-AG57 -> 2455 | AL57: Retained | AM57: OSEC-DILGB-A2-6-1998 | AN57: Accountant II | AO57: 16 | AP57: 1 | AQ57: 21969 | AR57: BALABAG, Iris Lami-ing | AS57: =IF(AR57="(Vacant)",AR57,IF(AR57="",AR57,"With Incumbent")) -> With Incumbent
A58: OSEC-DILGB-ADOF4-70-2005 | B58: Regional Office | C58: Administrative Officer IV (BO II) | D58: 15 | E58: =AF58*12 -> 245880 | F58: =+AH58*12 -> 254064 | G58: 179940 | H58: 3 | I58: 011 | J58: M | K58: T | L58: A.03.a.01.c | M58: Regional Office | N58: BRIONES | O58: Rolly | P58: =UPPER(O58) -> ROLLY | R58: B | S58: =P58&" "&R58&"."&" "&N58&" "&Q58 -> ROLLY B. BRIONES | T58: 21172 | U58: BRIONES, Rolly Burcao | V58: M | W58: 27951 | X58: =(NOW()-W58) -> 18154.538 | Y58: 904-166-999 | AA58: 37293 | AB58: 37834 | AC58: P | AD58: CSP | AF58: 20490 | AG58: 19040 | AH58: 21172 | AJ58: =AH58-AG58 -> 2132 | AL58: Retained | AM58: OSEC-DILGB-ADOF4-70-2005 | AN58: Administrative Officer IV (BO II) | AO58: 15 | AP58: 3 | AQ58: 21172 | AR58: BRIONES, Rolly Burcao | AS58: =IF(AR58="(Vacant)",AR58,IF(AR58="",AR58,"With Incumbent")) -> With Incumbent
AL59: Fr ORD RO IV-B | AN59: Administrative Officer IV (HRMO II) | AO59: 15 | AP59: 1 | AQ59: 20490 | AR59: (Vacant) | AS59: =IF(AR59="(Vacant)",AR59,IF(AR59="",AR59,"With Incumbent")) -> (Vacant) | AU59: Bachelor' Degree | AV59: 1 year of Relevant Experience | AW59: 4 Hours of Relevant Training | AX59: CSP / Second Level Eligibility | AY59: FOR ASSESSMENT
E60: =AF60*12 -> 245880 | F60: =+AH60*12 -> 254064 | G60: 179940 | I60: 011 | J60: R | K60: A | L60: A.03.a.01.c | M60: Regional Office | N60: RIMANDO | O60: Marie Cris | P60: =UPPER(O60) -> MARIE CRIS | R60: L | S60: =P60&" "&R60&"."&" "&N60&" "&Q60 -> MARIE CRIS L. RIMANDO | V60: F | W60: 24278 | X60: =(NOW()-W60) -> 21827.538 | Y60: 129-983-169 | AA60: 36374 | AB60: 37809 | AC60: P | AD60: CSP | AF60: 20490 | AG60: 19040 | AH60: 21172 | AJ60: =AH60-AG60 -> 2132 | AL60: Retained Fr ORD 1 | AM60: OSEC-DILGB-ADOF4-69-2005 | AN60: Administrative Officer IV CTI (Information Officer II) | AO60: 15 | AP60: 3 | AQ60: 21172 | AR60: RIMANDO, Marie Cris Lim | AS60: =IF(AR60="(Vacant)",AR60,IF(AR60="",AR60,"With Incumbent")) -> With Incumbent
A61: OSEC-DILGB-ADOF3-43-2005 | B61: Regional Office | C61: Administrative Officer III (Cashier II) | D61: 14 | E61: =AF61*12 -> 229344 | F61: =+AH61*12 -> 236736 | G61: 169764 | H61: 3 | I61: 011 | J61: R | K61: S | L61: A.03.a.01.c | M61: Regional Office | N61: GABOT | O61: Luzviminda | P61: =UPPER(O61) -> LUZVIMINDA | R61: M | S61: =P61&" "&R61&"."&" "&N61&" "&Q61 -> LUZVIMINDA M. GABOT | T61: 19728 | U61: GABOT, Luzviminda Montano | V61: F | W61: 21451 | X61: =(NOW()-W61) -> 24654.538 | Y61: 127-933-774 | AA61: 30082 | AB61: 37378 | AC61: P | AD61: CSP | AF61: 19112 | AG61: 17839 | AH61: 19728 | AJ61: =AH61-AG61 -> 1889 | AL61: Retained | AM61: OSEC-DILGB-ADOF3-43-2005 | AN61: Administrative Officer III (Cashier II) | AO61: 14 | AP61: 3 | AQ61: 19728 | AR61: GABOT, Luzviminda Montano | AS61: =IF(AR61="(Vacant)",AR61,IF(AR61="",AR61,"With Incumbent")) -> With Incumbent
A62: OSEC-DILGB-ADOF3-44-2005 | B62: Regional Office | C62: Administrative Officer III (RO II) | D62: 14 | E62: =AF62*12 -> 229344 | F62: =+AH62*12 -> 233016 | G62: 165612 | H62: 2 | I62: 011 | J62: R | K62: A | L62: A.03.a.01.c | M62: Regional Office | N62: GED-ANG | O62: Chrysantine | P62: =UPPER(O62) -> CHRYSANTINE | R62: C | S62: =P62&" "&R62&"."&" "&N62&" "&Q62 -> CHRYSANTINE C. GED-ANG | T62: 19418 | U62: GED-ANG, Chrysantine Chan | V62: F | W62: 28900 | X62: =(NOW()-W62) -> 17205.538 | Y62: 927-997-461 | AA62: 37564 | AB62: 38607 | AC62: P | AD62: CSP | AF62: 19112 | AG62: 17490 | AH62: 19418 | AJ62: =AH62-AG62 -> 1928 | AL62: Retained | AM62: OSEC-DILGB-ADOF3-44-2005 | AN62: Administrative Officer III (RO II) | AO62: 14 | AP62: 2 | AQ62: 19418 | AR62: GED-ANG, Chrysantine Chan | AS62: =IF(AR62="(Vacant)",AR62,IF(AR62="",AR62,"With Incumbent")) -> With Incumbent
A63: OSEC-DILGB-ADAS3-65-2005 | B63: Regional Office | C63: Administrative Assistant III (Storekeeper III) | D63: 09 | E63: =AF63*12 -> 163956 | F63: =+AH63*12 -> 169320 | G63: 126072 | H63: 3 | I63: 011 | J63: R | K63: A | L63: A.03.a.01.c | M63: Regional Office | N63: CASTRO | O63: Angelito | P63: =UPPER(O63) -> ANGELITO | R63: G | S63: =P63&" "&R63&"."&" "&N63&" "&Q63 -> ANGELITO G. CASTRO | T63: 14110 | U63: CASTRO, Angelito Gaddi | V63: M | W63: 26800 | X63: =(NOW()-W63) -> 19305.538 | Y63: 191-960-647 | AA63: 35827 | AB63: 37658 | AC63: P | AD63: CSSP | AF63: 13663 | AG63: 12978 | AH63: 14110 | AJ63: =AH63-AG63 -> 1132 | AL63: Retained | AM63: OSEC-DILGB-ADAS3-65-2005 | AN63: Administrative Assistant III (Storekeeper III) | AO63: 09 | AP63: 3 | AQ63: 14110 | AR63: CASTRO, Angelito Gaddi | AS63: =IF(AR63="(Vacant)",AR63,IF(AR63="",AR63,"With Incumbent")) -> With Incumbent
A64: OSEC-DILGB-ADAS2-61-2005 | B64: Regional Office | C64: Administrative Assistant II (AC III) | D64: 08 | E64: =AF64*12 -> 152820 | F64: =+AH64*12 -> 157812 | G64: 117828 | H64: 3 | I64: 011 | J64: R | K64: A | L64: A.03.a.01.c | M64: Benguet | N64: TOMAS | O64: Precilla | P64: =UPPER(O64) -> PRECILLA | R64: K | S64: =P64&" "&R64&"."&" "&N64&" "&Q64 -> PRECILLA K. TOMAS | T64: 13151 | U64: TOMAS, Prescilla Kitan | V64: F | W64: 24329 | X64: =(NOW()-W64) -> 21776.538 | Y64: 915-096-278 | AA64: 36145 | AB64: 37655 | AC64: P | AD64: CSSP | AF64: 12735 | AG64: 12110 | AH64: 13151 | AJ64: =AH64-AG64 -> 1041 | AL64: Retained | AM64: OSEC-DILGB-ADAS2-61-2005 | AN64: Administrative Assistant II (AC III) | AO64: 08 | AP64: 3 | AQ64: 13151 | AR64: TOMAS, Prescilla Kitan | AS64: =IF(AR64="(Vacant)",AR64,IF(AR64="",AR64,"With Incumbent")) -> With Incumbent
A65: OSEC-DILGB-ADAS2-62-2005 | B65: Regional Office | C65: Administrative Assistant II (Artist Illustrator II) | D65: 08 | E65: =AF65*12 -> 152820 | F65: =+AH65*12 -> 152820 | G65: vacant | H65: 1 | I65: 011 | J65: R | K65: A | L65: A.03.a.01.c | P65: =UPPER(O65) | S65: =P65&" "&R65&"."&" "&N65&" "&Q65 -> . | T65: 12735 | U65: (Vacant) | AF65: 12735 | AG65: 11636 | AH65: 12735 | AJ65: =AH65-AG65 -> 1099 | AL65: Abolished
A66: OSEC-DILGB-ADAS2-63-2005 | B66: Regional Office | C66: Administrative Assistant II (Bookkeeper II) | D66: 08 | E66: =AF66*12 -> 152820 | F66: =+AH66*12 -> 155292 | G66: 117828 | H66: 2 | I66: 011 | J66: R | K66: A | L66: A.03.a.01.c | M66: Regional Office | N66: EUSTAQUIO | O66: Arlene | P66: =UPPER(O66) -> ARLENE | R66: V | S66: =P66&" "&R66&"."&" "&N66&" "&Q66 -> ARLENE V. EUSTAQUIO | T66: 12941 | U66: EUSTAQUIO, Arlene Villanueva | V66: F | W66: 30026 | X66: =(NOW()-W66) -> 16079.538 | AA66: 38047 | AB66: 38226 | AC66: P | AD66: CSP | AF66: 12735 | AG66: 11871 | AH66: 12941 | AJ66: =AH66-AG66 -> 1070 | AL66: Reclass | AM66: OSEC-DILGB-ADAS2-63-2005 | AN66: Administrative Assistant III | AO66: 09 | AP66: 1 | AQ66: 13663 | AR66: EUSTAQUIO, Arlene Villanueva | AS66: =IF(AR66="(Vacant)",AR66,IF(AR66="",AR66,"With Incumbent")) -> With Incumbent
A67: OSEC-DILGB-ADAS2-64-2005 | B67: Regional Office | C67: Administrative Assistant II (DO II) | D67: 08 | E67: =AF67*12 -> 152820 | F67: =+AH67*12 -> 160392 | G67: 120768 | H67: 4 | I67: 011 | J67: R | K67: A | L67: A.03.a.01.c | M67: Regional Office | N67: LOPEZ | O67: Jessica Kim | P67: =UPPER(O67) -> JESSICA KIM | R67: A | S67: =P67&" "&R67&"."&" "&N67&" "&Q67 -> JESSICA KIM A. LOPEZ | T67: 13366 | U67: LOPEZ, Jessica Kim Angeles | V67: F | W67: 25390 | X67: =(NOW()-W67) -> 20715.538 | Y67: 914-805-367 | AA67: 36007 | AB67: 36325 | AC67: P | AD67: CSSP | AF67: 12735 | AG67: 12357 | AH67: 13366 | AJ67: =AH67-AG67 -> 1009 | AL67: Retained | AM67: OSEC-DILGB-ADAS2-64-2005 | AN67: Administrative Assistant II (DO II) | AO67: 08 | AP67: 4 | AQ67: 13366 | AR67: LOPEZ, Jessica Kim Angeles | AS67: =IF(AR67="(Vacant)",AR67,IF(AR67="",AR67,"With Incumbent")) -> With Incumbent
A68: OSEC-DILGB-ADAS2-65-2005 | B68: Regional Office | C68: Administrative Assistant II (HRMA) | D68: 08 | E68: =AF68*12 -> 152820 | F68: =+AH68*12 -> 155292 | G68: 114960 | H68: 2 | I68: 011 | J68: R | K68: A | L68: A.03.a.01.c | M68: Regional Office | N68: PAPAT-IW | O68: Zaldy | P68: =UPPER(O68) -> ZALDY | R68: B | S68: =P68&" "&R68&"."&" "&N68&" "&Q68 -> ZALDY B. PAPAT-IW | T68: 12941 | U68: PAPAT-IW, Zaldy Bugtong | V68: M | W68: 27757 | X68: =(NOW()-W68) -> 18348.538 | Y68: 916-245-161 | AA68: 37655 | AB68: 38607 | AC68: P | AD68: CSSP | AF68: 12735 | AG68: 11871 | AH68: 12941 | AJ68: =AH68-AG68 -> 1070 | AL68: To PO 5 / Retained
A69: OSEC-DILGB-ADA6-94-2005 | B69: Regional Office | C69: Administrative Aide VI (CEO II) | D69: 06 | E69: =AF69*12 -> 132744 | F69: =+AH69*12 -> 148764 | G69: 119352 | H69: 8 | I69: 011 | J69: R | K69: A | L69: A.03.a.01.c | M69: Regional Office | N69: DEDUQUE | O69: Katherine | P69: =UPPER(O69) -> KATHERINE | R69: P | S69: =P69&" "&R69&"."&" "&N69&" "&Q69 -> KATHERINE P. DEDUQUE | T69: 12397 | U69: DEDUQUE, Katherine Pablo | V69: F | W69: 20640 | X69: =(NOW()-W69) -> 25465.538 | Y69: 127-933-782 | AA69: 27442 | AB69: 27442 | AC69: P | AD69: MC 11 | AF69: 11062 | AG69: 11669 | AH69: 12397 | AJ69: =AH69-AG69 -> 728 | AL69: Abolished | AT69: Remain in the Service | AY69: to ADA6-102 PO
A70: OSEC-DILGB-ADA6-95-2005 | B70: Regional Office | C70: Administrative Aide VI (Cash Clerk II) | D70: 06 | E70: =AF70*12 -> 132744 | F70: =+AH70*12 -> 132744 | G70: 102912 | H70: 1 | I70: 011 | J70: R | K70: A | L70: A.03.a.01.c | S70: Vacant AGLANO, Oscarson B. | T70: 11062 | U70: (Vacant) | AF70: 11062 | AG70: 10133 | AH70: 11062 | AJ70: =AH70-AG70 -> 929 | AL70: To PO 6 Retained
A71: OSEC-DILGB-ADA6-96-2005 | B71: Regional Office | C71: Administrative Aide VI (Clerk III) | D71: 06 | E71: =AF71*12 -> 132744 | F71: =+AH71*12 -> 132744 | G71: 102912 | H71: 1 | I71: 011 | J71: R | K71: A | L71: A.03.a.01.c | S71: Vacant ATING, Lucas A. | T71: 11062 | U71: (Vacant) | AF71: 11062 | AG71: 10133 | AH71: 11062 | AJ71: =AH71-AG71 -> 929 | AL71: Retained | AM71: OSEC-DILGB-ADA6-96-2005 | AN71: Administrative Aide VI CTI | AO71: 06 | AP71: 1 | AQ71: 11062 | AR71: To be Abolished | AS71: =IF(AR71="(Vacant)",AR71,IF(AR71="",AR71,IF(AR71="To be Abolished",AR71,"With Incumbent"))) -> To be Abolished
A72: OSEC-DILGB-ADA6-97-2005 | B72: Regional Office | C72: Administrative Aide VI (Clerk III) | D72: 06 | E72: =AF72*12 -> 132744 | F72: =+AH72*12 -> 137100 | G72: 102912 | H72: 3 | I72: 011 | J72: R | K72: A | L72: A.03.a.01.c | M72: Kalinga | N72: MAGO | O72: Carmelita | P72: =UPPER(O72) -> CARMELITA | R72: C | S72: =P72&" "&R72&"."&" "&N72&" "&Q72 -> CARMELITA C. MAGO | T72: 11425 | U72: MAGO, Carmelita Cenabre | V72: F | W72: 20401 | X72: =(NOW()-W72) -> 25704.538 | Y72: 127-934-872 | AA72: 30769 | AB72: 37288 | AC72: P | AD72: CSSP | AF72: 11062 | AG72: 10548 | AH72: 11425 | AJ72: =AH72-AG72 -> 877 | AL72: To LGCD 4 Retained
A73: OSEC-DILGB-ADA6-98-2005 | B73: Regional Office | C73: Administrative Aide VI (Storekeeper II) | D73: 06 | E73: =AF73*12 -> 132744 | F73: =+AH73*12 -> 134904 | G73: 100404 | H73: 2 | I73: 011 | J73: R | K73: A | L73: A.03.a.01.c | M73: Regional Office | N73: IDOS | O73: Dexter | P73: =UPPER(O73) -> DEXTER | R73: L | S73: =P73&" "&R73&"."&" "&N73&" "&Q73 -> DEXTER L. IDOS | T73: 11242 | U73: IDOS, Dexter Las-o | V73: M | W73: 29647 | X73: =(NOW()-W73) -> 16458.538 | Y73: 932-867-431 | AA73: 38215 | AB73: 38384 | AC73: P | AD73: CSP | AF73: 11062 | AG73: 10338 | AH73: 11242 | AJ73: =AH73-AG73 -> 904 | AL73: Abolished | AT73: Remain in the Service | AY73: DILG pool
A74: OSEC-DILGB-ADA4-85-2005 | B74: Regional Office | C74: Administrative Aide IV (Clerk II) | D74: 04 | E74: =AF74*12 -> 114432 | F74: =+AH74*12 -> 116280 | G74: 88224 | H74: 2 | I74: 011 | J74: R | K74: A | L74: A.03.a.01.c | M74: Abra | N74: GUINABAN | O74: Joanna Ruth | P74: =UPPER(O74) -> JOANNA RUTH | R74: T | S74: =P74&" "&R74&"."&" "&N74&" "&Q74 -> JOANNA RUTH T. GUINABAN | T74: 9690 | U74: DOMASING, Joanna Ruth Guinaban | V74: F | W74: 27558 | X74: =(NOW()-W74) -> 18547.538 | Y74: 176-734-004 | AA74: 38226 | AB74: 38226 | AC74: P | AD74: CSP | AF74: 9536 | AG74: 8888 | AH74: 9690 | AJ74: =AH74-AG74 -> 802 | AL74: Retained | AM74: OSEC-DILGB-ADA4-85-2005 | AN74: Administrative Aide IV (Clerk II) | AO74: 04 | AP74: 2 | AQ74: 9690 | AR74: DOMASING, Joanna Ruth Guinaban | AS74: =IF(AR74="(Vacant)",AR74,IF(AR74="",AR74,"With Incumbent")) -> With Incumbent
A75: OSEC-DILGB-ADA4-86-2005 | B75: Regional Office | C75: Administrative Aide IV (Clerk II) | D75: 04 | E75: =AF75*12 -> 114432 | F75: =+AH75*12 -> 114432 | G75: vacant | H75: 1 | I75: 011 | J75: R | K75: A | L75: A.03.a.01.c | P75: =UPPER(O75) | S75: =P75&" "&R75&"."&" "&N75&" "&Q75 -> . | T75: 9536 | U75: (Vacant) | AF75: 9536 | AG75: 8713 | AH75: 9536 | AJ75: =AH75-AG75 -> 823 | AL75: Retained | AM75: OSEC-DILGB-ADA4-86-2005 | AN75: Administrative Aide IV (Clerk II) | AO75: 04 | AP75: 1 | AQ75: 9536 | AR75: (Vacant) | AS75: =IF(AR75="(Vacant)",AR75,IF(AR75="",AR75,"With Incumbent")) -> (Vacant) | AU75: Completion of 2 years studies in college | AV75: None Required | AW75: None Required | AX75: CSSP / 1st Level Eligibility | AY75: FOR ASSESSMENT
A76: OSEC-DILGB-ADA4-87-2005 | B76: Regional Office | C76: Administrative Assistant IV (Mechanic I) | D76: 04 | E76: =AF76*12 -> 114432 | F76: =+AH76*12 -> 114432 | G76: 102312 | H76: 1 | I76: 011 | J76: R | K76: A | L76: A.03.a.01.c | N76: TICBAEN | O76: Antonio | P76: =UPPER(O76) -> ANTONIO | R76: M | S76: =P76&" "&R76&"."&" "&N76&" "&Q76 -> ANTONIO M. TICBAEN | T76: 9536 | U76: (Vacant) | AF76: 9536 | AG76: 8713 | AH76: 9536 | AJ76: =AH76-AG76 -> 823 | AL76: Retained | AM76: OSEC-DILGB-ADA4-87-2005 | AN76: Administrative Aide IV (Clerk II) | AO76: 04 | AP76: 1 | AQ76: 9536 | AR76: (Vacant) | AS76: =IF(AR76="(Vacant)",AR76,IF(AR76="",AR76,"With Incumbent")) -> (Vacant) | AU76: Completion of 2 years studies in college | AV76: None Required | AW76: None Required | AX76: CSSP / 1st Level Eligibility | AY76: FOR ASSESSMENT
E77: =AF77*12 -> 106248 | F77: =+AH77*12 -> 111504 | G77: 85836 | I77: 011 | J77: R | K77: A | L77: A.03.a.01.c | M77: Regional Office | N77: TAMONDONG | O77: Jonathan | P77: =UPPER(O77) -> JONATHAN | R77: A | S77: =P77&" "&R77&"."&" "&N77&" "&Q77 -> JONATHAN A. TAMONDONG | V77: M | W77: 24419 | X77: =(NOW()-W77) -> 21686.538 | Y77: 175-568-367 | AA77: 34808 | AB77: 36054 | AC77: P | AD77: MC 11 | AF77: 8854 | AG77: 8580 | AH77: 9292 | AJ77: =AH77-AG77 -> 712 | AL77: Retained Fr ORD 3 | AM77: OSEC-DILGB-ADA3-61-2005 | AN77: Administrative Aide III CTI | AO77: 03 | AP77: 4 | AQ77: 9292 | AR77: TAMONDONG, Jonathan Ambat | AS77: =IF(AR77="(Vacant)",AR77,IF(AR77="",AR77,"With Incumbent")) -> With Incumbent
A78: OSEC-DILGB-SECG1-8-1998 | B78: Regional Office | C78: Security Guard I | D78: 03 | E78: =AF78*12 -> 106248 | F78: =+AH78*12 -> 119004 | G78: 92412 | H78: 8 | I78: 011 | J78: R | K78: A | L78: A.03.a.01.c | M78: Regional Office | N78: ROJO | O78: Gerardo | P78: =UPPER(O78) -> GERARDO | R78: R | S78: =P78&" "&R78&"."&" "&N78&" "&Q78 -> GERARDO R. ROJO | T78: 9917 | U78: ROJO, Gerardo Rontos | V78: M | W78: 22132 | X78: =(NOW()-W78) -> 23973.538 | Y78: 127-933-219 | AA78: 32371 | AB78: 32371 | AC78: P | AD78: RES 435 | AF78: 8854 | AG78: 9301 | AH78: 9917 | AJ78: =AH78-AG78 -> 616 | AL78: Retained | AM78: OSEC-DILGB-SECG1-8-1998 | AN78: Security Guard I CTI | AO78: 03 | AP78: 8 | AQ78: 9917 | AR78: ROJO, Gerardo Rontos | AS78: =IF(AR78="(Vacant)",AR78,IF(AR78="",AR78,"With Incumbent")) -> With Incumbent
A79: OSEC-DILGB-SECG1-9-1998 | B79: Regional Office | C79: Security Guard I | D79: 03 | E79: =AF79*12 -> 106248 | F79: =+AH79*12 -> 109704 | G79: 81696 | H79: 3 | I79: 011 | J79: R | K79: A | L79: A.03.a.01.c | M79: Regional Office | N79: PEREZ | O79: Roberto | P79: =UPPER(O79) -> ROBERTO | R79: A | S79: =P79&" "&R79&"."&" "&N79&" "&Q79 -> ROBERTO A. PEREZ | T79: 9142 | U79: PEREZ, Roberto Aquino | V79: M | W79: 26124 | X79: =(NOW()-W79) -> 19981.538 | Y79: 176- 643-612 | AA79: 35878 | AB79: 38018 | AC79: P | AD79: MC 11 | AF79: 8854 | AG79: 8409 | AH79: 9142 | AJ79: =AH79-AG79 -> 733 | AL79: Retained | AM79: OSEC-DILGB-SECG1-9-1998 | AN79: Security Guard I CTI | AO79: 03 | AP79: 3 | AQ79: 9142 | AR79: PEREZ, Roberto Aquino | AS79: =IF(AR79="(Vacant)",AR79,IF(AR79="",AR79,"With Incumbent")) -> With Incumbent
A80: OSEC-DILGB-SEC1-10-1998 | B80: Regional Office | C80: Security Guard I | D80: 03 | E80: =AF80*12 -> 106248 | F80: =+AH80*12 -> 109704 | G80: 83724 | H80: 3 | I80: 011 | J80: R | K80: A | L80: A.03.a.01.c | M80: Regional Office | N80: NONOG | O80: Edward | P80: =UPPER(O80) -> EDWARD | R80: B | S80: =P80&" "&R80&"."&" "&N80&" "&Q80 -> EDWARD B. NONOG | T80: 9142 | U80: NONOG, Edward Bolda | V80: M | W80: 28191 | X80: =(NOW()-W80) -> 17914.538 | Y80: 917-878-826 | AA80: 37173 | AB80: 37173 | AC80: P | AD80: MC 11 | AF80: 8854 | AG80: 8409 | AH80: 9142 | AJ80: =AH80-AG80 -> 733 | AL80: Retained | AM80: OSEC-DILGB-SEC1-10-1998 | AN80: Security Guard I CTI | AO80: 03 | AP80: 3 | AQ80: 9142 | AR80: NONOG, Edward Bolda | AS80: =IF(AR80="(Vacant)",AR80,IF(AR80="",AR80,"With Incumbent")) -> With Incumbent
A81: OSEC-DILGB-ADA2-54-2005 | B81: Regional Office | C81: Administrative Aide II (Messenger) | D81: 02 | E81: =AF81*12 -> 98268 | F81: =+AH81*12 -> 110040 | G81: 84792 | H81: 8 | I81: 011 | J81: R | K81: A | L81: A.03.a.01.c | M81: Regional Office | N81: PUMARES | O81: Orlando | P81: =UPPER(O81) -> ORLANDO | R81: C | S81: =P81&" "&R81&"."&" "&N81&" "&Q81 -> ORLANDO C. PUMARES | T81: 9170 | U81: PUMARES, Orlando Canco | V81: M | W81: 18445 | X81: =(NOW()-W81) -> 27660.538 | Y81: 127-933-242 | AA81: 32371 | AB81: 32371 | AC81: P | AD81: MC 11 | AF81: 8189 | AG81: 8569 | AH81: 9170 | AJ81: =AH81-AG81 -> 601 | AL81: Retained | AM81: OSEC-DILGB-ADA2-54-2005 | AN81: Administrative Aide II (Messenger) CTI | AO81: 02 | AP81: 8 | AQ81: 9170 | AR81: PUMARES, Orlando Canco | AS81: =IF(AR81="(Vacant)",AR81,IF(AR81="",AR81,IF(AR81="To be Abolished",AR81,"With Incumbent"))) -> With Incumbent | AT81: Avail Retirement Package | AY81: *
A82: OSEC-DILGB-ADA2-55-2005 | B82: Regional Office | C82: Administrative Aide II (RMO I) | D82: 02 | E82: =AF82*12 -> 98268 | F82: =+AH82*12 -> 110040 | G82: 84792 | H82: 8 | I82: 011 | J82: R | K82: A | L82: A.03.a.01.c | M82: Regional Office | N82: PASCUA | O82: Diosdado | P82: =UPPER(O82) -> DIOSDADO | R82: A | S82: =P82&" "&R82&"."&" "&N82&" "&Q82 -> DIOSDADO A. PASCUA | T82: 9170 | U82: PASCUA, Diosdado Aquino | V82: M | W82: 2/29/1955 | X82: =(NOW()-W82) -> #VALUE! | Y82: 127-933-235 | AA82: 32371 | AB82: 32371 | AC82: P | AD82: RES 435 | AF82: 8189 | AG82: 8569 | AH82: 9170 | AJ82: =AH82-AG82 -> 601 | AL82: Reclass | AM82: OSEC-DILGB-ADA2-55-2005 | AN82: Administrative Aide IV | AO82: 04 | AP82: 1 | AQ82: 9536 | AR82: PASCUA, Diosdado Aquino | AS82: =IF(AR82="(Vacant)",AR82,IF(AR82="",AR82,"With Incumbent")) -> With Incumbent
A83: OSEC-DILGB-ADA1-27-2005 | B83: Regional Office | C83: Administrative Aide I (UTW I) | D83: 01 | E83: =AF83*12 -> 90900 | F83: =+AH83*12 -> 90900 | G83: vacant | H83: 1 | I83: 011 | J83: R | K83: A | L83: A.03.a.01.c | P83: =UPPER(O83) | S83: =P83&" "&R83&"."&" "&N83&" "&Q83 -> . | T83: 7575 | U83: (Vacant) | AF83: 7575 | AG83: 6862 | AH83: 7575 | AJ83: =AH83-AG83 -> 713 | AL83: Retained | AM83: OSEC-DILGB-ADA1-27-2005 | AN83: Administrative Aide I CTI | AO83: 01 | AP83: 1 | AQ83: 7575 | AR83: To be Abolished | AS83: =IF(AR83="(Vacant)",AR83,IF(AR83="",AR83,IF(AR83="To be Abolished",AR83,"With Incumbent"))) -> To be Abolished
A84: Sub-Total | D84: =COUNTIF(D51:D83,"<>") -> 30 | AM84: Sub-Total | AO84: =COUNTIF(AO51:AO83,"<>") -> 27
A85: 65000000000 Provincial Office | F85: =+AH85*12 -> 0 | G85: 12 | AL85: Provincial Office
A86: OSEC-DILGB-LGOO8-2-1998 | B86: Baguio City | C86: Local Government Operations Officer VIII | D86: 26 | E86: =AF86*12 -> 511668 | F86: =+AH86*12 -> 535860 | G86: 312336 | H86: 4 | I86: 05 | J86: P | K86: K | L86: A.03.a.01.c | M86: ABRA | N86: CALINA | O86: Crescencio | P86: =UPPER(O86) -> CRESCENCIO | Q86: Jr. | R86: J | S86: =P86&" "&R86&"."&" "&N86&" "&Q86 -> CRESCENCIO J. CALINA Jr. | T86: 44655 | U86: CALINA, Crescencio Javier | V86: M | W86: 18188 | X86: =(NOW()-W86) -> 27917.538 | Y86: 127-933-580 | Z86: 32687 | AA86: 27820 | AB86: 37519 | AC86: P | AD86: CESO | AF86: 42639 | AG86: 37001 | AH86: 44655 | AJ86: =AH86-AG86 -> 7654 | AL86: Retained | AM86: OSEC-DILGB-LGOO8-2-1998 | AN86: Local Government Operations Officer VIII | AO86: 26 | AP86: 4 | AQ86: 44655 | AR86: CALINA, Crescencio Javier | AS86: =IF(AR86="(Vacant)",AR86,IF(AR86="",AR86,"With Incumbent")) -> With Incumbent
A87: OSEC-DILGB-LGOO8-45-1998 | B87: Abra | C87: Local Government Operations Officer VIII | D87: 26 | E87: =AF87*12 -> 511668 | F87: =+AH87*12 -> 519588 | G87: 297276 | H87: 2 | I87: 05 | J87: P | K87: K | L87: A.03.a.01.c | M87: Ifugao | N87: BALLUG | O87: Anthony | P87: =UPPER(O87) -> ANTHONY | R87: I | S87: =P87&" "&R87&"."&" "&N87&" "&Q87 -> ANTHONY I. BALLUG | T87: 43299 | U87: BALLUG, Anthony Ilacad | V87: M | W87: 24640 | X87: =(NOW()-W87) -> 21465.538 | Y87: 185-737-925 | AA87: 34808 | AB87: 39230 | AC87: P | AD87: CSEE | AF87: 42639 | AG87: 35615 | AH87: 43299 | AJ87: =AH87-AG87 -> 7684 | AL87: Retained | AM87: OSEC-DILGB-LGOO8-45-1998 | AN87: Local Government Operations Officer VIII | AO87: 26 | AP87: 2 | AQ87: 43299 | AR87: BALLUG, Anthony Ilacad | AS87: =IF(AR87="(Vacant)",AR87,IF(AR87="",AR87,"With Incumbent")) -> With Incumbent
A88: OSEC-DILGB-LGOO8-56-1998 | B88: Benguet | C88: Local Government Operations Officer VIII | D88: 26 | E88: =AF88*12 -> 511668 | F88: =+AH88*12 -> 519588 | G88: 297276 | H88: 2 | I88: 06 | J88: P | K88: K | L88: A.03.a.01.c | M88: Mt. Province | N88: FEGCAN | O88: Rufina | P88: =UPPER(O88) -> RUFINA | R88: T | S88: =P88&" "&R88&"."&" "&N88&" "&Q88 -> RUFINA T. FEGCAN | T88: 43299 | U88: FEGCAN, Rufina Talusig | V88: F | W88: 23658 | X88: =(NOW()-W88) -> 22447.538 | Y88: 127-934-198 | AA88: 32687 | AB88: 39230 | AC88: P | AD88: CSEE | AF88: 42639 | AG88: 35615 | AH88: 43299 | AJ88: =AH88-AG88 -> 7684 | AL88: Retained | AM88: OSEC-DILGB-LGOO8-56-1998 | AN88: Local Government Operations Officer VIII | AO88: 26 | AP88: 2 | AQ88: 43299 | AR88: FEGCAN, Rufina Talusig | AS88: =IF(AR88="(Vacant)",AR88,IF(AR88="",AR88,"With Incumbent")) -> With Incumbent
A89: OSEC-DILGB-LGOO8-67-1998 | B89: Mt. Province | C89: Local Government Operations Officer VIII | D89: 26 | E89: =AF89*12 -> 511668 | F89: =+AH89*12 -> 511668 | G89: 353376 | H89: 1 | I89: 09 | J89: P | K89: K | L89: A.03.a.01.c | M89: Baguio City | N89: TRINIDAD | O89: Evelyn | P89: =UPPER(O89) -> EVELYN | R89: B | S89: =P89&" "&R89&"."&" "&N89&" "&Q89 -> EVELYN B. TRINIDAD | T89: 42639 | U89: TRINIDAD, Evelyn Ballug | V89: F | W89: 22001 | X89: =(NOW()-W89) -> 24104.538 | Y89: 127-934-809 | AA89: 32615 | AB89: 40112 | AF89: 42639 | AG89: 34945 | AH89: 42639 | AJ89: =AH89-AG89 -> 7694 | AL89: Retained | AM89: OSEC-DILGB-LGOO8-67-1998 | AN89: Local Government Operations Officer VIII | AO89: 26 | AP89: 1 | AQ89: 42639 | AR89: TRINIDAD, Evelyn Ballug | AS89: =IF(AR89="(Vacant)",AR89,IF(AR89="",AR89,"With Incumbent")) -> With Incumbent
A90: OSEC-DILGB-LGOO8-79-1998 | B90: Ifugao | C90: Local Government Operations Officer VIII | D90: 26 | E90: =AF90*12 -> 511668 | F90: =+AH90*12 -> 570240 | G90: 353376 | H90: 8 | I90: 07 | J90: P | K90: K | L90: A.03.a.01.c | M90: Benguet | N90: MONAYAO | O90: Myrna | P90: =UPPER(O90) -> MYRNA | R90: B | S90: =P90&" "&R90&"."&" "&N90&" "&Q90 -> MYRNA B. MONAYAO | T90: 47520 | U90: MONAYAO, Myrna Buduhan | V90: F | W90: 17276 | X90: =(NOW()-W90) -> 28829.538 | Y90: 127-934-277 | AA90: 25615 | AB90: 32371 | AC90: P | AD90: TE/CESO | AF90: 42639 | AG90: 39956 | AH90: 47520 | AJ90: =AH90-AG90 -> 7564 | AL90: Retained | AM90: OSEC-DILGB-LGOO8-79-1998 | AN90: Local Government Operations Officer VIII | AO90: 26 | AP90: 8 | AQ90: 47520 | AR90: MONAYAO, Myrna Buduhan | AS90: =IF(AR90="(Vacant)",AR90,IF(AR90="",AR90,"With Incumbent")) -> With Incumbent
A91: OSEC-DILGB-LGOO8-91-1998 | B91: Kalinga | C91: Local Government Operations Officer VIII | D91: 26 | E91: =AF91*12 -> 511668 | F91: =+AH91*12 -> 527652 | G91: 304704 | H91: 3 | I91: 79 | J91: P | K91: K | L91: A.03.a.01.c | M91: Apayao | N91: MADARIAGA | O91: Eleonora | P91: =UPPER(O91) -> ELEONORA | R91: F | S91: =P91&" "&R91&"."&" "&N91&" "&Q91 -> ELEONORA F. MADARIAGA | T91: 43971 | U91: MADARIAGA, Eleonora Figueros | V91: F | W91: 17218 | X91: =(NOW()-W91) -> 28887.538 | Y91: 127-933-904 | AA91: 25629 | AB91: 37861 | AC91: P | AD91: CDO/CSEE | AF91: 42639 | AG91: 36301 | AH91: 43971 | AJ91: =AH91-AG91 -> 7670 | AL91: Retained | AM91: OSEC-DILGB-LGOO8-91-1998 | AN91: Local Government Operations Officer VIII | AO91: 26 | AP91: 3 | AQ91: 43971 | AR91: MADARIAGA, Eleonora Figueros | AS91: =IF(AR91="(Vacant)",AR91,IF(AR91="",AR91,"With Incumbent")) -> With Incumbent
A92: OSEC-DILGB-LGOO8-98-1998 | B92: Apayao | C92: Local Government Operations Officer VIII | D92: 26 | E92: =AF92*12 -> 511668 | F92: =+AH92*12 -> 535860 | G92: 312336 | H92: 4 | I92: 08 | J92: P | K92: K | L92: A.03.a.01.c | M92: Kalinga | N92: GAMATERO | O92: Francisco | P92: =UPPER(O92) -> FRANCISCO | R92: R | S92: =P92&" "&R92&"."&" "&N92&" "&Q92 -> FRANCISCO R. GAMATERO | T92: 44655 | U92: GAMATERO, Francisco Rola | V92: M | W92: 19058 | X92: =(NOW()-W92) -> 27047.538 | Y92: 133-291-473 | Z92: 32687 | AA92: 27743 | AB92: 36283 | AC92: P | AD92: CSP | AF92: 42639 | AG92: 37001 | AH92: 44655 | AJ92: =AH92-AG92 -> 7654 | AL92: Retained | AM92: OSEC-DILGB-LGOO8-98-1998 | AN92: Local Government Operations Officer VIII | AO92: 26 | AP92: 4 | AQ92: 44655 | AR92: GAMATERO, Francisco Rola | AS92: =IF(AR92="(Vacant)",AR92,IF(AR92="",AR92,"With Incumbent")) -> With Incumbent
A93: OSEC-DILGB-LGOO7-25-1998 | B93: Apayao | C93: Local Government Operations Officer VII | D93: 24 | E93: =AF93*12 -> 449676 | F93: =+AH93*12 -> 471252 | G93: 288780 | H93: 4 | I93: 08 | J93: P | K93: T | L93: A.03.a.01.c | M93: Benguet | N93: BUGTONG | O93: Alex | P93: =UPPER(O93) -> ALEX | R93: K | S93: =P93&" "&R93&"."&" "&N93&" "&Q93 -> ALEX K. BUGTONG | T93: 39271 | U93: BUGTONG, Alex Kitongan | V93: M | W93: 18620 | X93: =(NOW()-W93) -> 27485.538 | Y93: 127-933-953 | AA93: 27265 | AB93: 36591 | AC93: P | AD93: CDO | AF93: 37473 | AG93: 33201 | AH93: 39271 | AJ93: =AH93-AG93 -> 6070 | AL93: Abolished | AT93: Avail Retirement Package
A94: OSEC-DILGB-LGOO7-39-1998 | B94: Abra | C94: Local Government Operations Officer VII | D94: 24 | E94: =AF94*12 -> 449676 | F94: =+AH94*12 -> 463932 | G94: 281724 | H94: 3 | I94: 05 | J94: P | K94: T | L94: A.03.a.01.c | M94: Abra | N94: VALERA | O94: Rene | P94: =UPPER(O94) -> RENE | R94: V | S94: =P94&" "&R94&"."&" "&N94&" "&Q94 -> RENE V. VALERA | T94: 38661 | U94: VALERA, Rene Velasco | V94: M | W94: 23438 | X94: =(NOW()-W94) -> 22667.538 | Y94: 127-933-695 | AA94: 33451 | AB94: 37453 | AC94: P | AD94: RA 1080 | AF94: 37473 | AG94: 32567 | AH94: 38661 | AJ94: =AH94-AG94 -> 6094 | AL94: Abolished | AT94: Remain in the Service | AY94: to NEW LGOO VI
A95: OSEC-DILGB-LGOO7-40-1998 | B95: Benguet | C95: Local Government Operations Officer VII | D95: 24 | E95: =AF95*12 -> 449676 | F95: =+AH95*12 -> 494064 | G95: 310980 | H95: 7 | I95: 011 | J95: R | K95: T | L95: A.03.a.01.c | S95: vacant HUMIWAT, Gerardo Dumangeg | T95: 41172 | U95: (Vacant) | AF95: 37473 | AG95: 35195 | AH95: 41172 | AJ95: =AH95-AG95 -> 5977 | AL95: Abolished
A96: OSEC-DILGB-LGOO7-41-1998 | B96: Mt. Province | C96: Local Government Operations Officer VII | D96: 24 | E96: =AF96*12 -> 449676 | F96: =+AH96*12 -> 456732 | G96: 281724 | H96: 2 | I96: 09 | J96: P | K96: T | L96: A.03.a.01.c | P96: =UPPER(O96) | S96: FEGCAN, Rufina T. (vacant 2/9/07) | T96: 38061 | U96: (Vacant) | AF96: 37473 | AG96: 31943 | AH96: 38061 | AJ96: =AH96-AG96 -> 6118 | AL96: Abolished
A97: OSEC-DILGB-LGOO7-42-1998 | B97: Ifugao | C97: Local Government Operations Officer VII | D97: 24 | E97: =AF97*12 -> 449676 | F97: =+AH97*12 -> 463932 | G97: 281724 | H97: 3 | I97: 011 | J97: R | K97: T | L97: A.03.a.01.c | M97: Apayao | N97: BASQUEZ | O97: Marvin | P97: =UPPER(O97) -> MARVIN | R97: A | S97: =P97&" "&R97&"."&" "&N97&" "&Q97 -> MARVIN A. BASQUEZ | T97: 38661 | U97: BASQUEZ, Marvin Amanonce | V97: M | W97: 21687 | X97: =(NOW()-W97) -> 24418.538 | Y97: 127-934-718 | AA97: 31131 | AB97: 37561 | AC97: P | AD97: CSP | AF97: 37473 | AG97: 32567 | AH97: 38661 | AJ97: =AH97-AG97 -> 6094 | AL97: Reclass | AM97: OSEC-DILGB-LGOO7-42-1998 | AN97: Local Government Operations Officer VI | AO97: 22 | AP97: 8 | AQ97: 38661 | AR97: BASQUEZ, Marvin Amanonce | AS97: =IF(AR97="(Vacant)",AR97,IF(AR97="",AR97,"With Incumbent")) -> With Incumbent | AY97: RECLASS
A98: OSEC-DILGB-LGOO7-43-1998 | B98: Kalinga | C98: Local Government Operations Officer VII | D98: 24 | E98: =AF98*12 -> 449676 | F98: =+AH98*12 -> 463932 | G98: 281724 | H98: 3 | I98: 079 | J98: P | K98: T | L98: A.03.a.01.c | M98: Kalinga | N98: BARCELLANO | O98: Julio | P98: =UPPER(O98) -> JULIO | R98: J | S98: =P98&" "&R98&"."&" "&N98&" "&Q98 -> JULIO J. BARCELLANO | T98: 38661 | U98: BARCELLANO, Julio Jacob | V98: M | W98: 18813 | X98: =(NOW()-W98) -> 27292.538 | Y98: 127-934-726 | AA98: 27757 | AB98: 37453 | AC98: P | AD98: CSP | AF98: 37473 | AG98: 32567 | AH98: 38661 | AJ98: =AH98-AG98 -> 6094 | AL98: Abolished | AT98: Remain in the Service | AY98: to NEW LGOO VI
AL99: New Position | AM99: New | AN99: Local Government Operations Officer VI | AO99: 22 | AP99: 8 | AQ99: 38661 | AR99: (Vacant) | AS99: =IF(AR99="(Vacant)",AR99,IF(AR99="",AR99,"With Incumbent")) -> (Vacant) | AT99: VALERA, Rene Velasco | AU99: Bachelor' Degree | AV99: 3 years of Relevant Experience | AW99: Completion of Training Course for LGOOs | AX99: CSP / Second Level Eligibility | AY99: from LGOO7-39 FOR ASSESSMENT
AL100: New Position | AM100: New | AN100: Local Government Operations Officer VI | AO100: 22 | AP100: 8 | AQ100: 38661 | AR100: (Vacant) | AS100: =IF(AR100="(Vacant)",AR100,IF(AR100="",AR100,"With Incumbent")) -> (Vacant) | AT100: BARCELLANO, Julio Jacob | AU100: Bachelor' Degree | AV100: 3 years of Relevant Experience | AW100: Completion of Training Course for LGOOs | AX100: CSP / Second Level Eligibility | AY100: from LGOO7-43 FOR ASSESSMENT
AL101: New Position | AM101: New | AN101: Local Government Operations Officer VI | AO101: 22 | AP101: 1 | AQ101: 32973 | AR101: (Vacant) | AS101: =IF(AR101="(Vacant)",AR101,IF(AR101="",AR101,"With Incumbent")) -> (Vacant) | AU101: Bachelor' Degree | AV101: 3 years of Relevant Experience | AW101: Completion of Training Course for LGOOs | AX101: CSP / Second Level Eligibility | AY101: FOR ASSESSMENT
...

Sheet Reclass18

Sheet JO inventory
A1: LIST OF JOB ORDER/CONTRACT OF SERVICE/MOA PERSONNEL
A2: =CONCATENATE("As of ",TEXT(NOW(),"mmmm dd, yyyy")) -> As of March 24, 2026
A4: DEPARTMENT OF THE INTERIOR AND LOCAL GOVERNMENT
A5: Cordillera Administrative Region
A7: NO. | B7: SURNAME | C7: FIRSTNAME | D7: MIDDLE INITIAL | E7: Date of Birth | F7: Age | G7: Sex | H7: Level of CS Eligibility | I7: Work Status | J7: Level | K7: Start date | L7: End date | M7: 2018 1st Sem renewal | N7: No. of Years as JO/COS/ MOA | O7: Station | P7: Nature of Work | Q7: Position Title | R7: Fund Source | S7: monthlu salary | T7: ID NUMBER
P8: Select | Q8: Specify
A9: 1 | B9: Allig | C9: Mike Collins | D9: O | E9: 32370 | F9: =DATEDIF(E9,TODAY(),"Y") -> 37 | G9: M | H9: None | I9: Contract of Service | J9: 1 | K9: 42601 | L9: 43465 | M9: y | N9: =CONCATENATE(DATEDIF(K9,L9,"Y"),"y ",DATEDIF(K9+(360*(DATEDIF(K9,L9,"Y"))),L9,"M"),"m ",DATEDIF(K9+(30.5*(DATEDIF(K9,L9,"M"))),L9,"D"),"d") -> 2y 4m 10d | O9: Ifugao | P9: Admin. Support Services | Q9: Driver | R9: Regular Funds | S9: 10833 | T9: JO028 | U9: 42735 | V9: =DATEDIF(U9,TODAY(),"Y") -> 9
A10: =A119+1 -> 3 | B10: Badcao | C10: Jacinto | D10: B | E10: 31040 | F10: =DATEDIF(E10,TODAY(),"Y") -> 41 | G10: M | H10: RA 1080 Civil Engineer | I10: Contract of Service | J10: 2 | K10: 42887 | L10: 43465 | M10: y | N10: =CONCATENATE(DATEDIF(K10,L10,"Y"),"y ",DATEDIF(K10+(360*(DATEDIF(K10,L10,"Y"))),L10,"M"),"m ",DATEDIF(K10+(30.5*(DATEDIF(K10,L10,"M"))),L10,"D"),"d") -> 1y 7m 29d | O10: Region | P10: Technical Services | Q10: Engineer III | R10: LFP | S10: 36409 | T10: JO044
A11: =A10+1 -> 4 | B11: Balatbat | C11: Jaime Jr. | D11: A | E11: 28656 | F11: =DATEDIF(E11,TODAY(),"Y") -> 47 | G11: M | H11: None | I11: Contract of Service | J11: 1 | K11: 42629 | L11: 43465 | M11: y | N11: =CONCATENATE(DATEDIF(K11,L11,"Y"),"y ",DATEDIF(K11+(360*(DATEDIF(K11,L11,"Y"))),L11,"M"),"m ",DATEDIF(K11+(30*(DATEDIF(K11,L11,"M"))),L11,"D"),"d") -> 2y 3m 26d | O11: Region | P11: Admin. Support Services | Q11: Driver | R11: Regular Funds | S11: 10833 | T11: JO030
A12: =A11+1 -> 5 | B12: Ballug | C12: Jan Michael | D12: DG | E12: 33047 | F12: =DATEDIF(E12,TODAY(),"Y") -> 35 | G12: M | H12: None | I12: Contract of Service | J12: 1 | K12: 42767 | L12: 43465 | M12: y | N12: =CONCATENATE(DATEDIF(K12,L12,"Y"),"y ",DATEDIF(K12+(360*(DATEDIF(K12,L12,"Y"))),L12,"M"),"m ",DATEDIF(K12+(30.5*(DATEDIF(K12,L12,"M"))),L12,"D"),"d") -> 1y 11m 27d | O12: Baguio | P12: Admin. Support Services | Q12: Driver | R12: Regular Funds | S12: 10833 | T12: JO037 | U12: 42735 | V12: =DATEDIF(U12,TODAY(),"Y") -> 9
A13: =A12+1 -> 6 | B13: Blosan | C13: Marlon | D13: E | E13: 33316 | F13: =DATEDIF(E13,TODAY(),"Y") -> 35 | G13: M | H13: RA 1080 Civil Engineer | I13: Contract of Service | J13: 2 | K13: 42905 | L13: 43465 | M13: y | N13: =CONCATENATE(DATEDIF(K13,L13,"Y"),"y ",DATEDIF(K13+(360*(DATEDIF(K13,L13,"Y"))),L13,"M"),"m ",DATEDIF(K13+(30.5*(DATEDIF(K13,L13,"M"))),L13,"D"),"d") -> 1y 6m 11d | O13: Abra | P13: Technical Services | Q13: Engineer II | R13: LFP | S13: 28417 | T13: JO048
A14: =A13+1 -> 7 | B14: Bolhayon | C14: Jake | D14: B | E14: 32952 | F14: =DATEDIF(E14,TODAY(),"Y") -> 36 | G14: M | H14: None | I14: Contract of Service | J14: 1 | K14: 42552 | L14: 43465 | M14: y | N14: =CONCATENATE(DATEDIF(K14,L14,"Y"),"y ",DATEDIF(K14+(360*(DATEDIF(K14,L14,"Y"))),L14,"M"),"m ",DATEDIF(K14+(30.5*(DATEDIF(K14,L14,"M"))),L14,"D"),"d") -> 2y 6m 29d | O14: Ifugao | P14: Janitorial Services | Q14: Utility/Janitor | R14: Regular Funds | S14: 9478 | T14: JO026 | V14: =sumif(DATEDIF(O9,TODAY(),"Y")>.99,concatenate((DATEDIF(O9,TODAY(),"Y")," yr")),(sumif(DATEDIF(O9,TODAY(),"Y")<.99,concatenate((DATEDIF(O9,TODAY(),"M")," mo")),((sumif(DATEDIF(O9,TODAY(),"M")<.99,concatenate((DATEDIF(O9,TODAY(),"D")," days")),((("no date")))
A15: =A14+1 -> 8 | B15: Bumatay | C15: Michelle | D15: E | E15: 32944 | F15: =DATEDIF(E15,TODAY(),"Y") -> 36 | G15: F | H15: RA 1080 Sanitary Engineer | I15: Contract of Service | J15: 2 | K15: 42307 | L15: 43465 | M15: y | N15: =CONCATENATE(DATEDIF(K15,L15,"Y"),"y ",DATEDIF(K15+(360*(DATEDIF(K15,L15,"Y"))),L15,"M"),"m ",DATEDIF(K15+(30.5*(DATEDIF(K15,L15,"M"))),L15,"D"),"d") -> #NUM! | O15: Apayao | P15: Technical Services | Q15: Engineer III | R15: LFP | S15: 36409 | T15: JO019
A16: =A15+1 -> 9 | B16: Bumosao | C16: Charles | D16: D | E16: 31374 | F16: =DATEDIF(E16,TODAY(),"Y") -> 40 | G16: M | H16: RA 1080 Civil Engineer | I16: Contract of Service | J16: 2 | K16: 42201 | L16: 43465 | M16: y | N16: =CONCATENATE(DATEDIF(K16,L16,"Y"),"y ",DATEDIF(K16+(360*(DATEDIF(K16,L16,"Y"))),L16,"M"),"m ",DATEDIF(K16+(30.5*(DATEDIF(K16,L16,"M"))),L16,"D"),"d") -> 3y 6m 14d | O16: Kalinga | P16: Technical Services | Q16: Engineer III | R16: LFP | S16: 36409 | T16: JO017
A17: =A16+1 -> 10 | B17: Castro | C17: Angeline | D17: B | E17: 27437 | F17: =DATEDIF(E17,TODAY(),"Y") -> 51 | G17: F | H17: LET CSP CSSP | I17: Contract of Service | J17: 2 | K17: 42982 | L17: 43465 | M17: y | N17: =CONCATENATE(DATEDIF(K17,L17,"Y"),"y ",DATEDIF(K17+(360*(DATEDIF(K17,L17,"Y"))),L17,"M"),"m ",DATEDIF(K17+(30.5*(DATEDIF(K17,L17,"M"))),L17,"D"),"d") -> 1y 4m 26d | O17: Region | P17: Technical Services | Q17: Development Management Officer V | R17: CMGP/Kalsada | S17: 56610 | T17: JO051
A18: =A17+1 -> 11 | B18: Colintas | C18: Aris | D18: A | E18: 31099 | F18: =DATEDIF(E18,TODAY(),"Y") -> 41 | G18: M | H18: None | I18: Contract of Service | J18: 2 | K18: 42278 | L18: 43465 | M18: y | N18: =CONCATENATE(DATEDIF(K18,L18,"Y"),"y ",DATEDIF(K18+(360*(DATEDIF(K18,L18,"Y"))),L18,"M"),"m ",DATEDIF(K18+(30.5*(DATEDIF(K18,L18,"M"))),L18,"D"),"d") -> 3y 3m 28d | O18: Region | P18: IT Services | Q18: ISA I | R18: LFP | S18: 36409 | T18: JO018
A19: =A18+1 -> 12 | B19: Culti | C19: Avery | D19: B | E19: 27605 | F19: =DATEDIF(E19,TODAY(),"Y") -> 50 | G19: M | H19: RA 1080 Civil Engineer | I19: Contract of Service | J19: 2 | K19: 42308 | L19: 43465 | M19: y | N19: =CONCATENATE(DATEDIF(K19,L19,"Y"),"y ",DATEDIF(K19+(360*(DATEDIF(K19,L19,"Y"))),L19,"M"),"m ",DATEDIF(K19+(30.5*(DATEDIF(K19,L19,"M"))),L19,"D"),"d") -> #NUM! | O19: Ifugao | P19: Technical Services | Q19: Engineer III | R19: LFP | S19: 36409 | T19: JO020
A20: =A19+1 -> 13 | B20: Dalay-on | C20: Ivan Ley | D20: T | E20: 32955 | F20: =DATEDIF(E20,TODAY(),"Y") -> 36 | G20: M | H20: RA 1080 Civil Engineer | I20: Contract of Service | J20: 2 | K20: 42813 | L20: 43465 | M20: y | N20: =CONCATENATE(DATEDIF(K20,L20,"Y"),"y ",DATEDIF(K20+(360*(DATEDIF(K20,L20,"Y"))),L20,"M"),"m ",DATEDIF(K20+(30.5*(DATEDIF(K20,L20,"M"))),L20,"D"),"d") -> 1y 9m 12d | O20: Region | P20: Technical Services | Q20: Engineer II | R20: LFP | S20: 28417 | T20: JO039
A21: =A120+1 -> 15 | B21: Dangeo | C21: Delfin | D21: G | E21: 30375 | F21: =DATEDIF(E21,TODAY(),"Y") -> 43 | G21: M | H21: None | I21: Contract of Service | J21: 1 | K21: 42684 | L21: 43465 | M21: y | N21: =CONCATENATE(DATEDIF(K21,L21,"Y"),"y ",DATEDIF(K21+(360*(DATEDIF(K21,L21,"Y"))),L21,"M"),"m ",DATEDIF(K21+(30.5*(DATEDIF(K21,L21,"M"))),L21,"D"),"d") -> 2y 2m 19d | O21: Region | P21: Admin. Support Services | Q21: Driver | R21: Regular Funds | S21: 10833 | T21: JO032
A22: =A21+1 -> 16 | B22: Embargo | C22: Kennedy | D22: B | E22: 24088 | F22: =DATEDIF(E22,TODAY(),"Y") -> 60 | G22: M | H22: None | I22: Contract of Service | J22: 1 | K22: 42186 | L22: 43465 | M22: y | N22: =CONCATENATE(DATEDIF(K22,L22,"Y"),"y ",DATEDIF(K22+(360*(DATEDIF(K22,L22,"Y"))),L22,"M"),"m ",DATEDIF(K22+(30.5*(DATEDIF(K22,L22,"M"))),L22,"D"),"d") -> 3y 6m 29d | O22: Kalinga | P22: Security Services | Q22: Watchman | R22: Regular Funds | S22: 9478 | T22: JO014
A23: =A22+1 -> 17 | B23: Francia | C23: Judith | D23: C | E23: 24617 | F23: =DATEDIF(E23,TODAY(),"Y") -> 58 | G23: F | H23: None | I23: Contract of Service | J23: 1 | K23: 40483 | L23: 43465 | M23: y | N23: =CONCATENATE(DATEDIF(K23,L23,"Y"),"y ",DATEDIF(K23+(360*(DATEDIF(K23,L23,"Y"))),L23,"M"),"m ",DATEDIF(K23+(30.5*(DATEDIF(K23,L23,"M"))),L23,"D"),"d") -> 8y 3m 24d | O23: Region | P23: Janitorial Services | Q23: Cottage Caretaker | R23: Regular Funds | S23: 9478 | T23: JO010
A24: =A23+1 -> 18 | B24: Garnace | C24: Baldo | D24: N | F24: =DATEDIF(E24,TODAY(),"Y") -> 126 | G24: M | H24: None | I24: Contract of Service | J24: 2 | K24: 42922 | L24: 43465 | M24: y | N24: =CONCATENATE(DATEDIF(K24,L24,"Y"),"y ",DATEDIF(K24+(360*(DATEDIF(K24,L24,"Y"))),L24,"M"),"m ",DATEDIF(K24+(30*(DATEDIF(K24,L24,"M"))),L24,"D"),"d") -> 1y 5m 33d | O24: Region | P24: ADM Technical Support | Q24: RPMT PDO | R24: BUB/ADM | S24: 39151 | T24: JO050
A25: =A24+1 -> 19 | B25: Gatawa | C25: Jovany | D25: D | E25: 34105 | F25: =DATEDIF(E25,TODAY(),"Y") -> 32 | G25: M | H25: RA 1080 Civil Engineer | I25: Contract of Service | J25: 2 | K25: 42857 | L25: 43465 | M25: y | N25: =CONCATENATE(DATEDIF(K25,L25,"Y"),"y ",DATEDIF(K25+(360*(DATEDIF(K25,L25,"Y"))),L25,"M"),"m ",DATEDIF(K25+(30.5*(DATEDIF(K25,L25,"M"))),L25,"D"),"d") -> 1y 8m 29d | O25: Region | P25: Technical Services | Q25: Engineer II | R25: LFP | S25: 28417 | T25: JO041
A26: =A25+1 -> 20 | B26: Gernale | C26: Joe Pablo | D26: M | E26: 34289 | F26: =DATEDIF(E26,TODAY(),"Y") -> 32 | G26: M | H26: Professional | I26: Contract of Service | J26: 1 | K26: 42537 | L26: 43465 | M26: y | N26: =CONCATENATE(DATEDIF(K26,L26,"Y"),"y ",DATEDIF(K26+(360*(DATEDIF(K26,L26,"Y"))),L26,"M"),"m ",DATEDIF(K26+(30*(DATEDIF(K26,L26,"M"))),L26,"D"),"d") -> 2y 6m 28d | O26: Region | P26: Clerical Services | Q26: Clerk | R26: Regular Funds | S26: 11658 | T26: JO023
A27: =A26+1 -> 21 | B27: Haboc | C27: Felimon | D27: L | E27: 24168 | F27: =DATEDIF(E27,TODAY(),"Y") -> 60 | G27: M | H27: None | I27: Contract of Service | J27: 1 | K27: 42598 | L27: 43465 | M27: y | N27: =CONCATENATE(DATEDIF(K27,L27,"Y"),"y ",DATEDIF(K27+(360*(DATEDIF(K27,L27,"Y"))),L27,"M"),"m ",DATEDIF(K27+(30*(DATEDIF(K27,L27,"M"))),L27,"D"),"d") -> 2y 4m 27d | O27: Kalinga | P27: Admin. Support Services | Q27: Driver | R27: Regular Funds | S27: 10833 | T27: JO027
A28: =A27+1 -> 22 | B28: Khayad | C28: Ivy Rose | D28: A | E28: 32227 | F28: =DATEDIF(E28,TODAY(),"Y") -> 37 | G28: F | H28: RA 1080 Civil Engineer | I28: Contract of Service | J28: 2 | K28: 42186 | L28: 43465 | M28: y | N28: =CONCATENATE(DATEDIF(K28,L28,"Y"),"y ",DATEDIF(K28+(360*(DATEDIF(K28,L28,"Y"))),L28,"M"),"m ",DATEDIF(K28+(30.5*(DATEDIF(K28,L28,"M"))),L28,"D"),"d") -> 3y 6m 29d | O28: Mt. Province | P28: Technical Services | Q28: Engineer III | R28: LFP | S28: 36409 | T28: JO015
A29: =A28+1 -> 23 | B29: Kibod | C29: Diego | D29: F | E29: 27484 | F29: =DATEDIF(E29,TODAY(),"Y") -> 50 | G29: M | H29: None | I29: Contract of Service | J29: 1 | K29: 42339 | L29: 43465 | M29: y | N29: =CONCATENATE(DATEDIF(K29,L29,"Y"),"y ",DATEDIF(K29+(360*(DATEDIF(K29,L29,"Y"))),L29,"M"),"m ",DATEDIF(K29+(30.5*(DATEDIF(K29,L29,"M"))),L29,"D"),"d") -> 3y 1m 28d | O29: Benguet | P29: Admin. Support Services | Q29: Driver | R29: Regular Funds | S29: 10833 | T29: JO022
A30: =A29+1 -> 24 | B30: Lagazo | C30: Annabelle | E30: 29448 | F30: =DATEDIF(E30,TODAY(),"Y") -> 45 | G30: F | H30: RA 1080 Sanitary Engineer | I30: Contract of Service | J30: 2 | K30: 42818 | L30: 43465 | M30: y | N30: =CONCATENATE(DATEDIF(K30,L30,"Y"),"y ",DATEDIF(K30+(360*(DATEDIF(K30,L30,"Y"))),L30,"M"),"m ",DATEDIF(K30+(30.5*(DATEDIF(K30,L30,"M"))),L30,"D"),"d") -> 1y 9m 7d | O30: Region | P30: Technical Services | Q30: Engineer II | R30: Regular Funds | S30: 28417 | T30: JO040
A31: =A30+1 -> 25 | B31: Lawagan | C31: Wilner | D31: C | E31: 32575 | F31: =DATEDIF(E31,TODAY(),"Y") -> 37 | G31: M | H31: None | I31: Contract of Service | J31: 1 | K31: 42614 | L31: 43465 | M31: y | N31: =CONCATENATE(DATEDIF(K31,L31,"Y"),"y ",DATEDIF(K31+(360*(DATEDIF(K31,L31,"Y"))),L31,"M"),"m ",DATEDIF(K31+(30.5*(DATEDIF(K31,L31,"M"))),L31,"D"),"d") -> 2y 4m 28d | O31: Mt. Province | P31: Admin. Support Services | Q31: Driver | R31: Regular Funds | S31: 10833 | T31: JO029
A32: =A31+1 -> 26 | B32: Macli-ing | C32: Giezzel | D32: D | E32: 35092 | F32: =DATEDIF(E32,TODAY(),"Y") -> 30 | G32: F | H32: Professional | I32: Contract of Service | J32: 1 | K32: 42676 | L32: 43465 | M32: y | N32: =CONCATENATE(DATEDIF(K32,L32,"Y"),"y ",DATEDIF(K32+(360*(DATEDIF(K32,L32,"Y"))),L32,"M"),"m ",DATEDIF(K32+(30.5*(DATEDIF(K32,L32,"M"))),L32,"D"),"d") -> 2y 2m 27d | O32: Region | P32: Clerical Services | Q32: Clerk | R32: Regular Funds | S32: 11658 | T32: JO031
A33: =A32+1 -> 27 | B33: Miclat | C33: Reymarson | D33: P | E33: 32247 | F33: =DATEDIF(E33,TODAY(),"Y") -> 37 | G33: M | H33: None | I33: Contract of Service | J33: 2 | K33: 42871 | L33: 43465 | M33: y | N33: =CONCATENATE(DATEDIF(K33,L33,"Y"),"y ",DATEDIF(K33+(360*(DATEDIF(K33,L33,"Y"))),L33,"M"),"m ",DATEDIF(K33+(30.5*(DATEDIF(K33,L33,"M"))),L33,"D"),"d") -> 1y 7m 15d | O33: Benguet | P33: Assistance to Municipalities | Q33: CDO II | R33: BUB/ADM | S33: 28417 | T33: JO045
A34: =A33+1 -> 28 | B34: Moyaen | C34: Ariel | D34: P | E34: 28353 | F34: =DATEDIF(E34,TODAY(),"Y") -> 48 | G34: M | H34: RA 1080 Civil Engineer | I34: Contract of Service | J34: 2 | K34: 41325 | L34: 43465 | M34: y | N34: =CONCATENATE(DATEDIF(K34,L34,"Y"),"y ",DATEDIF(K34+(360*(DATEDIF(K34,L34,"Y"))),L34,"M"),"m ",DATEDIF(K34+(30.5*(DATEDIF(K34,L34,"M"))),L34,"D"),"d") -> 5y 11m 5d | O34: Region | P34: Technical Services | Q34: Engineer III | R34: LFP | S34: 36409 | T34: JO011
A35: =A34+1 -> 29 | B35: Moyaen | C35: Carmen | D35: G | E35: 30513 | F35: =DATEDIF(E35,TODAY(),"Y") -> 42 | G35: F | H35: Social Worker | I35: Contract of Service | J35: 2 | K35: 42922 | L35: 43465 | M35: y | N35: =CONCATENATE(DATEDIF(K35,L35,"Y"),"y ",DATEDIF(K35+(360*(DATEDIF(K35,L35,"Y"))),L35,"M"),"m ",DATEDIF(K35+(30*(DATEDIF(K35,L35,"M"))),L35,"D"),"d") -> 1y 5m 33d | O35: Region | P35: ADM Technical Support | Q35: RPMT Team Leader | R35: BUB/ADM | S35: 39151 | T35: JO049
A36: =A35+1 -> 30 | B36: Octaviano | C36: Julie Rose | D36: A | E36: 32633 | F36: =DATEDIF(E36,TODAY(),"Y") -> 36 | G36: F | H36: RA 1080 CPA | I36: Contract of Service | J36: 2 | K36: 42857 | L36: 43465 | M36: y | N36: =CONCATENATE(DATEDIF(K36,L36,"Y"),"y ",DATEDIF(K36+(360*(DATEDIF(K36,L36,"Y"))),L36,"M"),"m ",DATEDIF(K36+(30.5*(DATEDIF(K36,L36,"M"))),L36,"D"),"d") -> 1y 8m 29d | O36: Region | P36: Admin. Support Services | Q36: Financial Analyst | R36: LFP | S36: 36409 | T36: JO034
A37: =A121+1 -> 32 | B37: Samson | C37: Aljon Paulus | D37: M | E37: 32748 | F37: =DATEDIF(E37,TODAY(),"Y") -> 36 | G37: M | H37: None | I37: Contract of Service | J37: 2 | K37: 42857 | L37: 43465 | M37: y | N37: =CONCATENATE(DATEDIF(K37,L37,"Y"),"y ",DATEDIF(K37+(360*(DATEDIF(K37,L37,"Y"))),L37,"M"),"m ",DATEDIF(K37+(30.5*(DATEDIF(K37,L37,"M"))),L37,"D"),"d") -> 1y 8m 29d | O37: Region | P37: Operations Support Services | Q37: DB Administrator | R37: ISTMS | S37: 30000 | T37: JO043
A38: =A37+1 -> 33 | B38: Siador | C38: Arlyn | D38: C | E38: 29664 | F38: =DATEDIF(E38,TODAY(),"Y") -> 45 | G38: F | H38: Sub-Professional | I38: Contract of Service | J38: 1 | K38: 42537 | L38: 43465 | M38: y | N38: =CONCATENATE(DATEDIF(K38,L38,"Y"),"y ",DATEDIF(K38+(360*(DATEDIF(K38,L38,"Y"))),L38,"M"),"m ",DATEDIF(K38+(30*(DATEDIF(K38,L38,"M"))),L38,"D"),"d") -> 2y 6m 28d | O38: Region | P38: Clerical Services | Q38: Clerk | R38: Regular Funds | S38: 11658 | T38: JO024
A39: =A38+1 -> 34 | B39: Taclawan | C39: Clifford | D39: B | E39: 26497 | F39: =DATEDIF(E39,TODAY(),"Y") -> 53 | G39: M | H39: None | I39: Contract of Service | J39: 1 | K39: 42186 | L39: 43465 | M39: y | N39: =CONCATENATE(DATEDIF(K39,L39,"Y"),"y ",DATEDIF(K39+(360*(DATEDIF(K39,L39,"Y"))),L39,"M"),"m ",DATEDIF(K39+(30.5*(DATEDIF(K39,L39,"M"))),L39,"D"),"d") -> 3y 6m 29d | O39: Kalinga | P39: Security Services | Q39: Watchman | R39: Regular Funds | S39: 9478 | T39: JO016
A40: =A39+1 -> 35 | B40: Talusig | C40: Trinidad | D40: C | E40: 25123 | F40: =DATEDIF(E40,TODAY(),"Y") -> 57 | G40: F | H40: None | I40: Contract of Service | J40: 1 | K40: 41372 | L40: 43465 | M40: y | N40: =CONCATENATE(DATEDIF(K40,L40,"Y"),"y ",DATEDIF(K40+(360*(DATEDIF(K40,L40,"Y"))),L40,"M"),"m ",DATEDIF(K40+(30*(DATEDIF(K40,L40,"M"))),L40,"D"),"d") -> 5y 9m 53d | O40: Region | P40: Janitorial Services | Q40: Utility/Janitor | R40: Regular Funds | S40: 9478 | T40: JO012
A41: =A40+1 -> 36 | B41: Tekwaban | C41: Patrick | D41: B | E41: 32206 | F41: =DATEDIF(E41,TODAY(),"Y") -> 38 | G41: M | H41: RA 1080 Civil Engineer | I41: Contract of Service | J41: 2 | K41: 42310 | L41: 43465 | M41: y | N41: =CONCATENATE(DATEDIF(K41,L41,"Y"),"y ",DATEDIF(K41+(360*(DATEDIF(K41,L41,"Y"))),L41,"M"),"m ",DATEDIF(K41+(30*(DATEDIF(K41,L41,"M"))),L41,"D"),"d") -> 3y 2m 45d | O41: Benguet | P41: Technical Services | Q41: Engineer III | R41: LFP | S41: 36409 | T41: JO021
A42: =A41+1 -> 37 | B42: Villaflor | C42: Nino Boyet | D42: F | E42: 34046 | F42: =DATEDIF(E42,TODAY(),"Y") -> 33 | G42: M | H42: None | I42: Contract of Service | J42: 1 | K42: 42758 | L42: 43465 | M42: y | N42: =CONCATENATE(DATEDIF(K42,L42,"Y"),"y ",DATEDIF(K42+(360*(DATEDIF(K42,L42,"Y"))),L42,"M"),"m ",DATEDIF(K42+(30*(DATEDIF(K42,L42,"M"))),L42,"D"),"d") -> 1y 11m 17d | O42: Apayao | P42: Security Services | Q42: Watchman | R42: Regular Funds | S42: 9478 | T42: JO036
A43: =+A118+1 -> 61 | B43: BIANGALEN | C43: Junnel | D43: F | E43: 33045 | F43: =DATEDIF(E43,TODAY(),"Y") -> 35 | G43: M | H43: None | I43: Contract of Service | J43: 1 | K43: 42923 | L43: 43465 | M43: y | N43: =CONCATENATE(DATEDIF(K43,L43,"Y"),"y ",DATEDIF(K43+(360*(DATEDIF(K43,L43,"Y"))),L43,"M"),"m ",DATEDIF(K43+(30*(DATEDIF(K43,L43,"M"))),L43,"D"),"d") -> 1y 5m 32d | O43: Baguio | P43: Admin. Support Services | Q43: Utility/Janitor | R43: Regular Funds | S43: 9478 | T43: JO077
A44: =+A43+1 -> 62 | B44: ALAGAO | C44: Jesus Fernan | D44: A. | F44: =DATEDIF(E44,TODAY(),"Y") -> 126 | G44: M | I44: Contract of Service | J44: 1 | K44: 43024 | L44: 43465 | M44: y | N44: =CONCATENATE(DATEDIF(K44,L44,"Y"),"y ",DATEDIF(K44+(360*(DATEDIF(K44,L44,"Y"))),L44,"M"),"m ",DATEDIF(K44+(30*(DATEDIF(K44,L44,"M"))),L44,"D"),"d") -> 1y 2m 21d | O44: Abra | P44: Assistance to Municipalities | Q44: Community Devt Officer III | R44: BUB/ADM | S44: 35693 | T44: JO078
A45: =+A44+1 -> 63 | B45: ANGWANI | C45: Michelle | D45: P | F45: =DATEDIF(E45,TODAY(),"Y") -> 126 | G45: F | I45: Contract of Service | J45: 2 | K45: 43024 | L45: 43465 | M45: y | N45: =CONCATENATE(DATEDIF(K45,L45,"Y"),"y ",DATEDIF(K45+(360*(DATEDIF(K45,L45,"Y"))),L45,"M"),"m ",DATEDIF(K45+(30*(DATEDIF(K45,L45,"M"))),L45,"D"),"d") -> 1y 2m 21d | O45: Mt. Province | P45: Assistance to Municipalities | Q45: Community Devt Officer III | R45: BUB/ADM | S45: 35693 | T45: JO079
A46: =+A26+1 -> 21 | B46: KITONG | C46: ANGELIE | D46: S | F46: =DATEDIF(E46,TODAY(),"Y") -> 126 | G46: F | I46: Contract of Service | J46: 2 | K46: 43024 | L46: 43465 | M46: y | N46: =CONCATENATE(DATEDIF(K46,L46,"Y"),"y ",DATEDIF(K46+(360*(DATEDIF(K46,L46,"Y"))),L46,"M"),"m ",DATEDIF(K46+(30*(DATEDIF(K46,L46,"M"))),L46,"D"),"d") -> 1y 2m 21d | O46: Apayao | P46: Assistance to Municipalities | Q46: Community Devt Officer II | R46: BUB/ADM | S46: 27565 | T46: JO080
A47: =+A46+1 -> 22 | B47: AREOLA | C47: Mayjoy | D47: S | F47: =DATEDIF(E47,TODAY(),"Y") -> 126 | G47: F | H47: RA1080 Nursing | I47: Contract of Service | J47: 2 | K47: 43024 | L47: 43465 | M47: y | N47: =CONCATENATE(DATEDIF(K47,L47,"Y"),"y ",DATEDIF(K47+(360*(DATEDIF(K47,L47,"Y"))),L47,"M"),"m ",DATEDIF(K47+(30*(DATEDIF(K47,L47,"M"))),L47,"D"),"d") -> 1y 2m 21d | O47: Apayao | P47: Assistance to Municipalities | Q47: Community Devt Officer III | R47: BUB/ADM | S47: 35693 | T47: JO081
A48: =+A47+1 -> 23 | B48: GAMATERO | C48: ENGELBERT JACK | D48: B | F48: =DATEDIF(E48,TODAY(),"Y") -> 126 | G48: M | I48: Contract of Service | J48: 2 | K48: 43024 | L48: 43465 | M48: y | N48: =CONCATENATE(DATEDIF(K48,L48,"Y"),"y ",DATEDIF(K48+(360*(DATEDIF(K48,L48,"Y"))),L48,"M"),"m ",DATEDIF(K48+(30*(DATEDIF(K48,L48,"M"))),L48,"D"),"d") -> 1y 2m 21d | O48: Kalinga | P48: Assistance to Municipalities | Q48: Community Devt Officer III | R48: BUB/ADM | S48: 35693 | T48: JO082
A49: =+A48+1 -> 24 | B49: ALLOPOG | C49: Cheryl | D49: D | F49: =DATEDIF(E49,TODAY(),"Y") -> 126 | G49: F | I49: Contract of Service | J49: 2 | K49: 43024 | L49: 43465 | M49: y | N49: =CONCATENATE(DATEDIF(K49,L49,"Y"),"y ",DATEDIF(K49+(360*(DATEDIF(K49,L49,"Y"))),L49,"M"),"m ",DATEDIF(K49+(30*(DATEDIF(K49,L49,"M"))),L49,"D"),"d") -> 1y 2m 21d | O49: Abra | P49: Assistance to Municipalities | Q49: Community Devt Officer II | R49: BUB/ADM | S49: 27565 | T49: JO083
A50: =+A49+1 -> 25 | B50: ALANGUI | C50: Karl Mico | D50: D | F50: =DATEDIF(E50,TODAY(),"Y") -> 126 | G50: M | I50: Contract of Service | J50: 2 | K50: 43024 | L50: 43465 | M50: y | N50: =CONCATENATE(DATEDIF(K50,L50,"Y"),"y ",DATEDIF(K50+(360*(DATEDIF(K50,L50,"Y"))),L50,"M"),"m ",DATEDIF(K50+(30*(DATEDIF(K50,L50,"M"))),L50,"D"),"d") -> 1y 2m 21d | O50: Benguet | P50: Assistance to Municipalities | Q50: Community Devt Officer III | R50: BUB/ADM | S50: 35693 | T50: JO084
A51: =+A50+1 -> 26 | B51: CABBIGAT | C51: Ramses | D51: G | F51: =DATEDIF(E51,TODAY(),"Y") -> 126 | G51: M | I51: Contract of Service | J51: 2 | K51: 43024 | L51: 43465 | M51: y | N51: =CONCATENATE(DATEDIF(K51,L51,"Y"),"y ",DATEDIF(K51+(360*(DATEDIF(K51,L51,"Y"))),L51,"M"),"m ",DATEDIF(K51+(30*(DATEDIF(K51,L51,"M"))),L51,"D"),"d") -> 1y 2m 21d | O51: Ifugao | P51: Assistance to Municipalities | Q51: Community Devt Officer III | R51: BUB/ADM | S51: 35693 | T51: JO085
A52: =+A51+1 -> 27 | B52: LIM-ANG | C52: Lynette Rochelle | D52: C | F52: =DATEDIF(E52,TODAY(),"Y") -> 126 | G52: F | I52: Contract of Service | J52: 2 | K52: 43024 | L52: 43465 | M52: y | N52: =CONCATENATE(DATEDIF(K52,L52,"Y"),"y ",DATEDIF(K52+(360*(DATEDIF(K52,L52,"Y"))),L52,"M"),"m ",DATEDIF(K52+(30*(DATEDIF(K52,L52,"M"))),L52,"D"),"d") -> 1y 2m 21d | O52: Ifugao | P52: Assistance to Municipalities | Q52: Community Devt Officer II | R52: BUB/ADM | S52: 27565 | T52: JO086
A53: =+A52+1 -> 28 | B53: LEAL | C53: Lily | D53: D | F53: =DATEDIF(E53,TODAY(),"Y") -> 126 | G53: F | I53: Contract of Service | J53: 2 | K53: 43024 | L53: 43465 | M53: y | N53: =CONCATENATE(DATEDIF(K53,L53,"Y"),"y ",DATEDIF(K53+(360*(DATEDIF(K53,L53,"Y"))),L53,"M"),"m ",DATEDIF(K53+(30*(DATEDIF(K53,L53,"M"))),L53,"D"),"d") -> 1y 2m 21d | O53: Kalinga | P53: Assistance to Municipalities | Q53: Community Devt Officer II | R53: BUB/ADM | S53: 27565 | T53: JO087
A54: =+A53+1 -> 29 | B54: NASUNGAN | C54: Giovanni | D54: A | F54: =DATEDIF(E54,TODAY(),"Y") -> 126 | G54: M | I54: Contract of Service | J54: 2 | K54: 43024 | L54: 43465 | M54: y | N54: =CONCATENATE(DATEDIF(K54,L54,"Y"),"y ",DATEDIF(K54+(360*(DATEDIF(K54,L54,"Y"))),L54,"M"),"m ",DATEDIF(K54+(30*(DATEDIF(K54,L54,"M"))),L54,"D"),"d") -> 1y 2m 21d | O54: Mt. Province | P54: Assistance to Municipalities | Q54: Community Devt Officer II | R54: BUB/ADM | S54: 27565 | T54: JO088
A55: =+A54+1 -> 30 | F55: =DATEDIF(E55,TODAY(),"Y") -> 126 | M55: y | N55: =CONCATENATE(DATEDIF(K55,L55,"Y"),"y ",DATEDIF(K55+(360*(DATEDIF(K55,L55,"Y"))),L55,"M"),"m ",DATEDIF(K55+(30*(DATEDIF(K55,L55,"M"))),L55,"D"),"d") -> 0y 0m 0d | T55: JO089
A56: =+A55+1 -> 31 | F56: =DATEDIF(E56,TODAY(),"Y") -> 126 | I56: Contract of Service | M56: y | N56: =CONCATENATE(DATEDIF(K56,L56,"Y"),"y ",DATEDIF(K56+(360*(DATEDIF(K56,L56,"Y"))),L56,"M"),"m ",DATEDIF(K56+(30*(DATEDIF(K56,L56,"M"))),L56,"D"),"d") -> 0y 0m 0d | T56: JO090
A57: =+A56+1 -> 32 | B57: LABADCHAN | C57: AISHA | D57: D | E57: 34261 | F57: =DATEDIF(E57,TODAY(),"Y") -> 32 | G57: F | I57: Contract of Service | J57: 1 | K57: 43023 | L57: 43465 | M57: y | N57: =CONCATENATE(DATEDIF(K57,L57,"Y"),"y ",DATEDIF(K57+(360*(DATEDIF(K57,L57,"Y"))),L57,"M"),"m ",DATEDIF(K57+(30*(DATEDIF(K57,L57,"M"))),L57,"D"),"d") -> 1y 2m 22d | O57: Region | P57: Admin. Support Services | Q57: ADA IV | R57: Regular Funds | S57: 11658 | T57: JO091
A58: =+A122+1 -> 34 | B58: DULLIN | C58: IRENE | D58: L | E58: 28226 | F58: =DATEDIF(E58,TODAY(),"Y") -> 48 | G58: F | H58: None | I58: Contract of Service | J58: 1 | K58: 43070 | L58: 43465 | M58: y | N58: =CONCATENATE(DATEDIF(K58,L58,"Y"),"y ",DATEDIF(K58+(360*(DATEDIF(K58,L58,"Y"))),L58,"M"),"m ",DATEDIF(K58+(30*(DATEDIF(K58,L58,"M"))),L58,"D"),"d") -> 1y 1m 35d | O58: Region | P58: Admin. Support Services | Q58: Utility/Janitor | R58: Regular Funds | S58: 9478 | T58: JO094
A59: =+A58+1 -> 35 | B59: BLANDO | C59: CARLITO | D59: A | E59: 24381 | F59: =DATEDIF(E59,TODAY(),"Y") -> 59 | G59: M | H59: None | I59: Contract of Service | J59: 1 | K59: 43057 | L59: 43465 | M59: y | N59: =CONCATENATE(DATEDIF(K59,L59,"Y"),"y ",DATEDIF(K59+(360*(DATEDIF(K59,L59,"Y"))),L59,"M"),"m ",DATEDIF(K59+(30*(DATEDIF(K59,L59,"M"))),L59,"D"),"d") -> 1y 1m 18d | O59: Abra | P59: Admin. Support Services | Q59: Driver | R59: Regular Funds | S59: 10833 | T59: JO095
A60: =+A59+1 -> 36 | B60: abra | F60: =DATEDIF(E60,TODAY(),"Y") -> 126 | G60: M | I60: Contract of Service | J60: 1 | L60: 43465 | M60: y | N60: =CONCATENATE(DATEDIF(K60,L60,"Y"),"y ",DATEDIF(K60+(360*(DATEDIF(K60,L60,"Y"))),L60,"M"),"m ",DATEDIF(K60+(30*(DATEDIF(K60,L60,"M"))),L60,"D"),"d") -> 118y 32m 655d | O60: Abra | Q60: Utility/Janitor | R60: Regular Funds | S60: 9478 | T60: JO096
A61: =+A60+1 -> 37 | B61: DONG-LA | C61: JOECLE | D61: R | E61: 28527 | F61: =DATEDIF(E61,TODAY(),"Y") -> 48 | G61: M | I61: Contract of Service | J61: 2 | K61: 43412 | L61: 43465 | M61: y | N61: =CONCATENATE(DATEDIF(K61,L61,"Y"),"y ",DATEDIF(K61+(360*(DATEDIF(K61,L61,"Y"))),L61,"M"),"m ",DATEDIF(K61+(30*(DATEDIF(K61,L61,"M"))),L61,"D"),"d") -> 0y 1m 23d | O61: Region | P61: Legal Services | Q61: ATTY IV | R61: Regular Funds | S61: 58++ | T61: JO097
A62: =+A61+1 -> 38 | B62: BOGNADON | C62: Kylee Russel | D62: B | E62: 35154 | F62: =DATEDIF(E62,TODAY(),"Y") -> 29 | G62: M | I62: Contract of Service | J62: 1 | K62: 43116 | L62: 43465 | M62: y | N62: =CONCATENATE(DATEDIF(K62,L62,"Y"),"y ",DATEDIF(K62+(360*(DATEDIF(K62,L62,"Y"))),L62,"M"),"m ",DATEDIF(K62+(30*(DATEDIF(K62,L62,"M"))),L62,"D"),"d") -> 0y 11m 19d | O62: Region | P62: Admin. Support Services | Q62: ADA IV | R62: Regular Funds | S62: 11658 | T62: JO098
A63: 26 | B63: Mandras | C63: Luisito | D63: N | E63: 29283 | F63: 37 | G63: M | H63: None | I63: Contract of Service | J63: 1 | K63: 43103 | L63: 43465 | M63: y | N63: =CONCATENATE(DATEDIF(K63,L63,"Y"),"y ",DATEDIF(K63+(360*(DATEDIF(K63,L63,"Y"))),L63,"M"),"m ",DATEDIF(K63+(30*(DATEDIF(K63,L63,"M"))),L63,"D"),"d") -> 0y 11m 32d | O63: Region | P63: Janitorial Services | Q63: Utility/Janitor | R63: Regular Funds | S63: 10883 | T63: JO042 | U63: 42870 | V63: for recontracting once the nene pimentel hall is ready
A64: 4 | B64: Ambuyat | C64: Melchor | D64: D | E64: 25553 | F64: =DATEDIF(E64,TODAY(),"Y") -> 56 | G64: M | H64: None | I64: COS | J64: 1 | K64: 43101 | L64: 43281 | N64: =CONCATENATE(DATEDIF(K64,L64,"Y"),"y",DATEDIF(K64+(360*(DATEDIF(K64,L64,"Y"))),L64,"M"),"m ",DATEDIF(K64+(30*(DATEDIF(K64,L64,"M"))),L64,"D"),"d") -> 0y5m 30d | O64: Abra | P64: Utility Worker | Q64: Utility/Janitor | S64: 9981 | T64: JO092
A65: 12 | B65: Bulligan | C65: Luis Jr. | D65: G | E65: 30163 | F65: =DATEDIF(E65,TODAY(),"Y") -> 43 | G65: M | H65: None | I65: COS | J65: 1 | K65: 43105 | L65: 43281 | N65: =CONCATENATE(DATEDIF(K65,L65,"Y"),"y",DATEDIF(K65+(360*(DATEDIF(K65,L65,"Y"))),L65,"M"),"m ",DATEDIF(K65+(30*(DATEDIF(K65,L65,"M"))),L65,"D"),"d") -> 0y5m 26d | P65: Admin. Support Services | Q65: Driver | S65: 11837 | T65: JO100
A66: 21 | B66: Dongla | C66: Joecle | D66: R | E66: 28527 | F66: =DATEDIF(E66,TODAY(),"Y") -> 48 | G66: M | H66: BAR Exam | I66: COS | J66: 2 | K66: 43105 | L66: 43281 | N66: =CONCATENATE(DATEDIF(K66,L66,"Y"),"y ",DATEDIF(K66+(360*(DATEDIF(K66,L66,"Y"))),L66,"M"),"m ",DATEDIF(K66+(30*(DATEDIF(K66,L66,"M"))),L66,"D"),"d") -> 0y 5m 26d | P66: Technical Services | Q66: Atty. IV | S66: 58310 | T66: JO097
A67: 44 | B67: Parrocha | C67: Reynold | D67: L | E67: 33760 | F67: =DATEDIF(E67,TODAY(),"Y") -> 33 | G67: M | I67: COS | J67: 1 | K67: 43193 | L67: 43371 | N67: =CONCATENATE(DATEDIF(K67,L67,"Y"),"y ",DATEDIF(K67+(360*(DATEDIF(K67,L67,"Y"))),L67,"M"),"m ",DATEDIF(K67+(30*(DATEDIF(K67,L67,"M"))),L67,"D"),"d") -> 0y 5m 28d | P67: Utility Worker | Q67: Utility/Janitor | S67: 9981 | T67: JO101
A68: 50 | B68: Tayaban | C68: Irene | D68: C | E68: 22960 | F68: =DATEDIF(E68,TODAY(),"Y") -> 63 | G68: F | H68: None | I68: COS | J68: 1 | K68: 43160 | L68: 43281 | N68: =CONCATENATE(DATEDIF(K68,L68,"Y"),"y ",DATEDIF(K68+(360*(DATEDIF(K68,L68,"Y"))),L68,"M"),"m ",DATEDIF(K68+(30*(DATEDIF(K68,L68,"M"))),L68,"D"),"d") -> 0y 3m 31d | P68: Utility Worker | Q68: Utility/Janitor | S68: 9981 | T68: JO102
A69: Prepared by
E70: overall | F70: M | G70: =COUNTIF(sexjo,"M") -> 36 | H70: =SUM(G70:G71) -> 54 | S70: a
F71: F | G71: =COUNTIF(sexjo,"f") -> 18
A72: NORMAN I. BARNACHEA | E72: 2nd level | F72: M | G72: =COUNTIFS(sexjo,F72,leveljo,2) -> 17 | H72: =SUM(G72:G75) -> 54
A73: Admiistrative Officer V | F73: F | G73: =COUNTIFS(sexjo,F73,leveljo,2) -> 12
E74: 1st level | F74: M | G74: =COUNTIFS(sexjo,F74,leveljo,1) -> 19
F75: F | G75: =COUNTIFS(sexjo,F75,leveljo,1) -> 6
T81: Id number
A82: 9 | B82: Dolaoen | C82: Osborne | D82: P | E82: 27125 | F82: 42 | G82: M | H82: RA 1080 Civil Engineer | I82: COS | K82: 41932 | L82: 42719 | N82: 2y 2m 37d | O82: Abra | P82: Technical Services | Q82: Engineer III | U82: 42735 | V82: resigned
A83: 15 | B83: Inocente | C83: Jay | D83: B | E83: 34145 | F83: 23 | G83: M | H83: Sub-Professional | I83: COS | K83: 42536 | L83: 42719 | N83: 0y 6m 3d | O83: Apayao | P83: Security Services | Q83: Watchman | U83: 42735 | V83: resigned
A84: 21 | B84: Mordido | C84: Lorenzo | D84: C | E84: 25536 | F84: 47 | G84: M | H84: None | I84: COS | K84: 42401 | L84: 42719 | N84: 0y 10m 18d | O84: Region | P84: Janitorial Services | Q84: Utility/Gardener | U84: 42735 | V84: not renewed
A85: 25 | B85: Pultz | C85: Chandolph | D85: S | E85: 34347 | F85: 23 | G85: M | H85: None | I85: COS | K85: 41518 | L85: 42719 | N85: 3y 3m 31d | O85: Region | P85: Janitorial Services | Q85: Utility/Janitor | U85: 42735 | V85: not renewed
A86: 19 | B86: Madalang | C86: Renz Audrey | D86: A | E86: 32954 | F86: =DATEDIF(E86,TODAY(),"Y") -> 36 | G86: F | H86: RA 1080 CPA | I86: COS | J86: 2 | K86: 42125 | L86: 42719 | M86: 42736 | N86: =CONCATENATE(DATEDIF(K86,L86,"Y"),"y ",DATEDIF(K86+(360*(DATEDIF(K86,L86,"Y"))),L86,"M"),"m ",DATEDIF(K86+(30*(DATEDIF(K86,L86,"M"))),L86,"D"),"d") -> 1y 7m 24d | O86: Region | P86: Admin. Support Services | Q86: Financial Analyst | U86: 42800
A87: 22 | B87: Piluden | C87: Kareen | D87: L | E87: 31172 | F87: =DATEDIF(E87,TODAY(),"Y") -> 40 | G87: F | H87: Professional | I87: COS | J87: 1 | K87: 42676 | L87: 42719 | M87: 42736 | N87: =CONCATENATE(DATEDIF(K87,L87,"Y"),"y ",DATEDIF(K87+(360*(DATEDIF(K87,L87,"Y"))),L87,"M"),"m ",DATEDIF(K87+(30*(DATEDIF(K87,L87,"M"))),L87,"D"),"d") -> 0y 1m 13d | O87: Region | P87: Clerical Services | Q87: Clerk | U87: 42857 | V87: Resigned
A88: 30 | B88: Pongas | C88: Mike Burton | D88: M | E88: 32614 | F88: =DATEDIF(E88,TODAY(),"Y") -> 36 | G88: M | H88: RA 1080 Bar | I88: COS | J88: 2 | K88: 42751 | L88: new 2017 | N88: N/A | O88: Region | P88: Support to Operations | Q88: Atty II | T88: JO035 | U88: 42902 | V88: resigned
A89: 30 | B89: Pultz | C89: El-wood Duane | D89: L | E89: 27230 | F89: =DATEDIF(E89,TODAY(),"Y") -> 51 | G89: M | H89: None | I89: COS | J89: 1 | K89: 41649 | L89: 42719 | M89: 42736 | N89: =CONCATENATE(DATEDIF(K89,L89,"Y"),"y ",DATEDIF(K89+(360*(DATEDIF(K89,L89,"Y"))),L89,"M"),"m ",DATEDIF(K89+(30*(DATEDIF(K89,L89,"M"))),L89,"D"),"d") -> 2y 11m 20d | O89: Region | P89: Admin. Support Services | Q89: Driver | T89: JO013 | U89: 42891 | V89: Absorbed as CTO
A90: 15 | B90: Dupilpil | C90: Cherry | D90: D | E90: 27143 | F90: =DATEDIF(E90,TODAY(),"Y") -> 51 | G90: F | H90: None | I90: Contract of Service | J90: 1 | K90: 42688 | L90: 42932 | M90: 42736 | N90: =CONCATENATE(DATEDIF(K90,L90,"Y"),"y ",DATEDIF(K90+(360*(DATEDIF(K90,L90,"Y"))),L90,"M"),"m ",DATEDIF(K90+(30.5*(DATEDIF(K90,L90,"M"))),L90,"D"),"d") -> 0y 8m 0d | O90: Baguio | P90: Janitorial Services | Q90: Utility/Janitor | S90: 9478 | T90: JO033 | U90: 42916 | V90: not renewed
A91: 26 | B91: Mandras | C91: Luisito | D91: N | E91: 29283 | F91: =DATEDIF(E91,TODAY(),"Y") -> 46 | G91: M | H91: None | I91: Contract of Service | J91: 1 | K91: 42744 | L91: 42932 | N91: =CONCATENATE(DATEDIF(K91,L91,"Y"),"y ",DATEDIF(K91+(360*(DATEDIF(K91,L91,"Y"))),L91,"M"),"m ",DATEDIF(K91+(30.5*(DATEDIF(K91,L91,"M"))),L91,"D"),"d") -> 0y 6m 5d | O91: Region | P91: Janitorial Services | R91: Regular Funds | S91: 10883 | T91: JO042 | U91: 42870 | V91: for recontracting once the nene pimentel hall is ready | W91: OK | X91: 43101
A92: =A91+1 -> 27 | B92: Sison | C92: Michelle | D92: V | E92: 30417 | F92: =DATEDIF(E92,TODAY(),"Y") -> 42 | G92: F | H92: Sub-Professional | I92: Contract of Service | J92: 1 | K92: 42537 | L92: 42932 | M92: 42736 | N92: =CONCATENATE(DATEDIF(K92,L92,"Y"),"y ",DATEDIF(K92+(360*(DATEDIF(K92,L92,"Y"))),L92,"M"),"m ",DATEDIF(K92+(30*(DATEDIF(K92,L92,"M"))),L92,"D"),"d") -> 1y 1m 5d | O92: Region | P92: Clerical Services | Q92: Clerk | R92: Regular Funds | S92: 11658 | T92: JO025 | U92: 43028 | V92: Resigned
A93: =A92+1 -> 28 | B93: Bannawe | C93: Aubrey Keren Jill | D93: B | E93: 34199 | F93: =DATEDIF(E93,TODAY(),"Y") -> 32 | G93: F | H93: RA 1080 Architect | I93: Contract of Service | J93: 2 | K93: 42812 | L93: 42932 | M93: y | N93: =CONCATENATE(DATEDIF(K93,L93,"Y"),"y ",DATEDIF(K93+(360*(DATEDIF(K93,L93,"Y"))),L93,"M"),"m ",DATEDIF(K93+(30.5*(DATEDIF(K93,L93,"M"))),L93,"D"),"d") -> 0y 3m 29d | O93: Region | P93: Technical Services | Q93: Architect III | R93: Regular Funds | S93: 36409 | T93: JO038
A94: =A93+1 -> 29 | B94: Rimando | C94: Ronald | D94: C | E94: 32879 | F94: =DATEDIF(E94,TODAY(),"Y") -> 36 | G94: M | H94: None | I94: Contract of Service | J94: 1 | K94: 42874 | L94: 42932 | M94: Y | N94: =CONCATENATE(DATEDIF(K94,L94,"Y"),"y ",DATEDIF(K94+(360*(DATEDIF(K94,L94,"Y"))),L94,"M"),"m ",DATEDIF(K94+(30.5*(DATEDIF(K94,L94,"M"))),L94,"D"),"d") -> 0y 1m 28d | O94: Region | P94: Janitorial Services | Q94: Utility/Janitor | R94: Regular Funds | S94: 9478 | T94: JO046
A96: =+A42+1 -> 38 | B96: ALITA | C96: Jaysan | D96: B | E96: 34776 | F96: =DATEDIF(E96,TODAY(),"Y") -> 31 | G96: M | H96: None | I96: Contract of Service | J96: 2 | K96: 42948 | L96: 43100 | M96: Y | N96: =CONCATENATE(DATEDIF(K96,L96,"Y"),"y ",DATEDIF(K96+(360*(DATEDIF(K96,L96,"Y"))),L96,"M"),"m ",DATEDIF(K96+(30*(DATEDIF(K96,L96,"M"))),L96,"D"),"d") -> 0y 4m 32d | O96: Abra | P96: MasaMasid Tech Support | Q96: Community Facilitator | R96: Masa-Masid | S96: 30000 | T96: JO054
A97: =+A96+1 -> 39 | B97: BAGAYAO | C97: Clever | D97: C | E97: 33797 | F97: =DATEDIF(E97,TODAY(),"Y") -> 33 | G97: M | H97: None | I97: Contract of Service | J97: 2 | K97: 42948 | L97: 43100 | M97: Y | N97: =CONCATENATE(DATEDIF(K97,L97,"Y"),"y ",DATEDIF(K97+(360*(DATEDIF(K97,L97,"Y"))),L97,"M"),"m ",DATEDIF(K97+(30*(DATEDIF(K97,L97,"M"))),L97,"D"),"d") -> 0y 4m 32d | O97: Benguet | P97: MasaMasid Tech Support | Q97: Community Facilitator | R97: Masa-Masid | S97: 30001 | T97: JO055
A98: =+A97+1 -> 40 | B98: BAGUIDUDOL | C98: Noeliza | D98: B | E98: 34895 | F98: =DATEDIF(E98,TODAY(),"Y") -> 30 | G98: F | H98: RA6506 Criminology | I98: Contract of Service | J98: 2 | K98: 42948 | L98: 43100 | M98: Y | N98: =CONCATENATE(DATEDIF(K98,L98,"Y"),"y ",DATEDIF(K98+(360*(DATEDIF(K98,L98,"Y"))),L98,"M"),"m ",DATEDIF(K98+(30*(DATEDIF(K98,L98,"M"))),L98,"D"),"d") -> 0y 4m 32d | O98: Ifugao | P98: MasaMasid Tech Support | Q98: Community Facilitator | R98: Masa-Masid | S98: 30002 | T98: JO056
A99: =+A98+1 -> 41 | B99: BALDERAMA | C99: Antonio | D99: C | E99: 17986 | F99: =DATEDIF(E99,TODAY(),"Y") -> 76 | G99: M | H99: CS Professional | I99: Contract of Service | J99: 2 | K99: 42948 | L99: 43100 | M99: Y | N99: =CONCATENATE(DATEDIF(K99,L99,"Y"),"y ",DATEDIF(K99+(360*(DATEDIF(K99,L99,"Y"))),L99,"M"),"m ",DATEDIF(K99+(30*(DATEDIF(K99,L99,"M"))),L99,"D"),"d") -> 0y 4m 32d | O99: Apayao | P99: MasaMasid Tech Support | Q99: Community Facilitator | R99: Masa-Masid | S99: 30003 | T99: JO074
A100: =+A99+1 -> 42 | B100: BAÑEZ | C100: Jenniefer | D100: T | E100: 33253 | F100: =DATEDIF(E100,TODAY(),"Y") -> 35 | G100: F | H100: None | I100: Contract of Service | J100: 2 | K100: 42948 | L100: 43100 | M100: Y | N100: =CONCATENATE(DATEDIF(K100,L100,"Y"),"y ",DATEDIF(K100+(360*(DATEDIF(K100,L100,"Y"))),L100,"M"),"m ",DATEDIF(K100+(30*(DATEDIF(K100,L100,"M"))),L100,"D"),"d") -> 0y 4m 32d | O100: Abra | P100: MasaMasid Tech Support | Q100: Community Facilitator | R100: Masa-Masid | S100: 30004 | T100: JO057
A101: =+A100+1 -> 43 | B101: BARREYRO | C101: Eunice | D101: B | E101: 33042 | F101: =DATEDIF(E101,TODAY(),"Y") -> 35 | G101: F | H101: None | I101: Contract of Service | J101: 2 | K101: 42948 | L101: 43100 | M101: Y | N101: =CONCATENATE(DATEDIF(K101,L101,"Y"),"y ",DATEDIF(K101+(360*(DATEDIF(K101,L101,"Y"))),L101,"M"),"m ",DATEDIF(K101+(30*(DATEDIF(K101,L101,"M"))),L101,"D"),"d") -> 0y 4m 32d | O101: Abra | P101: MasaMasid Tech Support | Q101: Community Facilitator | R101: Masa-Masid | S101: 30005 | T101: JO058
A102: =+A101+1 -> 44 | B102: BLAZA | C102: Gwen Noralie | D102: T | E102: 35300 | F102: =DATEDIF(E102,TODAY(),"Y") -> 29 | G102: F | H102: PD 907 | I102: Contract of Service | J102: 2 | K102: 42948 | L102: 43100 | M102: Y | N102: =CONCATENATE(DATEDIF(K102,L102,"Y"),"y ",DATEDIF(K102+(360*(DATEDIF(K102,L102,"Y"))),L102,"M"),"m ",DATEDIF(K102+(30*(DATEDIF(K102,L102,"M"))),L102,"D"),"d") -> 0y 4m 32d | O102: Abra | P102: MasaMasid Tech Support | Q102: Community Facilitator | R102: Masa-Masid | S102: 30006 | T102: JO059
A103: =+A102+1 -> 45 | B103: CABBIGAT | C103: Jenna Marie | D103: T | E103: 34266 | F103: =DATEDIF(E103,TODAY(),"Y") -> 32 | G103: F | H103: RA1080 Teacher | I103: Contract of Service | J103: 2 | K103: 42979 | L103: 43100 | M103: Y | N103: =CONCATENATE(DATEDIF(K103,L103,"Y"),"y ",DATEDIF(K103+(360*(DATEDIF(K103,L103,"Y"))),L103,"M"),"m ",DATEDIF(K103+(30*(DATEDIF(K103,L103,"M"))),L103,"D"),"d") -> 0y 3m 31d | O103: Ifugao | P103: MasaMasid Tech Support | Q103: Community Facilitator | R103: Masa-Masid | S103: 30007 | T103: JO060
A104: =+A103+1 -> 46 | B104: CHOEGSAN | C104: Glenn | D104: A | E104: 29418 | F104: =DATEDIF(E104,TODAY(),"Y") -> 45 | G104: F | H104: None | I104: Contract of Service | J104: 2 | K104: 42948 | L104: 43100 | M104: Y | N104: =CONCATENATE(DATEDIF(K104,L104,"Y"),"y ",DATEDIF(K104+(360*(DATEDIF(K104,L104,"Y"))),L104,"M"),"m ",DATEDIF(K104+(30*(DATEDIF(K104,L104,"M"))),L104,"D"),"d") -> 0y 4m 32d | O104: Baguio | P104: MasaMasid Tech Support | Q104: Community Facilitator | R104: Masa-Masid | S104: 30008 | T104: JO061
A105: =+A104+1 -> 47 | B105: DAMIAN | C105: Kristine Valerie | D105: P | E105: 35227 | F105: =DATEDIF(E105,TODAY(),"Y") -> 29 | G105: F | H105: None | I105: Contract of Service | J105: 2 | K105: 42948 | L105: 43100 | M105: Y | N105: =CONCATENATE(DATEDIF(K105,L105,"Y"),"y ",DATEDIF(K105+(360*(DATEDIF(K105,L105,"Y"))),L105,"M"),"m ",DATEDIF(K105+(30*(DATEDIF(K105,L105,"M"))),L105,"D"),"d") -> 0y 4m 32d | O105: Abra | P105: MasaMasid Tech Support | Q105: Community Facilitator | R105: Masa-Masid | S105: 30009 | T105: JO062
A106: =+A105+1 -> 48 | B106: DELSON | C106: Joselle Avery | D106: D | E106: 32956 | F106: =DATEDIF(E106,TODAY(),"Y") -> 36 | G106: F | H106: RA1080 Nursing | I106: Contract of Service | J106: 2 | K106: 42948 | L106: 43100 | M106: Y | N106: =CONCATENATE(DATEDIF(K106,L106,"Y"),"y ",DATEDIF(K106+(360*(DATEDIF(K106,L106,"Y"))),L106,"M"),"m ",DATEDIF(K106+(30*(DATEDIF(K106,L106,"M"))),L106,"D"),"d") -> 0y 4m 32d | O106: Kalinga | P106: MasaMasid Tech Support | Q106: Community Facilitator | R106: Masa-Masid | S106: 30010 | T106: JO063
A107: =+A106+1 -> 49 | B107: DURAN | C107: Norberto | D107: C | E107: 26973 | F107: =DATEDIF(E107,TODAY(),"Y") -> 52 | G107: M | H107: None | I107: Contract of Service | J107: 2 | K107: 42948 | L107: 43100 | M107: Y | N107: =CONCATENATE(DATEDIF(K107,L107,"Y"),"y ",DATEDIF(K107+(360*(DATEDIF(K107,L107,"Y"))),L107,"M"),"m ",DATEDIF(K107+(30*(DATEDIF(K107,L107,"M"))),L107,"D"),"d") -> 0y 4m 32d | O107: Apayao | P107: MasaMasid Tech Support | Q107: Community Facilitator | R107: Masa-Masid | S107: 30011 | T107: JO064
A108: =+A107+1 -> 50 | B108: ESTANISLAO | C108: Maria Iza Brigitte | D108: G | E108: 34186 | F108: =DATEDIF(E108,TODAY(),"Y") -> 32 | G108: F | H108: None | I108: Contract of Service | J108: 2 | K108: 42948 | L108: 43100 | M108: Y | N108: =CONCATENATE(DATEDIF(K108,L108,"Y"),"y ",DATEDIF(K108+(360*(DATEDIF(K108,L108,"Y"))),L108,"M"),"m ",DATEDIF(K108+(30*(DATEDIF(K108,L108,"M"))),L108,"D"),"d") -> 0y 4m 32d | O108: Abra | P108: MasaMasid Tech Support | Q108: Community Facilitator | R108: Masa-Masid | S108: 30012 | T108: JO065
...

Sheet staffing plan
A1: PERSONAL SERVICES ITEMIZATION AND PLANTILLA OF PERSONNEL
A2: =CONCATENATE("As of ",TEXT(NOW(),"mmmm dd, yyyy")) -> As of March 24, 2026
A4: DEPARTMENT OF THE INTERIOR AND LOCAL GOVERNMENT
A5: Cordillera Administrative Region
B7: POSITION TITLE | C7: S G | AH7: A N N U A L S A L A R Y | AJ7: STEP | AK7: A R E A | AW7: I N C U M B E N T | AY7: SEX | AZ7: DATE OF BIRTH | BF7: Tax Identification Number (TIN) | BG7: DATE OF ORIGINAL APPT | BK7: DATE OF LAST PROMO-TION | BM7: STATUS | BN7: ELIGIBILITY | BP7: REMARK
A8: ITEM NUMBER | D8: QUALIFICATION STANDARD | I8: Shrt Position Title | J8: PTStation | K8: PosStSex | L8: Gender Station | M8: Competencies Required | AH8: AUTHORIZED | AI8: ACTUAL | AK8: CODE | AL8: TYPE | AM8: LEVEL | AN8: P/P/A/ ATTRI-BUTION | AO8: Station Allocation | AP8: Specific Allocation | AQ8: 1998 & 2010 RP plantila location per code | AR8: LAST NAME | AS8: FIRST NAME | AT8: MIDDLE NAME | AU8: MI | AX8: STATION | BA8: age | BB8: age group | BC8: Age group station | BD8: genderagegroupstation | BE8: PTSexCat | BH8: date of tranfer to DILG | BI8: age in service | BJ8: YRS IN DILG | BL8: YRS IN THE POSI | BO8: Highest Educ attainment | BQ8: Status grade
A9: (1) | B9: (2) | D9: Educ | E9: Exp | F9: Trng | G9: Eligibility | H9: Duties and Responsibilities | M9: Core | Q9: functional (LGOOs) | X9: Non-LGOOs | AD9: Leadership | AH9: (3) | AI9: (4) | AJ9: (5) | AK9: (6) | AL9: (7) | AM9: (8) | AN9: (9) | AW9: 10 | AY9: 11 | AZ9: 12 | BF9: 13 | BG9: 14 | BK9: 15 | BM9: 16 | BN9: 17 | BP9: 18
M10: CESGG | N10: CF | O10: EER | P10: OS | Q10: EC | R10: I | S10: MKI | T10: PRA | U10: PDM | V10: RB | W10: TP | X10: C/AT | Y10: C/WO | Z10: PO | AA10: I/D/RM | AB10: EC | AC10: AS | AD10: DIO | AE10: PWMT | AF10: PSDM | AG10: OA
A11: 61,000 Office of the Regional Director
A12: OSEC-DILGB-DIR4-18-1998 | B12: Director IV | C12: 28 | D12: Bachelors Degree | E12: 3 years of supervisory experience | F12: none required | G12: Civil Service Executive Eligibility (CSEE)/ Career Executive Service (CES) | I12: DIR4 | J12: =IF(AX12="Regional Office",CONCATENATE(I12,"R"),IF(AX12="Abra",CONCATENATE(I12,"Ab"),IF(AX12="Apayao",CONCATENATE(I12,"Ap"),IF(AX12="Baguio City",CONCATENATE(I12,"BC"),IF(AX12="Ifugao",CONCATENATE(I12,"I"),IF(AX12="Mt. Province",CONCATENATE(I12,"MP"),IF(AX12="Kalinga",CONCATENATE(I12,"K"),IF(AX12="Benguet",CONCATENATE(I12,"B"),"Vacant")))))))) -> DIR4R | K12: =CONCATENATE(J12,AY12) -> DIR4RM | L12: =IF(AX12="Regional Office",(IF(AY12="M","RM","RF")),IF(AX12="Abra",(IF(AY12="M","AbM","AbF")),IF(AX12="Baguio City",(IF(AY12="M","BCM","BCF")),IF(AX12="Apayao",(IF(AY12="M","ApM","ApF")),IF(AX12="Benguet",(IF(AY12="M","BM","BF")),IF(AX12="Ifugao",(IF(AY12="M","IM","IF")),IF(AX12="Kalinga",(IF(AY12="M","KM","KF")),IF(AX12="Mt. Province",(IF(AY12="M","MPM","MPF")),"XXX")))))))) -> RM | M12: 4 | N12: 4 | O12: 4 | P12: 4 | AH12: =VLOOKUP(C12,idica,2,FALSE)*12 -> 1646340 | AI12: =(SUMPRODUCT((norman=C12)*(grace=AJ12)*(barnachea)))*12 -> 1673208 | AJ12: 2 | AK12: 011 | AL12: R | AM12: K | AN12: 310100100001000 | AO12: Regional Office | AP12: ORD | AQ12: Regional Office | AR12: IRINGAN | AS12: Marlo | AT12: Lingan | AU12: =LEFT(AT12)&IF(ISNUMBER(FIND(" ",AT12)),MID(AT12,FIND(" ",AT12)+1,1),"")&IF(ISNUMBER(FIND(" ",AT12,FIND(" ",AT12)+1)),MID(AT12,FIND(" ",AT12,FIND(" ",AT12)+1)+1,1),"") -> L | AV12: =PROPER(CONCATENATE(AS12," ",AU12,". ",AR12)) -> Marlo L. Iringan | AW12: =CONCATENATE(AR12,", ",AS12," ",AT12) -> IRINGAN, Marlo Lingan | AX12: Regional Office | AY12: M | AZ12: 24422 | BA12: =DATEDIF(AZ12,TODAY(),"Y") -> 59 | BB12: =IF(BA12<30,"A",IF(BA12<40,"B",IF(BA12<50,"C",IF(BA12<60,"D",IF(BA12<65,"E","VACANT"))))) -> D | BC12: =+IF(AX12="Regional Office",(IF(BB12="A","RA",(IF(BB12="B","RB",IF(BB12="C","RC",IF(BB12="D","RD",IF(BB12="E","RE","VACANT"))))))),IF(AX12="Abra",(IF(BB12="A","AbA",(IF(BB12="B","AbB",IF(BB12="C","AbC",IF(BB12="D","AbD",IF(BB12="E","AbE","VACANT"))))))),IF(AX12="Baguio City",(IF(BB12="A","BCA",(IF(BB12="B","BCB",IF(BB12="C","BCC",IF(BB12="D","BCD",IF(BB12="E","BCE","VACANT"))))))),IF(AX12="Apayao",(IF(BB12="A","ApA",(IF(BB12="B","ApB",IF(BB12="C","ApC",IF(BB12="D","ApD",IF(BB12="E","ApE","VACANT"))))))),IF(AX12="Benguet",(IF(BB12="A","BA",(IF(BB12="B","BB",IF(BB12="C","BC",IF(BB12="D","BD",IF(BB12="E","BE","VACANT"))))))),IF(AX12="Ifugao",(IF(BB12="A","IA",(IF(BB12="B","IB",IF(BB12="C","IC",IF(BB12="D","ID",IF(BB12="E","IE","VACANT"))))))),IF(AX12="Kalinga",(IF(BB12="A","KA",(IF(BB12="B","KB",IF(BB12="C","KC",IF(BB12="D","KD",IF(BB12="E","KE","VACANT"))))))),IF(AX12="Mt. Province",(IF(BB12="A","MPA",(IF(BB12="B","MPB",IF(BB12="C","MPC",IF(BB12="D","MPD",IF(BB12="E","MPE","VACANT"))))))),"XXX")))))))) -> RD | BD12: =CONCATENATE(BC12,AY12) -> RDM | BE12: =CONCATENATE(I12,BD12) -> DIR4RDM | BF12: 133-289-742 | BG12: 32546 | BH12: 32675 | BI12: =DATEDIF(BG12,TODAY(),"Y") -> 37 | BJ12: =DATEDIF(BH12,TODAY(),"Y") -> 36 | BK12: 43146 | BL12: =DATEDIF(BK12,TODAY(),"Y") -> 8 | BM12: P | BN12: CESO III | BO12: MPA - 35u | BQ12: =CONCATENATE(3,AY12,BM12) -> 3MP
A13: OSEC-DILGB-DIR3-4-1998 | B13: Director III | C13: 27 | D13: Bachelors Degree | E13: 3 years of supervisory experience | F13: none required | G13: Civil Service Executive Eligibility (CSEE)/ Career Executive Service (CES) | I13: DIR3 | J13: =IF(AX13="Regional Office",CONCATENATE(I13,"R"),IF(AX13="Abra",CONCATENATE(I13,"Ab"),IF(AX13="Apayao",CONCATENATE(I13,"Ap"),IF(AX13="Baguio City",CONCATENATE(I13,"BC"),IF(AX13="Ifugao",CONCATENATE(I13,"I"),IF(AX13="Mt. Province",CONCATENATE(I13,"MP"),IF(AX13="Kalinga",CONCATENATE(I13,"K"),IF(AX13="Benguet",CONCATENATE(I13,"B"),"Vacant")))))))) -> DIR3R | K13: =CONCATENATE(J13,AY13) -> DIR3RF | L13: =IF(AX13="Regional Office",(IF(AY13="M","RM","RF")),IF(AX13="Abra",(IF(AY13="M","AbM","AbF")),IF(AX13="Baguio City",(IF(AY13="M","BCM","BCF")),IF(AX13="Apayao",(IF(AY13="M","ApM","ApF")),IF(AX13="Benguet",(IF(AY13="M","BM","BF")),IF(AX13="Ifugao",(IF(AY13="M","IM","IF")),IF(AX13="Kalinga",(IF(AY13="M","KM","KF")),IF(AX13="Mt. Province",(IF(AY13="M","MPM","MPF")),"XXX")))))))) -> RF | M13: 4 | N13: 4 | O13: 4 | P13: 4 | AH13: =VLOOKUP(C13,idica,2,FALSE)*12 -> 1456932 | AI13: =(SUMPRODUCT((norman=C13)*(grace=AJ13)*(barnachea)))*12 -> 1480716 | AJ13: 2 | AK13: 011 | AL13: R | AM13: K | AN13: 310100100001000 | AO13: Regional Office | AP13: ORD | AQ13: Regional Office | AR13: SAN JOSE | AS13: Araceli | AT13: Arruejo | AU13: =LEFT(AT13)&IF(ISNUMBER(FIND(" ",AT13)),MID(AT13,FIND(" ",AT13)+1,1),"")&IF(ISNUMBER(FIND(" ",AT13,FIND(" ",AT13)+1)),MID(AT13,FIND(" ",AT13,FIND(" ",AT13)+1)+1,1),"") -> A | AV13: =PROPER(CONCATENATE(AS13," ",AU13,". ",AR13)) -> Araceli A. San Jose | AW13: =CONCATENATE(AR13,", ",AS13," ",AT13) -> SAN JOSE, Araceli Arruejo | AX13: Regional Office | AY13: F | AZ13: 25461 | BA13: =DATEDIF(AZ13,TODAY(),"Y") -> 56 | BB13: =IF(BA13<30,"A",IF(BA13<40,"B",IF(BA13<50,"C",IF(BA13<60,"D",IF(BA13<65,"E","VACANT"))))) -> D | BC13: =+IF(AX13="Regional Office",(IF(BB13="A","RA",(IF(BB13="B","RB",IF(BB13="C","RC",IF(BB13="D","RD",IF(BB13="E","RE","VACANT"))))))),IF(AX13="Abra",(IF(BB13="A","AbA",(IF(BB13="B","AbB",IF(BB13="C","AbC",IF(BB13="D","AbD",IF(BB13="E","AbE","VACANT"))))))),IF(AX13="Baguio City",(IF(BB13="A","BCA",(IF(BB13="B","BCB",IF(BB13="C","BCC",IF(BB13="D","BCD",IF(BB13="E","BCE","VACANT"))))))),IF(AX13="Apayao",(IF(BB13="A","ApA",(IF(BB13="B","ApB",IF(BB13="C","ApC",IF(BB13="D","ApD",IF(BB13="E","ApE","VACANT"))))))),IF(AX13="Benguet",(IF(BB13="A","BA",(IF(BB13="B","BB",IF(BB13="C","BC",IF(BB13="D","BD",IF(BB13="E","BE","VACANT"))))))),IF(AX13="Ifugao",(IF(BB13="A","IA",(IF(BB13="B","IB",IF(BB13="C","IC",IF(BB13="D","ID",IF(BB13="E","IE","VACANT"))))))),IF(AX13="Kalinga",(IF(BB13="A","KA",(IF(BB13="B","KB",IF(BB13="C","KC",IF(BB13="D","KD",IF(BB13="E","KE","VACANT"))))))),IF(AX13="Mt. Province",(IF(BB13="A","MPA",(IF(BB13="B","MPB",IF(BB13="C","MPC",IF(BB13="D","MPD",IF(BB13="E","MPE","VACANT"))))))),"XXX")))))))) -> RD | BD13: =CONCATENATE(BC13,AY13) -> RDF | BE13: =CONCATENATE(I13,BD13) -> DIR3RDF | BF13: 187-269-180 | BG13: 35457 | BH13: 35457 | BI13: =DATEDIF(BG13,TODAY(),"Y") -> 29 | BJ13: =DATEDIF(BH13,TODAY(),"Y") -> 29 | BK13: 43549 | BL13: =DATEDIF(BK13,TODAY(),"Y") -> 6 | BM13: P | BN13: CESO IV | BO13: MPA | BQ13: =CONCATENATE(3,AY13,BM13) -> 3FP
A14: OSEC-DILGB-ATTY4-9-1998 | B14: Attorney IV | C14: 23 | D14: Bachelor of Laws | E14: 2 years of relevant experience | F14: 8 hours of relevant training | G14: RA 1080 | H14: 1. Under the general supervision of the Regional Diretor, prepares letters/correspondence and takes appropriate actions on legal matters brought to the office by local government officials, DILG Central Office, other national agencies, and other persons/entities; 2. Renders written legal opinions or comments on queries endorsed to the regional office by the Central Office, field offices, including local governement units, and other entities; 3. Acts as a Resource Person and renders on-site technical assistance/advice to DILG field personnel, LGU officials and functionaries and to the geberal public on legal and operational matters, upon the directive of the Regional Director; 4. Acts as the Legal Adviser of the Regional Director and assists the Regional Director in implementing the decisions/reso;utions of the Ombudsman, Courts, and other quasi-juducial bodies; 5. Conducts confidential/discreet fact-finding inquiries and investigations as directed by the Office of the President, DILG Central Office, the Regional Director, Civil Service Commission, and the Ombudsman; 6. Conducts fact-finding inquiry/investigations relating to cases of DILG Regional Office personnel and recommends actions on cases filed against DILG personnel; 7. Conducts continuing researches and studies on laws, rules and regulations affecting local government units and Office operations; 8. Reviews drafts of proposed circulars, guidelines and/or issuances pertaining to DILG and local government operations, as well as review of drafts of contracts/MOA/MOU between DILG and its contracting parties; and 9. Prepare reports, communications and all other issunaces required by management. | I14: ATTY4 | J14: =IF(AX14="Regional Office",CONCATENATE(I14,"R"),IF(AX14="Abra",CONCATENATE(I14,"Ab"),IF(AX14="Apayao",CONCATENATE(I14,"Ap"),IF(AX14="Baguio City",CONCATENATE(I14,"BC"),IF(AX14="Ifugao",CONCATENATE(I14,"I"),IF(AX14="Mt. Province",CONCATENATE(I14,"MP"),IF(AX14="Kalinga",CONCATENATE(I14,"K"),IF(AX14="Benguet",CONCATENATE(I14,"B"),"Vacant")))))))) -> ATTY4R | K14: =CONCATENATE(J14,AY14) -> ATTY4RF | L14: =IF(AX14="Regional Office",(IF(AY14="M","RM","RF")),IF(AX14="Abra",(IF(AY14="M","AbM","AbF")),IF(AX14="Baguio City",(IF(AY14="M","BCM","BCF")),IF(AX14="Apayao",(IF(AY14="M","ApM","ApF")),IF(AX14="Benguet",(IF(AY14="M","BM","BF")),IF(AX14="Ifugao",(IF(AY14="M","IM","IF")),IF(AX14="Kalinga",(IF(AY14="M","KM","KF")),IF(AX14="Mt. Province",(IF(AY14="M","MPM","MPF")),"XXX")))))))) -> RF | M14: 3 | N14: 3 | O14: 3 | P14: 3 | AH14: =VLOOKUP(C14,idica,2,FALSE)*12 -> 885732 | AI14: =(SUMPRODUCT((norman=C14)*(grace=AJ14)*(barnachea)))*12 -> 885732 | AJ14: 1 | AK14: 011 | AL14: R | AM14: S | AN14: 310100100001000 | AO14: Regional Office | AP14: ORD | AQ14: Regional Office | AR14: SHONTOGAN | AS14: Genevieve | AT14: Miguel | AU14: =LEFT(AT14)&IF(ISNUMBER(FIND(" ",AT14)),MID(AT14,FIND(" ",AT14)+1,1),"")&IF(ISNUMBER(FIND(" ",AT14,FIND(" ",AT14)+1)),MID(AT14,FIND(" ",AT14,FIND(" ",AT14)+1)+1,1),"") -> M | AV14: =PROPER(CONCATENATE(AS14," ",AU14,". ",AR14)) -> Genevieve M. Shontogan | AW14: =CONCATENATE(AR14,", ",AS14," ",AT14) -> SHONTOGAN, Genevieve Miguel | AX14: Regional Office | AY14: F | AZ14: 31267 | BA14: =DATEDIF(AZ14,TODAY(),"Y") -> 40 | BB14: =IF(BA14<30,"A",IF(BA14<40,"B",IF(BA14<50,"C",IF(BA14<60,"D",IF(BA14<65,"E","VACANT"))))) -> C | BC14: =+IF(AX14="Regional Office",(IF(BB14="A","RA",(IF(BB14="B","RB",IF(BB14="C","RC",IF(BB14="D","RD",IF(BB14="E","RE","VACANT"))))))),IF(AX14="Abra",(IF(BB14="A","AbA",(IF(BB14="B","AbB",IF(BB14="C","AbC",IF(BB14="D","AbD",IF(BB14="E","AbE","VACANT"))))))),IF(AX14="Baguio City",(IF(BB14="A","BCA",(IF(BB14="B","BCB",IF(BB14="C","BCC",IF(BB14="D","BCD",IF(BB14="E","BCE","VACANT"))))))),IF(AX14="Apayao",(IF(BB14="A","ApA",(IF(BB14="B","ApB",IF(BB14="C","ApC",IF(BB14="D","ApD",IF(BB14="E","ApE","VACANT"))))))),IF(AX14="Benguet",(IF(BB14="A","BA",(IF(BB14="B","BB",IF(BB14="C","BC",IF(BB14="D","BD",IF(BB14="E","BE","VACANT"))))))),IF(AX14="Ifugao",(IF(BB14="A","IA",(IF(BB14="B","IB",IF(BB14="C","IC",IF(BB14="D","ID",IF(BB14="E","IE","VACANT"))))))),IF(AX14="Kalinga",(IF(BB14="A","KA",(IF(BB14="B","KB",IF(BB14="C","KC",IF(BB14="D","KD",IF(BB14="E","KE","VACANT"))))))),IF(AX14="Mt. Province",(IF(BB14="A","MPA",(IF(BB14="B","MPB",IF(BB14="C","MPC",IF(BB14="D","MPD",IF(BB14="E","MPE","VACANT"))))))),"XXX")))))))) -> RC | BD14: =CONCATENATE(BC14,AY14) -> RCF | BE14: =CONCATENATE(I14,BD14) -> ATTY4RCF | BF14: 414-630-652 | BG14: 41824 | BH14: 43360 | BI14: =DATEDIF(BG14,TODAY(),"Y") -> 11 | BJ14: =DATEDIF(BH14,TODAY(),"Y") -> 7 | BK14: 43360 | BL14: =DATEDIF(BK14,TODAY(),"Y") -> 7 | BM14: P | BN14: RA 1080 | BO14: LLb | BQ14: =CONCATENATE(2,AY14,BM14) -> 2FP
A15: OSEC-DILGB-ITO1-2-2010 | B15: Information Technology Officer I | C15: 19 | D15: Bachelors Degree relevant to the job | E15: 2 years of relevant experience | F15: 8 hours of relevant training | G15: Career Service (Professional) Second Level Eligibility | H15: • Designs, Develops and Maintains the regional website; • Attends technical committee meetings and sessions and provides inputs, as appropriate; • Recommends internal standards, policies, procedures/work flows on technology, information systems, data management and security; • Establishes and maintains a general file of policies and documents on IT solutions and systems; • Reviews internal policies and recommends enhancements/developments as necessary; • Consults with different units and consolidates proposals/inputs on IT requirements to form part of regional ICT Plan; • Monitors and/or maintains operations and maintenance of IT systems following plans and policies • Manages the overall data communications network including network performance; • Installs, configures and maintains LAN/WAN servers and workstations and hardware and software platform interface; • Investigates and resolves communications network and connectivity problems, including user access and component configuration to recommend future enhancements; • Responds to inquiries and requests for assistance on IT systems and networks; • Documents problems and resolutions as future reference for further courses of action such as acquisition or use of new products or services; • Coordinates with organizational units for the development and implementation of IT plans and policies, including requests for assistance and requests for hardware or software programs; • Drafts communications and correspondences in response to queries and requests for information of other operating units in support of the functions of the division; • Assists in the preparation of various reports/presentation as instructed and retrieval and packaging of documents and reports; • Assists in coordinating with organizational units for the development and implementation of IT plans and policies, including requests for assistance and requests for hardware or software programs; Performs other duties that may be assigned or delegated. | I15: ITO1 | J15: =IF(AX15="Regional Office",CONCATENATE(I15,"R"),IF(AX15="Abra",CONCATENATE(I15,"Ab"),IF(AX15="Apayao",CONCATENATE(I15,"Ap"),IF(AX15="Baguio City",CONCATENATE(I15,"BC"),IF(AX15="Ifugao",CONCATENATE(I15,"I"),IF(AX15="Mt. Province",CONCATENATE(I15,"MP"),IF(AX15="Kalinga",CONCATENATE(I15,"K"),IF(AX15="Benguet",CONCATENATE(I15,"B"),"Vacant")))))))) -> ITO1R | K15: =CONCATENATE(J15,AY15) -> ITO1RM | L15: =IF(AX15="Regional Office",(IF(AY15="M","RM","RF")),IF(AX15="Abra",(IF(AY15="M","AbM","AbF")),IF(AX15="Baguio City",(IF(AY15="M","BCM","BCF")),IF(AX15="Apayao",(IF(AY15="M","ApM","ApF")),IF(AX15="Benguet",(IF(AY15="M","BM","BF")),IF(AX15="Ifugao",(IF(AY15="M","IM","IF")),IF(AX15="Kalinga",(IF(AY15="M","KM","KF")),IF(AX15="Mt. Province",(IF(AY15="M","MPM","MPF")),"XXX")))))))) -> RM | M15: 3 | N15: 3 | O15: 3 | P15: 3 | AH15: =VLOOKUP(C15,idica,2,FALSE)*12 -> 543228 | AI15: =(SUMPRODUCT((norman=C15)*(grace=AJ15)*(barnachea)))*12 -> 561108 | AJ15: 3 | AK15: 011 | AL15: R | AM15: S | AN15: 310100100001000 | AO15: Regional Office | AP15: ORD | AQ15: Regional Office | AR15: PAPAT-IW | AS15: Zaldy | AT15: Bugtong | AU15: =LEFT(AT15)&IF(ISNUMBER(FIND(" ",AT15)),MID(AT15,FIND(" ",AT15)+1,1),"")&IF(ISNUMBER(FIND(" ",AT15,FIND(" ",AT15)+1)),MID(AT15,FIND(" ",AT15,FIND(" ",AT15)+1)+1,1),"") -> B | AV15: =PROPER(CONCATENATE(AS15," ",AU15,". ",AR15)) -> Zaldy B. Papat-Iw | AW15: =CONCATENATE(AR15,", ",AS15," ",AT15) -> PAPAT-IW, Zaldy Bugtong | AX15: Regional Office | AY15: M | AZ15: 27757 | BA15: =DATEDIF(AZ15,TODAY(),"Y") -> 50 | BB15: =IF(BA15<30,"A",IF(BA15<40,"B",IF(BA15<50,"C",IF(BA15<60,"D",IF(BA15<65,"E","VACANT"))))) -> D | BC15: =+IF(AX15="Regional Office",(IF(BB15="A","RA",(IF(BB15="B","RB",IF(BB15="C","RC",IF(BB15="D","RD",IF(BB15="E","RE","VACANT"))))))),IF(AX15="Abra",(IF(BB15="A","AbA",(IF(BB15="B","AbB",IF(BB15="C","AbC",IF(BB15="D","AbD",IF(BB15="E","AbE","VACANT"))))))),IF(AX15="Baguio City",(IF(BB15="A","BCA",(IF(BB15="B","BCB",IF(BB15="C","BCC",IF(BB15="D","BCD",IF(BB15="E","BCE","VACANT"))))))),IF(AX15="Apayao",(IF(BB15="A","ApA",(IF(BB15="B","ApB",IF(BB15="C","ApC",IF(BB15="D","ApD",IF(BB15="E","ApE","VACANT"))))))),IF(AX15="Benguet",(IF(BB15="A","BA",(IF(BB15="B","BB",IF(BB15="C","BC",IF(BB15="D","BD",IF(BB15="E","BE","VACANT"))))))),IF(AX15="Ifugao",(IF(BB15="A","IA",(IF(BB15="B","IB",IF(BB15="C","IC",IF(BB15="D","ID",IF(BB15="E","IE","VACANT"))))))),IF(AX15="Kalinga",(IF(BB15="A","KA",(IF(BB15="B","KB",IF(BB15="C","KC",IF(BB15="D","KD",IF(BB15="E","KE","VACANT"))))))),IF(AX15="Mt. Province",(IF(BB15="A","MPA",(IF(BB15="B","MPB",IF(BB15="C","MPC",IF(BB15="D","MPD",IF(BB15="E","MPE","VACANT"))))))),"XXX")))))))) -> RD | BD15: =CONCATENATE(BC15,AY15) -> RDM | BE15: =CONCATENATE(I15,BD15) -> ITO1RDM | BF15: 916-245-161 | BG15: 37655 | BH15: 37655 | BI15: =DATEDIF(BG15,TODAY(),"Y") -> 23 | BJ15: =DATEDIF(BH15,TODAY(),"Y") -> 23 | BK15: 40969 | BL15: =DATEDIF(BK15,TODAY(),"Y") -> 14 | BM15: P | BN15: CSP | BO15: MSIT - 6u | BQ15: =CONCATENATE(2,AY15,BM15) -> 2MP
A16: OSEC-DILGB-PLO3-93-2010 | B16: Planning Officer III | C16: 18 | I16: PLO3 | J16: =IF(AX16="Regional Office",CONCATENATE(I16,"R"),IF(AX16="Abra",CONCATENATE(I16,"Ab"),IF(AX16="Apayao",CONCATENATE(I16,"Ap"),IF(AX16="Baguio City",CONCATENATE(I16,"BC"),IF(AX16="Ifugao",CONCATENATE(I16,"I"),IF(AX16="Mt. Province",CONCATENATE(I16,"MP"),IF(AX16="Kalinga",CONCATENATE(I16,"K"),IF(AX16="Benguet",CONCATENATE(I16,"B"),"Vacant")))))))) -> PLO3R | K16: =CONCATENATE(J16,AY16) -> PLO3RF | L16: =IF(AX16="Regional Office",(IF(AY16="M","RM","RF")),IF(AX16="Abra",(IF(AY16="M","AbM","AbF")),IF(AX16="Baguio City",(IF(AY16="M","BCM","BCF")),IF(AX16="Apayao",(IF(AY16="M","ApM","ApF")),IF(AX16="Benguet",(IF(AY16="M","BM","BF")),IF(AX16="Ifugao",(IF(AY16="M","IM","IF")),IF(AX16="Kalinga",(IF(AY16="M","KM","KF")),IF(AX16="Mt. Province",(IF(AY16="M","MPM","MPF")),"XXX")))))))) -> RF | M16: 3 | N16: 3 | O16: 3 | P16: 3 | AH16: =VLOOKUP(C16,idica,2,FALSE)*12 -> 487644 | AI16: =(SUMPRODUCT((norman=C16)*(grace=AJ16)*(barnachea)))*12 -> 487644 | AJ16: 1 | AK16: 011 | AL16: R | AM16: S | AN16: 310100100001000 | AO16: Regional Office | AP16: ORD | AQ16: Regional Office | AR16: BINAY-AN | AS16: Fe | AT16: Suerte | AU16: =LEFT(AT16)&IF(ISNUMBER(FIND(" ",AT16)),MID(AT16,FIND(" ",AT16)+1,1),"")&IF(ISNUMBER(FIND(" ",AT16,FIND(" ",AT16)+1)),MID(AT16,FIND(" ",AT16,FIND(" ",AT16)+1)+1,1),"") -> S | AV16: =PROPER(CONCATENATE(AS16," ",AU16,". ",AR16)) -> Fe S. Binay-An | AW16: =CONCATENATE(AR16,", ",AS16," ",AT16) -> BINAY-AN, Fe Suerte | AX16: Regional Office | AY16: F | AZ16: 29850 | BA16: =DATEDIF(AZ16,TODAY(),"Y") -> 44 | BB16: =IF(BA16<30,"A",IF(BA16<40,"B",IF(BA16<50,"C",IF(BA16<60,"D",IF(BA16<65,"E","VACANT"))))) -> C | BC16: =+IF(AX16="Regional Office",(IF(BB16="A","RA",(IF(BB16="B","RB",IF(BB16="C","RC",IF(BB16="D","RD",IF(BB16="E","RE","VACANT"))))))),IF(AX16="Abra",(IF(BB16="A","AbA",(IF(BB16="B","AbB",IF(BB16="C","AbC",IF(BB16="D","AbD",IF(BB16="E","AbE","VACANT"))))))),IF(AX16="Baguio City",(IF(BB16="A","BCA",(IF(BB16="B","BCB",IF(BB16="C","BCC",IF(BB16="D","BCD",IF(BB16="E","BCE","VACANT"))))))),IF(AX16="Apayao",(IF(BB16="A","ApA",(IF(BB16="B","ApB",IF(BB16="C","ApC",IF(BB16="D","ApD",IF(BB16="E","ApE","VACANT"))))))),IF(AX16="Benguet",(IF(BB16="A","BA",(IF(BB16="B","BB",IF(BB16="C","BC",IF(BB16="D","BD",IF(BB16="E","BE","VACANT"))))))),IF(AX16="Ifugao",(IF(BB16="A","IA",(IF(BB16="B","IB",IF(BB16="C","IC",IF(BB16="D","ID",IF(BB16="E","IE","VACANT"))))))),IF(AX16="Kalinga",(IF(BB16="A","KA",(IF(BB16="B","KB",IF(BB16="C","KC",IF(BB16="D","KD",IF(BB16="E","KE","VACANT"))))))),IF(AX16="Mt. Province",(IF(BB16="A","MPA",(IF(BB16="B","MPB",IF(BB16="C","MPC",IF(BB16="D","MPD",IF(BB16="E","MPE","VACANT"))))))),"XXX")))))))) -> RC | BD16: =CONCATENATE(BC16,AY16) -> RCF | BE16: =CONCATENATE(I16,BD16) -> PLO3RCF | BF16: 921-559-466 | BG16: 41260 | BH16: 41260 | BI16: =DATEDIF(BG16,TODAY(),"Y") -> 13 | BJ16: =DATEDIF(BH16,TODAY(),"Y") -> 13 | BK16: 42653 | BL16: =DATEDIF(BK16,TODAY(),"Y") -> 9 | BM16: P | BN16: RA 1080 | BO16: MBA | BQ16: =CONCATENATE(2,AY16,BM16) -> 2FP
A17: OSEC-DILGB-ADAS3-64-2005 | B17: Administrative Assistant III | C17: 9 | D17: Completion of two years studies in college | E17: 1 year of relevant experience | F17: 4 hours of relevant training | G17: Career Service (Subprofessional) First Eligibility | H17: Drafts letters; correspondences; Maintain RD's agenda and assist in planning appointments, meetings, conferences etc. Calendars events and appointments of the RD. Receive and screen phone calls and redirect them when appropriate Handle and prioritize all outgoing or incoming correspondence (e-mail, letters, packages etc.) Handle and entertain RD's visitors; Make travel arrangements for the RD and other executives Records/Files custodian of the RD; Maintain electronic and paper records ensuring information is organized and easily accessible Handle confidential documents ensuring they remain secure Prepare Disbursement Vouchers Monitor and manage office supplies Perform other related functions as may be deemed necessay | I17: ADAS3 | J17: =IF(AX17="Regional Office",CONCATENATE(I17,"R"),IF(AX17="Abra",CONCATENATE(I17,"Ab"),IF(AX17="Apayao",CONCATENATE(I17,"Ap"),IF(AX17="Baguio City",CONCATENATE(I17,"BC"),IF(AX17="Ifugao",CONCATENATE(I17,"I"),IF(AX17="Mt. Province",CONCATENATE(I17,"MP"),IF(AX17="Kalinga",CONCATENATE(I17,"K"),IF(AX17="Benguet",CONCATENATE(I17,"B"),"Vacant")))))))) -> ADAS3R | K17: =CONCATENATE(J17,AY17) -> ADAS3RF | L17: =IF(AX17="Regional Office",(IF(AY17="M","RM","RF")),IF(AX17="Abra",(IF(AY17="M","AbM","AbF")),IF(AX17="Baguio City",(IF(AY17="M","BCM","BCF")),IF(AX17="Apayao",(IF(AY17="M","ApM","ApF")),IF(AX17="Benguet",(IF(AY17="M","BM","BF")),IF(AX17="Ifugao",(IF(AY17="M","IM","IF")),IF(AX17="Kalinga",(IF(AY17="M","KM","KF")),IF(AX17="Mt. Province",(IF(AY17="M","MPM","MPF")),"XXX")))))))) -> RF | M17: 1 | N17: 1 | O17: 1 | P17: 1 | AH17: =VLOOKUP(C17,idica,2,FALSE)*12 -> 215700 | AI17: =(SUMPRODUCT((norman=C17)*(grace=AJ17)*(barnachea)))*12 -> 226752 | AJ17: 7 | AK17: 011 | AL17: R | AM17: A | AN17: 310100100001000 | AO17: Regional Office | AP17: ORD | AQ17: Regional Office | AR17: DAOAS | AS17: Marian Pait | AT17: Bigsang | AU17: =LEFT(AT17)&IF(ISNUMBER(FIND(" ",AT17)),MID(AT17,FIND(" ",AT17)+1,1),"")&IF(ISNUMBER(FIND(" ",AT17,FIND(" ",AT17)+1)),MID(AT17,FIND(" ",AT17,FIND(" ",AT17)+1)+1,1),"") -> B | AV17: =PROPER(CONCATENATE(AS17," ",AU17,". ",AR17)) -> Marian Pait B. Daoas | AW17: =CONCATENATE(AR17,", ",AS17," ",AT17) -> DAOAS, Marian Pait Bigsang | AX17: Regional Office | AY17: F | AZ17: 23697 | BA17: =DATEDIF(AZ17,TODAY(),"Y") -> 61 | BB17: =IF(BA17<30,"A",IF(BA17<40,"B",IF(BA17<50,"C",IF(BA17<60,"D",IF(BA17<65,"E","VACANT"))))) -> E | BC17: =+IF(AX17="Regional Office",(IF(BB17="A","RA",(IF(BB17="B","RB",IF(BB17="C","RC",IF(BB17="D","RD",IF(BB17="E","RE","VACANT"))))))),IF(AX17="Abra",(IF(BB17="A","AbA",(IF(BB17="B","AbB",IF(BB17="C","AbC",IF(BB17="D","AbD",IF(BB17="E","AbE","VACANT"))))))),IF(AX17="Baguio City",(IF(BB17="A","BCA",(IF(BB17="B","BCB",IF(BB17="C","BCC",IF(BB17="D","BCD",IF(BB17="E","BCE","VACANT"))))))),IF(AX17="Apayao",(IF(BB17="A","ApA",(IF(BB17="B","ApB",IF(BB17="C","ApC",IF(BB17="D","ApD",IF(BB17="E","ApE","VACANT"))))))),IF(AX17="Benguet",(IF(BB17="A","BA",(IF(BB17="B","BB",IF(BB17="C","BC",IF(BB17="D","BD",IF(BB17="E","BE","VACANT"))))))),IF(AX17="Ifugao",(IF(BB17="A","IA",(IF(BB17="B","IB",IF(BB17="C","IC",IF(BB17="D","ID",IF(BB17="E","IE","VACANT"))))))),IF(AX17="Kalinga",(IF(BB17="A","KA",(IF(BB17="B","KB",IF(BB17="C","KC",IF(BB17="D","KD",IF(BB17="E","KE","VACANT"))))))),IF(AX17="Mt. Province",(IF(BB17="A","MPA",(IF(BB17="B","MPB",IF(BB17="C","MPC",IF(BB17="D","MPD",IF(BB17="E","MPE","VACANT"))))))),"XXX")))))))) -> RE | BD17: =CONCATENATE(BC17,AY17) -> REF | BE17: =CONCATENATE(I17,BD17) -> ADAS3REF | BF17: 185-738-006 | BG17: 35037 | BH17: 35037 | BI17: =DATEDIF(BG17,TODAY(),"Y") -> 30 | BJ17: =DATEDIF(BH17,TODAY(),"Y") -> 30 | BK17: 36069 | BL17: =DATEDIF(BK17,TODAY(),"Y") -> 27 | BM17: P | BN17: CSSP | BO17: BS Secretarial Admin | BQ17: =CONCATENATE(1,AY17,BM17) -> 1FP
A18: OSEC-DILGB-ADA4-83-2005 | B18: Administrative Aide IV (Driver II) | C18: 4 | D18: Elementary School Graduate | E18: None Required | F18: None Required | G18: None Required (MC 11, s. 96 - Cat. III) | I18: ADA4 | J18: =IF(AX18="Regional Office",CONCATENATE(I18,"R"),IF(AX18="Abra",CONCATENATE(I18,"Ab"),IF(AX18="Apayao",CONCATENATE(I18,"Ap"),IF(AX18="Baguio City",CONCATENATE(I18,"BC"),IF(AX18="Ifugao",CONCATENATE(I18,"I"),IF(AX18="Mt. Province",CONCATENATE(I18,"MP"),IF(AX18="Kalinga",CONCATENATE(I18,"K"),IF(AX18="Benguet",CONCATENATE(I18,"B"),"Vacant")))))))) -> ADA4R | K18: =CONCATENATE(J18,AY18) -> ADA4RM | L18: =IF(AX18="Regional Office",(IF(AY18="M","RM","RF")),IF(AX18="Abra",(IF(AY18="M","AbM","AbF")),IF(AX18="Baguio City",(IF(AY18="M","BCM","BCF")),IF(AX18="Apayao",(IF(AY18="M","ApM","ApF")),IF(AX18="Benguet",(IF(AY18="M","BM","BF")),IF(AX18="Ifugao",(IF(AY18="M","IM","IF")),IF(AX18="Kalinga",(IF(AY18="M","KM","KF")),IF(AX18="Mt. Province",(IF(AY18="M","MPM","MPF")),"XXX")))))))) -> RM | M18: 1 | N18: 1 | O18: 1 | P18: 1 | AH18: =VLOOKUP(C18,idica,2,FALSE)*12 -> 158568 | AI18: =(SUMPRODUCT((norman=C18)*(grace=AJ18)*(barnachea)))*12 -> 158568 | AJ18: 1 | AK18: 011 | AL18: R | AM18: A | AN18: 310100100001000 | AO18: Regional Office | AP18: ORD | AQ18: Regional Office | AR18: PULTZ | AS18: El-wood Duane | AT18: Lingbawan | AU18: =LEFT(AT18)&IF(ISNUMBER(FIND(" ",AT18)),MID(AT18,FIND(" ",AT18)+1,1),"")&IF(ISNUMBER(FIND(" ",AT18,FIND(" ",AT18)+1)),MID(AT18,FIND(" ",AT18,FIND(" ",AT18)+1)+1,1),"") -> L | AV18: =PROPER(CONCATENATE(AS18," ",AU18,". ",AR18)) -> El-Wood Duane L. Pultz | AW18: =CONCATENATE(AR18,", ",AS18," ",AT18) -> PULTZ, El-wood Duane Lingbawan | AX18: Regional Office | AY18: M | AZ18: 27230 | BA18: =DATEDIF(AZ18,TODAY(),"Y") -> 51 | BB18: =IF(BA18<30,"A",IF(BA18<40,"B",IF(BA18<50,"C",IF(BA18<60,"D",IF(BA18<65,"E","VACANT"))))) -> D | BC18: =+IF(AX18="Regional Office",(IF(BB18="A","RA",(IF(BB18="B","RB",IF(BB18="C","RC",IF(BB18="D","RD",IF(BB18="E","RE","VACANT"))))))),IF(AX18="Abra",(IF(BB18="A","AbA",(IF(BB18="B","AbB",IF(BB18="C","AbC",IF(BB18="D","AbD",IF(BB18="E","AbE","VACANT"))))))),IF(AX18="Baguio City",(IF(BB18="A","BCA",(IF(BB18="B","BCB",IF(BB18="C","BCC",IF(BB18="D","BCD",IF(BB18="E","BCE","VACANT"))))))),IF(AX18="Apayao",(IF(BB18="A","ApA",(IF(BB18="B","ApB",IF(BB18="C","ApC",IF(BB18="D","ApD",IF(BB18="E","ApE","VACANT"))))))),IF(AX18="Benguet",(IF(BB18="A","BA",(IF(BB18="B","BB",IF(BB18="C","BC",IF(BB18="D","BD",IF(BB18="E","BE","VACANT"))))))),IF(AX18="Ifugao",(IF(BB18="A","IA",(IF(BB18="B","IB",IF(BB18="C","IC",IF(BB18="D","ID",IF(BB18="E","IE","VACANT"))))))),IF(AX18="Kalinga",(IF(BB18="A","KA",(IF(BB18="B","KB",IF(BB18="C","KC",IF(BB18="D","KD",IF(BB18="E","KE","VACANT"))))))),IF(AX18="Mt. Province",(IF(BB18="A","MPA",(IF(BB18="B","MPB",IF(BB18="C","MPC",IF(BB18="D","MPD",IF(BB18="E","MPE","VACANT"))))))),"XXX")))))))) -> RD | BD18: =CONCATENATE(BC18,AY18) -> RDM | BE18: =CONCATENATE(I18,BD18) -> ADA4RDM | BF18: 452-273-461 | BG18: 42891 | BH18: 42891 | BI18: =DATEDIF(BG18,TODAY(),"Y") -> 8 | BJ18: =DATEDIF(BH18,TODAY(),"Y") -> 8 | BK18: 42891 | BL18: =DATEDIF(BK18,TODAY(),"Y") -> 8 | BM18: CTO | BO18: Automotive, Mechanic, Driving | BQ18: =CONCATENATE(1,AY18,BM18) -> 1MCTO
A19: Sub-Total | AJ19: =COUNTIF(AJ12:AJ18,"<>") -> 7
A20: 62,000 Capability Development Division
A21: OSEC-DILGB-LGOO7-37-1998 | B21: Local Government Operations Officer VII | C21: 24 | D21: Mater's Degree or Certificate in Leadership and Management from the CSC | E21: Four (4) years of supervisory/management experience | F21: Forty (40) hours of supervisory/management learning and development intervention undertaken within the last five (5) years | G21: CS Professional/ 2nd Level Eligibility | I21: LGOO7 | J21: =IF(AX21="Regional Office",CONCATENATE(I21,"R"),IF(AX21="Abra",CONCATENATE(I21,"Ab"),IF(AX21="Apayao",CONCATENATE(I21,"Ap"),IF(AX21="Baguio City",CONCATENATE(I21,"BC"),IF(AX21="Ifugao",CONCATENATE(I21,"I"),IF(AX21="Mt. Province",CONCATENATE(I21,"MP"),IF(AX21="Kalinga",CONCATENATE(I21,"K"),IF(AX21="Benguet",CONCATENATE(I21,"B"),"Vacant")))))))) -> LGOO7R | K21: =CONCATENATE(J21,AY21) -> LGOO7RF | L21: =IF(AX21="Regional Office",(IF(AY21="M","RM","RF")),IF(AX21="Abra",(IF(AY21="M","AbM","AbF")),IF(AX21="Baguio City",(IF(AY21="M","BCM","BCF")),IF(AX21="Apayao",(IF(AY21="M","ApM","ApF")),IF(AX21="Benguet",(IF(AY21="M","BM","BF")),IF(AX21="Ifugao",(IF(AY21="M","IM","IF")),IF(AX21="Kalinga",(IF(AY21="M","KM","KF")),IF(AX21="Mt. Province",(IF(AY21="M","MPM","MPF")),"XXX")))))))) -> RF | M21: 3 | N21: 3 | O21: 3 | P21: 3 | AH21: =VLOOKUP(C21,idica,2,FALSE)*12 -> 1000872 | AI21: =(SUMPRODUCT((norman=C21)*(grace=AJ21)*(barnachea)))*12 -> 1000872 | AJ21: 1 | AK21: 06 | AL21: P | AM21: K | AN21: 310100100001000 | AO21: Regional Office | AP21: CDD | AQ21: Benguet - Region | AR21: PAYANG | AS21: Daisy | AT21: Amoy | AU21: =LEFT(AT21)&IF(ISNUMBER(FIND(" ",AT21)),MID(AT21,FIND(" ",AT21)+1,1),"")&IF(ISNUMBER(FIND(" ",AT21,FIND(" ",AT21)+1)),MID(AT21,FIND(" ",AT21,FIND(" ",AT21)+1)+1,1),"") -> A | AV21: =PROPER(CONCATENATE(AS21," ",AU21,". ",AR21)) -> Daisy A. Payang | AW21: =CONCATENATE(AR21,", ",AS21," ",AT21) -> PAYANG, Daisy Amoy | AX21: Regional Office | AY21: F | AZ21: 25540 | BA21: =DATEDIF(AZ21,TODAY(),"Y") -> 56 | BB21: =IF(BA21<30,"A",IF(BA21<40,"B",IF(BA21<50,"C",IF(BA21<60,"D",IF(BA21<65,"E","VACANT"))))) -> D | BC21: =+IF(AX21="Regional Office",(IF(BB21="A","RA",(IF(BB21="B","RB",IF(BB21="C","RC",IF(BB21="D","RD",IF(BB21="E","RE","VACANT"))))))),IF(AX21="Abra",(IF(BB21="A","AbA",(IF(BB21="B","AbB",IF(BB21="C","AbC",IF(BB21="D","AbD",IF(BB21="E","AbE","VACANT"))))))),IF(AX21="Baguio City",(IF(BB21="A","BCA",(IF(BB21="B","BCB",IF(BB21="C","BCC",IF(BB21="D","BCD",IF(BB21="E","BCE","VACANT"))))))),IF(AX21="Apayao",(IF(BB21="A","ApA",(IF(BB21="B","ApB",IF(BB21="C","ApC",IF(BB21="D","ApD",IF(BB21="E","ApE","VACANT"))))))),IF(AX21="Benguet",(IF(BB21="A","BA",(IF(BB21="B","BB",IF(BB21="C","BC",IF(BB21="D","BD",IF(BB21="E","BE","VACANT"))))))),IF(AX21="Ifugao",(IF(BB21="A","IA",(IF(BB21="B","IB",IF(BB21="C","IC",IF(BB21="D","ID",IF(BB21="E","IE","VACANT"))))))),IF(AX21="Kalinga",(IF(BB21="A","KA",(IF(BB21="B","KB",IF(BB21="C","KC",IF(BB21="D","KD",IF(BB21="E","KE","VACANT"))))))),IF(AX21="Mt. Province",(IF(BB21="A","MPA",(IF(BB21="B","MPB",IF(BB21="C","MPC",IF(BB21="D","MPD",IF(BB21="E","MPE","VACANT"))))))),"XXX")))))))) -> RD | BD21: =CONCATENATE(BC21,AY21) -> RDF | BE21: =CONCATENATE(I21,BD21) -> LGOO7RDF | BF21: 164-776-684 | BG21: 33648 | BH21: 33648 | BI21: =DATEDIF(BG21,TODAY(),"Y") -> 34 | BJ21: =DATEDIF(BH21,TODAY(),"Y") -> 34 | BK21: 42569 | BL21: =DATEDIF(BK21,TODAY(),"Y") -> 9 | BM21: P | BN21: PD 907 | BO21: PhD | BQ21: =CONCATENATE(2,AY21,BM21) -> 2FP
A22: OSEC-DILGB-LGOO6-12-1998 | B22: Local Government Operations Officer VI | C22: 22 | I22: LGOO6 | J22: =IF(AX22="Regional Office",CONCATENATE(I22,"R"),IF(AX22="Abra",CONCATENATE(I22,"Ab"),IF(AX22="Apayao",CONCATENATE(I22,"Ap"),IF(AX22="Baguio City",CONCATENATE(I22,"BC"),IF(AX22="Ifugao",CONCATENATE(I22,"I"),IF(AX22="Mt. Province",CONCATENATE(I22,"MP"),IF(AX22="Kalinga",CONCATENATE(I22,"K"),IF(AX22="Benguet",CONCATENATE(I22,"B"),"Vacant")))))))) -> LGOO6B | K22: =CONCATENATE(J22,AY22) -> LGOO6BF | L22: =IF(AX22="Regional Office",(IF(AY22="M","RM","RF")),IF(AX22="Abra",(IF(AY22="M","AbM","AbF")),IF(AX22="Baguio City",(IF(AY22="M","BCM","BCF")),IF(AX22="Apayao",(IF(AY22="M","ApM","ApF")),IF(AX22="Benguet",(IF(AY22="M","BM","BF")),IF(AX22="Ifugao",(IF(AY22="M","IM","IF")),IF(AX22="Kalinga",(IF(AY22="M","KM","KF")),IF(AX22="Mt. Province",(IF(AY22="M","MPM","MPF")),"XXX")))))))) -> BF | M22: 3 | N22: 3 | O22: 3 | P22: 3 | AH22: =VLOOKUP(C22,idica,2,FALSE)*12 -> 783828 | AI22: =(SUMPRODUCT((norman=C22)*(grace=AJ22)*(barnachea)))*12 -> 822840 | AJ22: 4 | AK22: 011 | AL22: R | AM22: T | AN22: 310100100001000 | AO22: Regional Office | AP22: CDD | AQ22: Regional Office | AR22: CLAUDIO | AS22: Ofelia | AT22: Linggon | AU22: =LEFT(AT22)&IF(ISNUMBER(FIND(" ",AT22)),MID(AT22,FIND(" ",AT22)+1,1),"")&IF(ISNUMBER(FIND(" ",AT22,FIND(" ",AT22)+1)),MID(AT22,FIND(" ",AT22,FIND(" ",AT22)+1)+1,1),"") -> L | AV22: =PROPER(CONCATENATE(AS22," ",AU22,". ",AR22)) -> Ofelia L. Claudio | AW22: =CONCATENATE(AR22,", ",AS22," ",AT22) -> CLAUDIO, Ofelia Linggon | AX22: Benguet | AY22: F | AZ22: 21997 | BA22: =DATEDIF(AZ22,TODAY(),"Y") -> 66 | BB22: =IF(BA22<30,"A",IF(BA22<40,"B",IF(BA22<50,"C",IF(BA22<60,"D",IF(BA22<65,"E","VACANT"))))) -> VACANT | BC22: =+IF(AX22="Regional Office",(IF(BB22="A","RA",(IF(BB22="B","RB",IF(BB22="C","RC",IF(BB22="D","RD",IF(BB22="E","RE","VACANT"))))))),IF(AX22="Abra",(IF(BB22="A","AbA",(IF(BB22="B","AbB",IF(BB22="C","AbC",IF(BB22="D","AbD",IF(BB22="E","AbE","VACANT"))))))),IF(AX22="Baguio City",(IF(BB22="A","BCA",(IF(BB22="B","BCB",IF(BB22="C","BCC",IF(BB22="D","BCD",IF(BB22="E","BCE","VACANT"))))))),IF(AX22="Apayao",(IF(BB22="A","ApA",(IF(BB22="B","ApB",IF(BB22="C","ApC",IF(BB22="D","ApD",IF(BB22="E","ApE","VACANT"))))))),IF(AX22="Benguet",(IF(BB22="A","BA",(IF(BB22="B","BB",IF(BB22="C","BC",IF(BB22="D","BD",IF(BB22="E","BE","VACANT"))))))),IF(AX22="Ifugao",(IF(BB22="A","IA",(IF(BB22="B","IB",IF(BB22="C","IC",IF(BB22="D","ID",IF(BB22="E","IE","VACANT"))))))),IF(AX22="Kalinga",(IF(BB22="A","KA",(IF(BB22="B","KB",IF(BB22="C","KC",IF(BB22="D","KD",IF(BB22="E","KE","VACANT"))))))),IF(AX22="Mt. Province",(IF(BB22="A","MPA",(IF(BB22="B","MPB",IF(BB22="C","MPC",IF(BB22="D","MPD",IF(BB22="E","MPE","VACANT"))))))),"XXX")))))))) -> VACANT | BD22: =CONCATENATE(BC22,AY22) -> VACANTF | BE22: =CONCATENATE(I22,BD22) -> LGOO6VACANTF | BF22: 127-934-210 | BG22: 32687 | BH22: 32687 | BI22: =DATEDIF(BG22,TODAY(),"Y") -> 36 | BJ22: =DATEDIF(BH22,TODAY(),"Y") -> 36 | BK22: 39510 | BL22: =DATEDIF(BK22,TODAY(),"Y") -> 18 | BM22: P | BN22: CSP | BO22: PhD - 6u | BQ22: =CONCATENATE(2,AY22,BM22) -> 2FP
A23: OSEC-DILGB-LGOO5-791-1998 | B23: Local Government Operations Officer V | C23: 20 | I23: LGOO5 | J23: =IF(AX23="Regional Office",CONCATENATE(I23,"R"),IF(AX23="Abra",CONCATENATE(I23,"Ab"),IF(AX23="Apayao",CONCATENATE(I23,"Ap"),IF(AX23="Baguio City",CONCATENATE(I23,"BC"),IF(AX23="Ifugao",CONCATENATE(I23,"I"),IF(AX23="Mt. Province",CONCATENATE(I23,"MP"),IF(AX23="Kalinga",CONCATENATE(I23,"K"),IF(AX23="Benguet",CONCATENATE(I23,"B"),"Vacant")))))))) -> LGOO5R | K23: =CONCATENATE(J23,AY23) -> LGOO5RM | L23: =IF(AX23="Regional Office",(IF(AY23="M","RM","RF")),IF(AX23="Abra",(IF(AY23="M","AbM","AbF")),IF(AX23="Baguio City",(IF(AY23="M","BCM","BCF")),IF(AX23="Apayao",(IF(AY23="M","ApM","ApF")),IF(AX23="Benguet",(IF(AY23="M","BM","BF")),IF(AX23="Ifugao",(IF(AY23="M","IM","IF")),IF(AX23="Kalinga",(IF(AY23="M","KM","KF")),IF(AX23="Mt. Province",(IF(AY23="M","MPM","MPF")),"XXX")))))))) -> RM | M23: 3 | N23: 3 | O23: 3 | P23: 3 | AH23: =VLOOKUP(C23,idica,2,FALSE)*12 -> 613860 | AI23: =(SUMPRODUCT((norman=C23)*(grace=AJ23)*(barnachea)))*12 -> 654924 | AJ23: 5 | AK23: 0540 | AL23: M | AM23: T | AN23: 310100100001000 | AO23: Regional Office | AP23: CDD | AQ23: Atok - Regional Office | AR23: GONZALES | AS23: Rolando | AT23: Ronquillo | AU23: =LEFT(AT23)&IF(ISNUMBER(FIND(" ",AT23)),MID(AT23,FIND(" ",AT23)+1,1),"")&IF(ISNUMBER(FIND(" ",AT23,FIND(" ",AT23)+1)),MID(AT23,FIND(" ",AT23,FIND(" ",AT23)+1)+1,1),"") -> R | AV23: =PROPER(CONCATENATE(AS23," ",AU23,". ",AR23)) -> Rolando R. Gonzales | AW23: =CONCATENATE(AR23,", ",AS23," ",AT23) -> GONZALES, Rolando Ronquillo | AX23: Regional Office | AY23: M | AZ23: 23864 | BA23: =DATEDIF(AZ23,TODAY(),"Y") -> 60 | BB23: =IF(BA23<30,"A",IF(BA23<40,"B",IF(BA23<50,"C",IF(BA23<60,"D",IF(BA23<65,"E","VACANT"))))) -> E | BC23: =+IF(AX23="Regional Office",(IF(BB23="A","RA",(IF(BB23="B","RB",IF(BB23="C","RC",IF(BB23="D","RD",IF(BB23="E","RE","VACANT"))))))),IF(AX23="Abra",(IF(BB23="A","AbA",(IF(BB23="B","AbB",IF(BB23="C","AbC",IF(BB23="D","AbD",IF(BB23="E","AbE","VACANT"))))))),IF(AX23="Baguio City",(IF(BB23="A","BCA",(IF(BB23="B","BCB",IF(BB23="C","BCC",IF(BB23="D","BCD",IF(BB23="E","BCE","VACANT"))))))),IF(AX23="Apayao",(IF(BB23="A","ApA",(IF(BB23="B","ApB",IF(BB23="C","ApC",IF(BB23="D","ApD",IF(BB23="E","ApE","VACANT"))))))),IF(AX23="Benguet",(IF(BB23="A","BA",(IF(BB23="B","BB",IF(BB23="C","BC",IF(BB23="D","BD",IF(BB23="E","BE","VACANT"))))))),IF(AX23="Ifugao",(IF(BB23="A","IA",(IF(BB23="B","IB",IF(BB23="C","IC",IF(BB23="D","ID",IF(BB23="E","IE","VACANT"))))))),IF(AX23="Kalinga",(IF(BB23="A","KA",(IF(BB23="B","KB",IF(BB23="C","KC",IF(BB23="D","KD",IF(BB23="E","KE","VACANT"))))))),IF(AX23="Mt. Province",(IF(BB23="A","MPA",(IF(BB23="B","MPB",IF(BB23="C","MPC",IF(BB23="D","MPD",IF(BB23="E","MPE","VACANT"))))))),"XXX")))))))) -> RE | BD23: =CONCATENATE(BC23,AY23) -> REM | BE23: =CONCATENATE(I23,BD23) -> LGOO5REM | BF23: 138-169-683 | BG23: 35079 | BH23: 35079 | BI23: =DATEDIF(BG23,TODAY(),"Y") -> 30 | BJ23: =DATEDIF(BH23,TODAY(),"Y") -> 30 | BK23: 38607 | BL23: =DATEDIF(BK23,TODAY(),"Y") -> 20 | BM23: P | BN23: CSP | BO23: MPA | BP23: Shifting | BQ23: =CONCATENATE(2,AY23,BM23) -> 2MP
A24: OSEC-DILGB-LGOO5-802-1998 | B24: Local Government Operations Officer V | C24: 20 | I24: LGOO5 | J24: =IF(AX24="Regional Office",CONCATENATE(I24,"R"),IF(AX24="Abra",CONCATENATE(I24,"Ab"),IF(AX24="Apayao",CONCATENATE(I24,"Ap"),IF(AX24="Baguio City",CONCATENATE(I24,"BC"),IF(AX24="Ifugao",CONCATENATE(I24,"I"),IF(AX24="Mt. Province",CONCATENATE(I24,"MP"),IF(AX24="Kalinga",CONCATENATE(I24,"K"),IF(AX24="Benguet",CONCATENATE(I24,"B"),"Vacant")))))))) -> LGOO5R | K24: =CONCATENATE(J24,AY24) -> LGOO5RM | L24: =IF(AX24="Regional Office",(IF(AY24="M","RM","RF")),IF(AX24="Abra",(IF(AY24="M","AbM","AbF")),IF(AX24="Baguio City",(IF(AY24="M","BCM","BCF")),IF(AX24="Apayao",(IF(AY24="M","ApM","ApF")),IF(AX24="Benguet",(IF(AY24="M","BM","BF")),IF(AX24="Ifugao",(IF(AY24="M","IM","IF")),IF(AX24="Kalinga",(IF(AY24="M","KM","KF")),IF(AX24="Mt. Province",(IF(AY24="M","MPM","MPF")),"XXX")))))))) -> RM | M24: 3 | N24: 3 | O24: 3 | P24: 3 | AH24: =VLOOKUP(C24,idica,2,FALSE)*12 -> 613860 | AI24: =(SUMPRODUCT((norman=C24)*(grace=AJ24)*(barnachea)))*12 -> 665616 | AJ24: 6 | AK24: 011 | AL24: R | AM24: T | AN24: 310100100001000 | AO24: Regional Office | AP24: CDD | AQ24: Regional Office | AR24: MAUTING | AS24: Johnny | AT24: Laayon | AU24: =LEFT(AT24)&IF(ISNUMBER(FIND(" ",AT24)),MID(AT24,FIND(" ",AT24)+1,1),"")&IF(ISNUMBER(FIND(" ",AT24,FIND(" ",AT24)+1)),MID(AT24,FIND(" ",AT24,FIND(" ",AT24)+1)+1,1),"") -> L | AV24: =PROPER(CONCATENATE(AS24," ",AU24,". ",AR24)) -> Johnny L. Mauting | AW24: =CONCATENATE(AR24,", ",AS24," ",AT24) -> MAUTING, Johnny Laayon | AX24: Regional Office | AY24: M | AZ24: 26969 | BA24: =DATEDIF(AZ24,TODAY(),"Y") -> 52 | BB24: =IF(BA24<30,"A",IF(BA24<40,"B",IF(BA24<50,"C",IF(BA24<60,"D",IF(BA24<65,"E","VACANT"))))) -> D | BC24: =+IF(AX24="Regional Office",(IF(BB24="A","RA",(IF(BB24="B","RB",IF(BB24="C","RC",IF(BB24="D","RD",IF(BB24="E","RE","VACANT"))))))),IF(AX24="Abra",(IF(BB24="A","AbA",(IF(BB24="B","AbB",IF(BB24="C","AbC",IF(BB24="D","AbD",IF(BB24="E","AbE","VACANT"))))))),IF(AX24="Baguio City",(IF(BB24="A","BCA",(IF(BB24="B","BCB",IF(BB24="C","BCC",IF(BB24="D","BCD",IF(BB24="E","BCE","VACANT"))))))),IF(AX24="Apayao",(IF(BB24="A","ApA",(IF(BB24="B","ApB",IF(BB24="C","ApC",IF(BB24="D","ApD",IF(BB24="E","ApE","VACANT"))))))),IF(AX24="Benguet",(IF(BB24="A","BA",(IF(BB24="B","BB",IF(BB24="C","BC",IF(BB24="D","BD",IF(BB24="E","BE","VACANT"))))))),IF(AX24="Ifugao",(IF(BB24="A","IA",(IF(BB24="B","IB",IF(BB24="C","IC",IF(BB24="D","ID",IF(BB24="E","IE","VACANT"))))))),IF(AX24="Kalinga",(IF(BB24="A","KA",(IF(BB24="B","KB",IF(BB24="C","KC",IF(BB24="D","KD",IF(BB24="E","KE","VACANT"))))))),IF(AX24="Mt. Province",(IF(BB24="A","MPA",(IF(BB24="B","MPB",IF(BB24="C","MPC",IF(BB24="D","MPD",IF(BB24="E","MPE","VACANT"))))))),"XXX")))))))) -> RD | BD24: =CONCATENATE(BC24,AY24) -> RDM | BE24: =CONCATENATE(I24,BD24) -> LGOO5RDM | BF24: 185-741-147 | BG24: 34892 | BH24: 34892 | BI24: =DATEDIF(BG24,TODAY(),"Y") -> 30 | BJ24: =DATEDIF(BH24,TODAY(),"Y") -> 30 | BK24: 37355 | BL24: =DATEDIF(BK24,TODAY(),"Y") -> 23 | BM24: P | BN24: CSP | BO24: MPA | BP24: Shifting | BQ24: =CONCATENATE(2,AY24,BM24) -> 2MP
A25: OSEC-DILGB-LGOO5-813-1998 | B25: Local Government Operations Officer V | C25: 20 | I25: LGOO5 | J25: =IF(AX25="Regional Office",CONCATENATE(I25,"R"),IF(AX25="Abra",CONCATENATE(I25,"Ab"),IF(AX25="Apayao",CONCATENATE(I25,"Ap"),IF(AX25="Baguio City",CONCATENATE(I25,"BC"),IF(AX25="Ifugao",CONCATENATE(I25,"I"),IF(AX25="Mt. Province",CONCATENATE(I25,"MP"),IF(AX25="Kalinga",CONCATENATE(I25,"K"),IF(AX25="Benguet",CONCATENATE(I25,"B"),"Vacant")))))))) -> Vacant | K25: =CONCATENATE(J25,AY25) -> Vacant | L25: =IF(AX25="Regional Office",(IF(AY25="M","RM","RF")),IF(AX25="Abra",(IF(AY25="M","AbM","AbF")),IF(AX25="Baguio City",(IF(AY25="M","BCM","BCF")),IF(AX25="Apayao",(IF(AY25="M","ApM","ApF")),IF(AX25="Benguet",(IF(AY25="M","BM","BF")),IF(AX25="Ifugao",(IF(AY25="M","IM","IF")),IF(AX25="Kalinga",(IF(AY25="M","KM","KF")),IF(AX25="Mt. Province",(IF(AY25="M","MPM","MPF")),"XXX")))))))) -> XXX | M25: 3 | N25: 3 | O25: 3 | P25: 3 | AH25: =VLOOKUP(C25,idica,2,FALSE)*12 -> 613860 | AI25: =(SUMPRODUCT((norman=C25)*(grace=AJ25)*(barnachea)))*12 -> 0 | AJ25: 0 | AK25: 011 | AL25: R | AM25: T | AN25: 310100100001000 | AO25: Regional Office | AP25: CDD | AQ25: Regional Office | AR25: Vacant GRIBA | AU25: =LEFT(AT25)&IF(ISNUMBER(FIND(" ",AT25)),MID(AT25,FIND(" ",AT25)+1,1),"")&IF(ISNUMBER(FIND(" ",AT25,FIND(" ",AT25)+1)),MID(AT25,FIND(" ",AT25,FIND(" ",AT25)+1)+1,1),"") | AV25: =PROPER(CONCATENATE(AS25," ",AU25,". ",AR25)) -> . Vacant Griba | AW25: =CONCATENATE(AR25,", ",AS25," ",AT25) -> Vacant GRIBA, | BA25: =DATEDIF(AZ25,TODAY(),"Y") -> 126 | BB25: =IF(BA25<30,"A",IF(BA25<40,"B",IF(BA25<50,"C",IF(BA25<60,"D",IF(BA25<65,"E","VACANT"))))) -> VACANT | BC25: =+IF(AX25="Regional Office",(IF(BB25="A","RA",(IF(BB25="B","RB",IF(BB25="C","RC",IF(BB25="D","RD",IF(BB25="E","RE","VACANT"))))))),IF(AX25="Abra",(IF(BB25="A","AbA",(IF(BB25="B","AbB",IF(BB25="C","AbC",IF(BB25="D","AbD",IF(BB25="E","AbE","VACANT"))))))),IF(AX25="Baguio City",(IF(BB25="A","BCA",(IF(BB25="B","BCB",IF(BB25="C","BCC",IF(BB25="D","BCD",IF(BB25="E","BCE","VACANT"))))))),IF(AX25="Apayao",(IF(BB25="A","ApA",(IF(BB25="B","ApB",IF(BB25="C","ApC",IF(BB25="D","ApD",IF(BB25="E","ApE","VACANT"))))))),IF(AX25="Benguet",(IF(BB25="A","BA",(IF(BB25="B","BB",IF(BB25="C","BC",IF(BB25="D","BD",IF(BB25="E","BE","VACANT"))))))),IF(AX25="Ifugao",(IF(BB25="A","IA",(IF(BB25="B","IB",IF(BB25="C","IC",IF(BB25="D","ID",IF(BB25="E","IE","VACANT"))))))),IF(AX25="Kalinga",(IF(BB25="A","KA",(IF(BB25="B","KB",IF(BB25="C","KC",IF(BB25="D","KD",IF(BB25="E","KE","VACANT"))))))),IF(AX25="Mt. Province",(IF(BB25="A","MPA",(IF(BB25="B","MPB",IF(BB25="C","MPC",IF(BB25="D","MPD",IF(BB25="E","MPE","VACANT"))))))),"XXX")))))))) -> XXX | BD25: =CONCATENATE(BC25,AY25) -> XXX | BE25: =CONCATENATE(I25,BD25) -> LGOO5XXX | BI25: =DATEDIF(BG25,TODAY(),"Y") -> 126 | BJ25: =DATEDIF(BH25,TODAY(),"Y") -> 126 | BL25: =DATEDIF(BK25,TODAY(),"Y") -> 126 | BQ25: =CONCATENATE(2,AY25,BM25) -> 2
A26: OSEC-DILGB-LGOO4-161-1998 | B26: Local Government Operations Officer IV | C26: 18 | I26: LGOO4 | J26: =IF(AX26="Regional Office",CONCATENATE(I26,"R"),IF(AX26="Abra",CONCATENATE(I26,"Ab"),IF(AX26="Apayao",CONCATENATE(I26,"Ap"),IF(AX26="Baguio City",CONCATENATE(I26,"BC"),IF(AX26="Ifugao",CONCATENATE(I26,"I"),IF(AX26="Mt. Province",CONCATENATE(I26,"MP"),IF(AX26="Kalinga",CONCATENATE(I26,"K"),IF(AX26="Benguet",CONCATENATE(I26,"B"),"Vacant")))))))) -> LGOO4R | K26: =CONCATENATE(J26,AY26) -> LGOO4RM | L26: =IF(AX26="Regional Office",(IF(AY26="M","RM","RF")),IF(AX26="Abra",(IF(AY26="M","AbM","AbF")),IF(AX26="Baguio City",(IF(AY26="M","BCM","BCF")),IF(AX26="Apayao",(IF(AY26="M","ApM","ApF")),IF(AX26="Benguet",(IF(AY26="M","BM","BF")),IF(AX26="Ifugao",(IF(AY26="M","IM","IF")),IF(AX26="Kalinga",(IF(AY26="M","KM","KF")),IF(AX26="Mt. Province",(IF(AY26="M","MPM","MPF")),"XXX")))))))) -> RM | M26: 3 | N26: 3 | O26: 3 | P26: 3 | AH26: =VLOOKUP(C26,idica,2,FALSE)*12 -> 487644 | AI26: =(SUMPRODUCT((norman=C26)*(grace=AJ26)*(barnachea)))*12 -> 487644 | AJ26: 1 | AK26: 011 | AL26: P | AM26: T | AN26: 310100100001000 | AO26: Regional Office | AP26: MED | AQ26: Regional Office | AR26: DAEP | AS26: Sherwin Ray | AT26: Ochoco | AU26: =LEFT(AT26)&IF(ISNUMBER(FIND(" ",AT26)),MID(AT26,FIND(" ",AT26)+1,1),"")&IF(ISNUMBER(FIND(" ",AT26,FIND(" ",AT26)+1)),MID(AT26,FIND(" ",AT26,FIND(" ",AT26)+1)+1,1),"") -> O | AV26: =PROPER(CONCATENATE(AS26," ",AU26,". ",AR26)) -> Sherwin Ray O. Daep | AW26: =CONCATENATE(AR26,", ",AS26," ",AT26) -> DAEP, Sherwin Ray Ochoco | AX26: Regional Office | AY26: M | AZ26: 30364 | BA26: =DATEDIF(AZ26,TODAY(),"Y") -> 43 | BB26: =IF(BA26<30,"A",IF(BA26<40,"B",IF(BA26<50,"C",IF(BA26<60,"D",IF(BA26<65,"E","VACANT"))))) -> C | BC26: =+IF(AX26="Regional Office",(IF(BB26="A","RA",(IF(BB26="B","RB",IF(BB26="C","RC",IF(BB26="D","RD",IF(BB26="E","RE","VACANT"))))))),IF(AX26="Abra",(IF(BB26="A","AbA",(IF(BB26="B","AbB",IF(BB26="C","AbC",IF(BB26="D","AbD",IF(BB26="E","AbE","VACANT"))))))),IF(AX26="Baguio City",(IF(BB26="A","BCA",(IF(BB26="B","BCB",IF(BB26="C","BCC",IF(BB26="D","BCD",IF(BB26="E","BCE","VACANT"))))))),IF(AX26="Apayao",(IF(BB26="A","ApA",(IF(BB26="B","ApB",IF(BB26="C","ApC",IF(BB26="D","ApD",IF(BB26="E","ApE","VACANT"))))))),IF(AX26="Benguet",(IF(BB26="A","BA",(IF(BB26="B","BB",IF(BB26="C","BC",IF(BB26="D","BD",IF(BB26="E","BE","VACANT"))))))),IF(AX26="Ifugao",(IF(BB26="A","IA",(IF(BB26="B","IB",IF(BB26="C","IC",IF(BB26="D","ID",IF(BB26="E","IE","VACANT"))))))),IF(AX26="Kalinga",(IF(BB26="A","KA",(IF(BB26="B","KB",IF(BB26="C","KC",IF(BB26="D","KD",IF(BB26="E","KE","VACANT"))))))),IF(AX26="Mt. Province",(IF(BB26="A","MPA",(IF(BB26="B","MPB",IF(BB26="C","MPC",IF(BB26="D","MPD",IF(BB26="E","MPE","VACANT"))))))),"XXX")))))))) -> RC | BD26: =CONCATENATE(BC26,AY26) -> RCM | BE26: =CONCATENATE(I26,BD26) -> LGOO4RCM | BF26: 178-120-158 | BG26: 40927 | BH26: 40927 | BI26: =DATEDIF(BG26,TODAY(),"Y") -> 14 | BJ26: =DATEDIF(BH26,TODAY(),"Y") -> 14 | BK26: 43129 | BL26: =DATEDIF(BK26,TODAY(),"Y") -> 8 | BM26: P | BN26: CSP | BO26: BS Mktng | BP26: Region | BQ26: =CONCATENATE(2,AY26,BM26) -> 2MP
A27: OSEC-DILGB-LGOO4-164-1998 | B27: Local Government Operations Officer IV | C27: 18 | I27: LGOO4 | J27: =IF(AX27="Regional Office",CONCATENATE(I27,"R"),IF(AX27="Abra",CONCATENATE(I27,"Ab"),IF(AX27="Apayao",CONCATENATE(I27,"Ap"),IF(AX27="Baguio City",CONCATENATE(I27,"BC"),IF(AX27="Ifugao",CONCATENATE(I27,"I"),IF(AX27="Mt. Province",CONCATENATE(I27,"MP"),IF(AX27="Kalinga",CONCATENATE(I27,"K"),IF(AX27="Benguet",CONCATENATE(I27,"B"),"Vacant")))))))) -> LGOO4R | K27: =CONCATENATE(J27,AY27) -> LGOO4RM | L27: =IF(AX27="Regional Office",(IF(AY27="M","RM","RF")),IF(AX27="Abra",(IF(AY27="M","AbM","AbF")),IF(AX27="Baguio City",(IF(AY27="M","BCM","BCF")),IF(AX27="Apayao",(IF(AY27="M","ApM","ApF")),IF(AX27="Benguet",(IF(AY27="M","BM","BF")),IF(AX27="Ifugao",(IF(AY27="M","IM","IF")),IF(AX27="Kalinga",(IF(AY27="M","KM","KF")),IF(AX27="Mt. Province",(IF(AY27="M","MPM","MPF")),"XXX")))))))) -> RM | M27: 3 | N27: 3 | O27: 3 | P27: 3 | AH27: =VLOOKUP(C27,idica,2,FALSE)*12 -> 487644 | AI27: =(SUMPRODUCT((norman=C27)*(grace=AJ27)*(barnachea)))*12 -> 487644 | AJ27: 1 | AK27: 011 | AL27: R | AM27: T | AN27: 310100100001000 | AO27: Regional Office | AP27: CDD | AQ27: Regional Office | AR27: BRETT | AS27: Ralph Kevin | AT27: Bacagan | AU27: =LEFT(AT27)&IF(ISNUMBER(FIND(" ",AT27)),MID(AT27,FIND(" ",AT27)+1,1),"")&IF(ISNUMBER(FIND(" ",AT27,FIND(" ",AT27)+1)),MID(AT27,FIND(" ",AT27,FIND(" ",AT27)+1)+1,1),"") -> B | AV27: =PROPER(CONCATENATE(AS27," ",AU27,". ",AR27)) -> Ralph Kevin B. Brett | AW27: =CONCATENATE(AR27,", ",AS27," ",AT27) -> BRETT, Ralph Kevin Bacagan | AX27: Regional Office | AY27: M | AZ27: 30231 | BA27: =DATEDIF(AZ27,TODAY(),"Y") -> 43 | BB27: =IF(BA27<30,"A",IF(BA27<40,"B",IF(BA27<50,"C",IF(BA27<60,"D",IF(BA27<65,"E","VACANT"))))) -> C | BC27: =+IF(AX27="Regional Office",(IF(BB27="A","RA",(IF(BB27="B","RB",IF(BB27="C","RC",IF(BB27="D","RD",IF(BB27="E","RE","VACANT"))))))),IF(AX27="Abra",(IF(BB27="A","AbA",(IF(BB27="B","AbB",IF(BB27="C","AbC",IF(BB27="D","AbD",IF(BB27="E","AbE","VACANT"))))))),IF(AX27="Baguio City",(IF(BB27="A","BCA",(IF(BB27="B","BCB",IF(BB27="C","BCC",IF(BB27="D","BCD",IF(BB27="E","BCE","VACANT"))))))),IF(AX27="Apayao",(IF(BB27="A","ApA",(IF(BB27="B","ApB",IF(BB27="C","ApC",IF(BB27="D","ApD",IF(BB27="E","ApE","VACANT"))))))),IF(AX27="Benguet",(IF(BB27="A","BA",(IF(BB27="B","BB",IF(BB27="C","BC",IF(BB27="D","BD",IF(BB27="E","BE","VACANT"))))))),IF(AX27="Ifugao",(IF(BB27="A","IA",(IF(BB27="B","IB",IF(BB27="C","IC",IF(BB27="D","ID",IF(BB27="E","IE","VACANT"))))))),IF(AX27="Kalinga",(IF(BB27="A","KA",(IF(BB27="B","KB",IF(BB27="C","KC",IF(BB27="D","KD",IF(BB27="E","KE","VACANT"))))))),IF(AX27="Mt. Province",(IF(BB27="A","MPA",(IF(BB27="B","MPB",IF(BB27="C","MPC",IF(BB27="D","MPD",IF(BB27="E","MPE","VACANT"))))))),"XXX")))))))) -> RC | BD27: =CONCATENATE(BC27,AY27) -> RCM | BE27: =CONCATENATE(I27,BD27) -> LGOO4RCM | BF27: 941-815-183 | BG27: 41927 | BH27: 41927 | BI27: =DATEDIF(BG27,TODAY(),"Y") -> 11 | BJ27: =DATEDIF(BH27,TODAY(),"Y") -> 11 | BK27: 43283 | BL27: =DATEDIF(BK27,TODAY(),"Y") -> 7 | BM27: P | BN27: CSP | BO27: BS Fin Mgmt | BQ27: =CONCATENATE(2,AY27,BM27) -> 2MP
A28: OSEC-DILGB-ADA6-97-2005 | B28: Administrative Aide VI | C28: 6 | D28: Completion of two years studies in college | E28: None Required | F28: None Required | G28: Career Service (Subprofessional) First Eligibility | H28:  Prepares simple correspondences  Receives and records incoming and outgoing communications, correspondences  Performs highly skilled and responsible clerical work  Makes and receives calls  Maintains log books  Provides administrative support to trainings  Sorts and maintains documents/records (Memos, Circulars, Orders)  Prepares and maintains registry of records  Provides messengerial services  Performs other related duties that may be assigned or delegated. | I28: ADA6 | J28: =IF(AX28="Regional Office",CONCATENATE(I28,"R"),IF(AX28="Abra",CONCATENATE(I28,"Ab"),IF(AX28="Apayao",CONCATENATE(I28,"Ap"),IF(AX28="Baguio City",CONCATENATE(I28,"BC"),IF(AX28="Ifugao",CONCATENATE(I28,"I"),IF(AX28="Mt. Province",CONCATENATE(I28,"MP"),IF(AX28="Kalinga",CONCATENATE(I28,"K"),IF(AX28="Benguet",CONCATENATE(I28,"B"),"Vacant")))))))) -> Vacant | K28: =CONCATENATE(J28,AY28) -> Vacant | L28: =IF(AX28="Regional Office",(IF(AY28="M","RM","RF")),IF(AX28="Abra",(IF(AY28="M","AbM","AbF")),IF(AX28="Baguio City",(IF(AY28="M","BCM","BCF")),IF(AX28="Apayao",(IF(AY28="M","ApM","ApF")),IF(AX28="Benguet",(IF(AY28="M","BM","BF")),IF(AX28="Ifugao",(IF(AY28="M","IM","IF")),IF(AX28="Kalinga",(IF(AY28="M","KM","KF")),IF(AX28="Mt. Province",(IF(AY28="M","MPM","MPF")),"XXX")))))))) -> XXX | M28: 1 | N28: 1 | O28: 1 | P28: 1 | AH28: =VLOOKUP(C28,idica,2,FALSE)*12 -> 178164 | AI28: =(SUMPRODUCT((norman=C28)*(grace=AJ28)*(barnachea)))*12 -> 0 | AJ28: 0 | AK28: 011 | AL28: R | AM28: A | AN28: 310100100001000 | AO28: Regional Office | AP28: CDD | AQ28: Regional Office | AR28: Vacant MAGO | AU28: =LEFT(AT28)&IF(ISNUMBER(FIND(" ",AT28)),MID(AT28,FIND(" ",AT28)+1,1),"")&IF(ISNUMBER(FIND(" ",AT28,FIND(" ",AT28)+1)),MID(AT28,FIND(" ",AT28,FIND(" ",AT28)+1)+1,1),"") | AV28: =PROPER(CONCATENATE(AS28," ",AU28,". ",AR28)) -> . Vacant Mago | AW28: =CONCATENATE(AR28,", ",AS28," ",AT28) -> Vacant MAGO, | BA28: =DATEDIF(AZ28,TODAY(),"Y") -> 126 | BB28: =IF(BA28<30,"A",IF(BA28<40,"B",IF(BA28<50,"C",IF(BA28<60,"D",IF(BA28<65,"E","VACANT"))))) -> VACANT | BC28: =+IF(AX28="Regional Office",(IF(BB28="A","RA",(IF(BB28="B","RB",IF(BB28="C","RC",IF(BB28="D","RD",IF(BB28="E","RE","VACANT"))))))),IF(AX28="Abra",(IF(BB28="A","AbA",(IF(BB28="B","AbB",IF(BB28="C","AbC",IF(BB28="D","AbD",IF(BB28="E","AbE","VACANT"))))))),IF(AX28="Baguio City",(IF(BB28="A","BCA",(IF(BB28="B","BCB",IF(BB28="C","BCC",IF(BB28="D","BCD",IF(BB28="E","BCE","VACANT"))))))),IF(AX28="Apayao",(IF(BB28="A","ApA",(IF(BB28="B","ApB",IF(BB28="C","ApC",IF(BB28="D","ApD",IF(BB28="E","ApE","VACANT"))))))),IF(AX28="Benguet",(IF(BB28="A","BA",(IF(BB28="B","BB",IF(BB28="C","BC",IF(BB28="D","BD",IF(BB28="E","BE","VACANT"))))))),IF(AX28="Ifugao",(IF(BB28="A","IA",(IF(BB28="B","IB",IF(BB28="C","IC",IF(BB28="D","ID",IF(BB28="E","IE","VACANT"))))))),IF(AX28="Kalinga",(IF(BB28="A","KA",(IF(BB28="B","KB",IF(BB28="C","KC",IF(BB28="D","KD",IF(BB28="E","KE","VACANT"))))))),IF(AX28="Mt. Province",(IF(BB28="A","MPA",(IF(BB28="B","MPB",IF(BB28="C","MPC",IF(BB28="D","MPD",IF(BB28="E","MPE","VACANT"))))))),"XXX")))))))) -> XXX | BD28: =CONCATENATE(BC28,AY28) -> XXX | BE28: =CONCATENATE(I28,BD28) -> ADA6XXX | BI28: =DATEDIF(BG28,TODAY(),"Y") -> 126 | BJ28: =DATEDIF(BH28,TODAY(),"Y") -> 126 | BL28: =DATEDIF(BK28,TODAY(),"Y") -> 126 | BQ28: =CONCATENATE(1,AY28,BM28) -> 1
A29: Sub-Total | AJ29: =COUNTIF(AJ21:AJ28,"<>") -> 8
A30: 63,000 Monitoring and Evaluation Division
A31: OSEC-DILGB-LGOO7-38-1998 | B31: Local Government Operations Officer VII | C31: 24 | D31: Mater's Degree or Certificate in Leadership and Management from the CSC | E31: Four (4) years of supervisory/management experience | F31: Forty (40) hours of supervisory/management learning and development intervention undertaken within the last five (5) years | G31: CS Professional/ 2nd Level Eligibility | I31: LGOO7 | J31: =IF(AX31="Regional Office",CONCATENATE(I31,"R"),IF(AX31="Abra",CONCATENATE(I31,"Ab"),IF(AX31="Apayao",CONCATENATE(I31,"Ap"),IF(AX31="Baguio City",CONCATENATE(I31,"BC"),IF(AX31="Ifugao",CONCATENATE(I31,"I"),IF(AX31="Mt. Province",CONCATENATE(I31,"MP"),IF(AX31="Kalinga",CONCATENATE(I31,"K"),IF(AX31="Benguet",CONCATENATE(I31,"B"),"Vacant")))))))) -> LGOO7R | K31: =CONCATENATE(J31,AY31) -> LGOO7RF | L31: =IF(AX31="Regional Office",(IF(AY31="M","RM","RF")),IF(AX31="Abra",(IF(AY31="M","AbM","AbF")),IF(AX31="Baguio City",(IF(AY31="M","BCM","BCF")),IF(AX31="Apayao",(IF(AY31="M","ApM","ApF")),IF(AX31="Benguet",(IF(AY31="M","BM","BF")),IF(AX31="Ifugao",(IF(AY31="M","IM","IF")),IF(AX31="Kalinga",(IF(AY31="M","KM","KF")),IF(AX31="Mt. Province",(IF(AY31="M","MPM","MPF")),"XXX")))))))) -> RF | M31: 3 | N31: 3 | O31: 3 | P31: 3 | AH31: =VLOOKUP(C31,idica,2,FALSE)*12 -> 1000872 | AI31: =(SUMPRODUCT((norman=C31)*(grace=AJ31)*(barnachea)))*12 -> 1000872 | AJ31: 1 | AK31: 011 | AL31: P | AM31: K | AN31: 310100100001000 | AO31: Regional Office | AP31: MED | AQ31: Regional Office | AR31: GUERZON | AS31: Marleen | AT31: Montano | AU31: =LEFT(AT31)&IF(ISNUMBER(FIND(" ",AT31)),MID(AT31,FIND(" ",AT31)+1,1),"")&IF(ISNUMBER(FIND(" ",AT31,FIND(" ",AT31)+1)),MID(AT31,FIND(" ",AT31,FIND(" ",AT31)+1)+1,1),"") -> M | AV31: =PROPER(CONCATENATE(AS31," ",AU31,". ",AR31)) -> Marleen M. Guerzon | AW31: =CONCATENATE(AR31,", ",AS31," ",AT31) -> GUERZON, Marleen Montano | AX31: Regional Office | AY31: F | AZ31: 24396 | BA31: =DATEDIF(AZ31,TODAY(),"Y") -> 59 | BB31: =IF(BA31<30,"A",IF(BA31<40,"B",IF(BA31<50,"C",IF(BA31<60,"D",IF(BA31<65,"E","VACANT"))))) -> D | BC31: =+IF(AX31="Regional Office",(IF(BB31="A","RA",(IF(BB31="B","RB",IF(BB31="C","RC",IF(BB31="D","RD",IF(BB31="E","RE","VACANT"))))))),IF(AX31="Abra",(IF(BB31="A","AbA",(IF(BB31="B","AbB",IF(BB31="C","AbC",IF(BB31="D","AbD",IF(BB31="E","AbE","VACANT"))))))),IF(AX31="Baguio City",(IF(BB31="A","BCA",(IF(BB31="B","BCB",IF(BB31="C","BCC",IF(BB31="D","BCD",IF(BB31="E","BCE","VACANT"))))))),IF(AX31="Apayao",(IF(BB31="A","ApA",(IF(BB31="B","ApB",IF(BB31="C","ApC",IF(BB31="D","ApD",IF(BB31="E","ApE","VACANT"))))))),IF(AX31="Benguet",(IF(BB31="A","BA",(IF(BB31="B","BB",IF(BB31="C","BC",IF(BB31="D","BD",IF(BB31="E","BE","VACANT"))))))),IF(AX31="Ifugao",(IF(BB31="A","IA",(IF(BB31="B","IB",IF(BB31="C","IC",IF(BB31="D","ID",IF(BB31="E","IE","VACANT"))))))),IF(AX31="Kalinga",(IF(BB31="A","KA",(IF(BB31="B","KB",IF(BB31="C","KC",IF(BB31="D","KD",IF(BB31="E","KE","VACANT"))))))),IF(AX31="Mt. Province",(IF(BB31="A","MPA",(IF(BB31="B","MPB",IF(BB31="C","MPC",IF(BB31="D","MPD",IF(BB31="E","MPE","VACANT"))))))),"XXX")))))))) -> RD | BD31: =CONCATENATE(BC31,AY31) -> RDF | BE31: =CONCATENATE(I31,BD31) -> LGOO7RDF | BF31: 127-933-026 | BG31: 32511 | BH31: 32511 | BI31: =DATEDIF(BG31,TODAY(),"Y") -> 37 | BJ31: =DATEDIF(BH31,TODAY(),"Y") -> 37 | BK31: 43132 | BL31: =DATEDIF(BK31,TODAY(),"Y") -> 8 | BM31: P | BN31: CSP | BO31: PhD - 6u | BP31: transfer from PO - CH Benguet feb 2019 | BQ31: =CONCATENATE(2,AY31,BM31) -> 2FP
A32: OSEC-DILGB-LGOO6-14-1998 | B32: Local Government Operations Officer VI | C32: 22 | I32: LGOO6 | J32: =IF(AX32="Regional Office",CONCATENATE(I32,"R"),IF(AX32="Abra",CONCATENATE(I32,"Ab"),IF(AX32="Apayao",CONCATENATE(I32,"Ap"),IF(AX32="Baguio City",CONCATENATE(I32,"BC"),IF(AX32="Ifugao",CONCATENATE(I32,"I"),IF(AX32="Mt. Province",CONCATENATE(I32,"MP"),IF(AX32="Kalinga",CONCATENATE(I32,"K"),IF(AX32="Benguet",CONCATENATE(I32,"B"),"Vacant")))))))) -> LGOO6R | K32: =CONCATENATE(J32,AY32) -> LGOO6RF | L32: =IF(AX32="Regional Office",(IF(AY32="M","RM","RF")),IF(AX32="Abra",(IF(AY32="M","AbM","AbF")),IF(AX32="Baguio City",(IF(AY32="M","BCM","BCF")),IF(AX32="Apayao",(IF(AY32="M","ApM","ApF")),IF(AX32="Benguet",(IF(AY32="M","BM","BF")),IF(AX32="Ifugao",(IF(AY32="M","IM","IF")),IF(AX32="Kalinga",(IF(AY32="M","KM","KF")),IF(AX32="Mt. Province",(IF(AY32="M","MPM","MPF")),"XXX")))))))) -> RF | M32: 3 | N32: 3 | O32: 3 | P32: 3 | AH32: =VLOOKUP(C32,idica,2,FALSE)*12 -> 783828 | AI32: =(SUMPRODUCT((norman=C32)*(grace=AJ32)*(barnachea)))*12 -> 809628 | AJ32: 3 | AK32: 011 | AL32: R | AM32: T | AN32: 310100100001000 | AO32: Regional Office | AP32: MED | AQ32: Regional Office | AR32: ADNOL | AS32: Bable | AT32: Ged-ang | AU32: =LEFT(AT32)&IF(ISNUMBER(FIND(" ",AT32)),MID(AT32,FIND(" ",AT32)+1,1),"")&IF(ISNUMBER(FIND(" ",AT32,FIND(" ",AT32)+1)),MID(AT32,FIND(" ",AT32,FIND(" ",AT32)+1)+1,1),"") -> G | AV32: =PROPER(CONCATENATE(AS32," ",AU32,". ",AR32)) -> Bable G. Adnol | AW32: =CONCATENATE(AR32,", ",AS32," ",AT32) -> ADNOL, Bable Ged-ang | AX32: Regional Office | AY32: F | AZ32: 25374 | BA32: =DATEDIF(AZ32,TODAY(),"Y") -> 56 | BB32: =IF(BA32<30,"A",IF(BA32<40,"B",IF(BA32<50,"C",IF(BA32<60,"D",IF(BA32<65,"E","VACANT"))))) -> D | BC32: =+IF(AX32="Regional Office",(IF(BB32="A","RA",(IF(BB32="B","RB",IF(BB32="C","RC",IF(BB32="D","RD",IF(BB32="E","RE","VACANT"))))))),IF(AX32="Abra",(IF(BB32="A","AbA",(IF(BB32="B","AbB",IF(BB32="C","AbC",IF(BB32="D","AbD",IF(BB32="E","AbE","VACANT"))))))),IF(AX32="Baguio City",(IF(BB32="A","BCA",(IF(BB32="B","BCB",IF(BB32="C","BCC",IF(BB32="D","BCD",IF(BB32="E","BCE","VACANT"))))))),IF(AX32="Apayao",(IF(BB32="A","ApA",(IF(BB32="B","ApB",IF(BB32="C","ApC",IF(BB32="D","ApD",IF(BB32="E","ApE","VACANT"))))))),IF(AX32="Benguet",(IF(BB32="A","BA",(IF(BB32="B","BB",IF(BB32="C","BC",IF(BB32="D","BD",IF(BB32="E","BE","VACANT"))))))),IF(AX32="Ifugao",(IF(BB32="A","IA",(IF(BB32="B","IB",IF(BB32="C","IC",IF(BB32="D","ID",IF(BB32="E","IE","VACANT"))))))),IF(AX32="Kalinga",(IF(BB32="A","KA",(IF(BB32="B","KB",IF(BB32="C","KC",IF(BB32="D","KD",IF(BB32="E","KE","VACANT"))))))),IF(AX32="Mt. Province",(IF(BB32="A","MPA",(IF(BB32="B","MPB",IF(BB32="C","MPC",IF(BB32="D","MPD",IF(BB32="E","MPE","VACANT"))))))),"XXX")))))))) -> RD | BD32: =CONCATENATE(BC32,AY32) -> RDF | BE32: =CONCATENATE(I32,BD32) -> LGOO6RDF | BF32: 185-743-190 | BG32: 34808 | BH32: 34808 | BI32: =DATEDIF(BG32,TODAY(),"Y") -> 30 | BJ32: =DATEDIF(BH32,TODAY(),"Y") -> 30 | BK32: 40262 | BL32: =DATEDIF(BK32,TODAY(),"Y") -> 15 | BM32: P | BN32: CSP | BO32: PhD | BQ32: =CONCATENATE(2,AY32,BM32) -> 2FP
A33: OSEC-DILGB-LGOO5-99-2010 | B33: Local Government Operations Officer V | C33: 20 | I33: LGOO5 | J33: =IF(AX33="Regional Office",CONCATENATE(I33,"R"),IF(AX33="Abra",CONCATENATE(I33,"Ab"),IF(AX33="Apayao",CONCATENATE(I33,"Ap"),IF(AX33="Baguio City",CONCATENATE(I33,"BC"),IF(AX33="Ifugao",CONCATENATE(I33,"I"),IF(AX33="Mt. Province",CONCATENATE(I33,"MP"),IF(AX33="Kalinga",CONCATENATE(I33,"K"),IF(AX33="Benguet",CONCATENATE(I33,"B"),"Vacant")))))))) -> LGOO5R | K33: =CONCATENATE(J33,AY33) -> LGOO5RF | L33: =IF(AX33="Regional Office",(IF(AY33="M","RM","RF")),IF(AX33="Abra",(IF(AY33="M","AbM","AbF")),IF(AX33="Baguio City",(IF(AY33="M","BCM","BCF")),IF(AX33="Apayao",(IF(AY33="M","ApM","ApF")),IF(AX33="Benguet",(IF(AY33="M","BM","BF")),IF(AX33="Ifugao",(IF(AY33="M","IM","IF")),IF(AX33="Kalinga",(IF(AY33="M","KM","KF")),IF(AX33="Mt. Province",(IF(AY33="M","MPM","MPF")),"XXX")))))))) -> RF | M33: 3 | N33: 3 | O33: 3 | P33: 3 | AH33: =VLOOKUP(C33,idica,2,FALSE)*12 -> 613860 | AI33: =(SUMPRODUCT((norman=C33)*(grace=AJ33)*(barnachea)))*12 -> 623868 | AJ33: 2 | AK33: 011 | AL33: R | AM33: T | AN33: 310100100001000 | AO33: Regional Office | AP33: MED | AQ33: Regional Office | AR33: RIMANDO | AS33: Marie Cris | AT33: Lim | AU33: =LEFT(AT33)&IF(ISNUMBER(FIND(" ",AT33)),MID(AT33,FIND(" ",AT33)+1,1),"")&IF(ISNUMBER(FIND(" ",AT33,FIND(" ",AT33)+1)),MID(AT33,FIND(" ",AT33,FIND(" ",AT33)+1)+1,1),"") -> L | AV33: =PROPER(CONCATENATE(AS33," ",AU33,". ",AR33)) -> Marie Cris L. Rimando | AW33: =CONCATENATE(AR33,", ",AS33," ",AT33) -> RIMANDO, Marie Cris Lim | AX33: Regional Office | AY33: F | AZ33: 24278 | BA33: =DATEDIF(AZ33,TODAY(),"Y") -> 59 | BB33: =IF(BA33<30,"A",IF(BA33<40,"B",IF(BA33<50,"C",IF(BA33<60,"D",IF(BA33<65,"E","VACANT"))))) -> D | BC33: =+IF(AX33="Regional Office",(IF(BB33="A","RA",(IF(BB33="B","RB",IF(BB33="C","RC",IF(BB33="D","RD",IF(BB33="E","RE","VACANT"))))))),IF(AX33="Abra",(IF(BB33="A","AbA",(IF(BB33="B","AbB",IF(BB33="C","AbC",IF(BB33="D","AbD",IF(BB33="E","AbE","VACANT"))))))),IF(AX33="Baguio City",(IF(BB33="A","BCA",(IF(BB33="B","BCB",IF(BB33="C","BCC",IF(BB33="D","BCD",IF(BB33="E","BCE","VACANT"))))))),IF(AX33="Apayao",(IF(BB33="A","ApA",(IF(BB33="B","ApB",IF(BB33="C","ApC",IF(BB33="D","ApD",IF(BB33="E","ApE","VACANT"))))))),IF(AX33="Benguet",(IF(BB33="A","BA",(IF(BB33="B","BB",IF(BB33="C","BC",IF(BB33="D","BD",IF(BB33="E","BE","VACANT"))))))),IF(AX33="Ifugao",(IF(BB33="A","IA",(IF(BB33="B","IB",IF(BB33="C","IC",IF(BB33="D","ID",IF(BB33="E","IE","VACANT"))))))),IF(AX33="Kalinga",(IF(BB33="A","KA",(IF(BB33="B","KB",IF(BB33="C","KC",IF(BB33="D","KD",IF(BB33="E","KE","VACANT"))))))),IF(AX33="Mt. Province",(IF(BB33="A","MPA",(IF(BB33="B","MPB",IF(BB33="C","MPC",IF(BB33="D","MPD",IF(BB33="E","MPE","VACANT"))))))),"XXX")))))))) -> RD | BD33: =CONCATENATE(BC33,AY33) -> RDF | BE33: =CONCATENATE(I33,BD33) -> LGOO5RDF | BF33: 129-983-169 | BG33: 36374 | BH33: 36374 | BI33: =DATEDIF(BG33,TODAY(),"Y") -> 26 | BJ33: =DATEDIF(BH33,TODAY(),"Y") -> 26 | BK33: 41526 | BL33: =DATEDIF(BK33,TODAY(),"Y") -> 12 | BM33: P | BN33: CSP | BO33: PhD | BP33: Shifting | BQ33: =CONCATENATE(2,AY33,BM33) -> 2FP
A34: OSEC-DILGB-LGOO5-824-1998 | B34: Local Government Operations Officer V | C34: 20 | I34: LGOO5 | J34: =IF(AX34="Regional Office",CONCATENATE(I34,"R"),IF(AX34="Abra",CONCATENATE(I34,"Ab"),IF(AX34="Apayao",CONCATENATE(I34,"Ap"),IF(AX34="Baguio City",CONCATENATE(I34,"BC"),IF(AX34="Ifugao",CONCATENATE(I34,"I"),IF(AX34="Mt. Province",CONCATENATE(I34,"MP"),IF(AX34="Kalinga",CONCATENATE(I34,"K"),IF(AX34="Benguet",CONCATENATE(I34,"B"),"Vacant")))))))) -> LGOO5R | K34: =CONCATENATE(J34,AY34) -> LGOO5RF | L34: =IF(AX34="Regional Office",(IF(AY34="M","RM","RF")),IF(AX34="Abra",(IF(AY34="M","AbM","AbF")),IF(AX34="Baguio City",(IF(AY34="M","BCM","BCF")),IF(AX34="Apayao",(IF(AY34="M","ApM","ApF")),IF(AX34="Benguet",(IF(AY34="M","BM","BF")),IF(AX34="Ifugao",(IF(AY34="M","IM","IF")),IF(AX34="Kalinga",(IF(AY34="M","KM","KF")),IF(AX34="Mt. Province",(IF(AY34="M","MPM","MPF")),"XXX")))))))) -> RF | M34: 3 | N34: 3 | O34: 3 | P34: 3 | AH34: =VLOOKUP(C34,idica,2,FALSE)*12 -> 613860 | AI34: =(SUMPRODUCT((norman=C34)*(grace=AJ34)*(barnachea)))*12 -> 634056 | AJ34: 3 | AK34: 011 | AL34: R | AM34: T | AN34: 310100100001000 | AO34: Regional Office | AP34: MED | AQ34: Regional Office | AR34: GARCIA | AS34: Florinda | AT34: Manuyag | AU34: =LEFT(AT34)&IF(ISNUMBER(FIND(" ",AT34)),MID(AT34,FIND(" ",AT34)+1,1),"")&IF(ISNUMBER(FIND(" ",AT34,FIND(" ",AT34)+1)),MID(AT34,FIND(" ",AT34,FIND(" ",AT34)+1)+1,1),"") -> M | AV34: =PROPER(CONCATENATE(AS34," ",AU34,". ",AR34)) -> Florinda M. Garcia | AW34: =CONCATENATE(AR34,", ",AS34," ",AT34) -> GARCIA, Florinda Manuyag | AX34: Regional Office | AY34: F | AZ34: 22504 | BA34: =DATEDIF(AZ34,TODAY(),"Y") -> 64 | BB34: =IF(BA34<30,"A",IF(BA34<40,"B",IF(BA34<50,"C",IF(BA34<60,"D",IF(BA34<65,"E","VACANT"))))) -> E | BC34: =+IF(AX34="Regional Office",(IF(BB34="A","RA",(IF(BB34="B","RB",IF(BB34="C","RC",IF(BB34="D","RD",IF(BB34="E","RE","VACANT"))))))),IF(AX34="Abra",(IF(BB34="A","AbA",(IF(BB34="B","AbB",IF(BB34="C","AbC",IF(BB34="D","AbD",IF(BB34="E","AbE","VACANT"))))))),IF(AX34="Baguio City",(IF(BB34="A","BCA",(IF(BB34="B","BCB",IF(BB34="C","BCC",IF(BB34="D","BCD",IF(BB34="E","BCE","VACANT"))))))),IF(AX34="Apayao",(IF(BB34="A","ApA",(IF(BB34="B","ApB",IF(BB34="C","ApC",IF(BB34="D","ApD",IF(BB34="E","ApE","VACANT"))))))),IF(AX34="Benguet",(IF(BB34="A","BA",(IF(BB34="B","BB",IF(BB34="C","BC",IF(BB34="D","BD",IF(BB34="E","BE","VACANT"))))))),IF(AX34="Ifugao",(IF(BB34="A","IA",(IF(BB34="B","IB",IF(BB34="C","IC",IF(BB34="D","ID",IF(BB34="E","IE","VACANT"))))))),IF(AX34="Kalinga",(IF(BB34="A","KA",(IF(BB34="B","KB",IF(BB34="C","KC",IF(BB34="D","KD",IF(BB34="E","KE","VACANT"))))))),IF(AX34="Mt. Province",(IF(BB34="A","MPA",(IF(BB34="B","MPB",IF(BB34="C","MPC",IF(BB34="D","MPD",IF(BB34="E","MPE","VACANT"))))))),"XXX")))))))) -> RE | BD34: =CONCATENATE(BC34,AY34) -> REF | BE34: =CONCATENATE(I34,BD34) -> LGOO5REF | BF34: 122-174-963 | BG34: 36100 | BH34: 36100 | BI34: =DATEDIF(BG34,TODAY(),"Y") -> 27 | BJ34: =DATEDIF(BH34,TODAY(),"Y") -> 27 | BK34: 41149 | BL34: =DATEDIF(BK34,TODAY(),"Y") -> 13 | BM34: P | BN34: CSP | BO34: MPA | BP34: Shifting | BQ34: =CONCATENATE(2,AY34,BM34) -> 2FP
A35: OSEC-DILGB-LGOO5-835-1998 | B35: Local Government Operations Officer V | C35: 20 | I35: LGOO5 | J35: =IF(AX35="Regional Office",CONCATENATE(I35,"R"),IF(AX35="Abra",CONCATENATE(I35,"Ab"),IF(AX35="Apayao",CONCATENATE(I35,"Ap"),IF(AX35="Baguio City",CONCATENATE(I35,"BC"),IF(AX35="Ifugao",CONCATENATE(I35,"I"),IF(AX35="Mt. Province",CONCATENATE(I35,"MP"),IF(AX35="Kalinga",CONCATENATE(I35,"K"),IF(AX35="Benguet",CONCATENATE(I35,"B"),"Vacant")))))))) -> LGOO5R | K35: =CONCATENATE(J35,AY35) -> LGOO5RM | L35: =IF(AX35="Regional Office",(IF(AY35="M","RM","RF")),IF(AX35="Abra",(IF(AY35="M","AbM","AbF")),IF(AX35="Baguio City",(IF(AY35="M","BCM","BCF")),IF(AX35="Apayao",(IF(AY35="M","ApM","ApF")),IF(AX35="Benguet",(IF(AY35="M","BM","BF")),IF(AX35="Ifugao",(IF(AY35="M","IM","IF")),IF(AX35="Kalinga",(IF(AY35="M","KM","KF")),IF(AX35="Mt. Province",(IF(AY35="M","MPM","MPF")),"XXX")))))))) -> RM | M35: 3 | N35: 3 | O35: 3 | P35: 3 | AH35: =VLOOKUP(C35,idica,2,FALSE)*12 -> 613860 | AI35: =(SUMPRODUCT((norman=C35)*(grace=AJ35)*(barnachea)))*12 -> 613860 | AJ35: 1 | AK35: 011 | AL35: R | AM35: T | AN35: 310100100001000 | AO35: Regional Office | AP35: CDD | AQ35: Regional Office | AR35: TINDUNGAN | AS35: Kenneth | AT35: Cuyapi | AU35: =LEFT(AT35)&IF(ISNUMBER(FIND(" ",AT35)),MID(AT35,FIND(" ",AT35)+1,1),"")&IF(ISNUMBER(FIND(" ",AT35,FIND(" ",AT35)+1)),MID(AT35,FIND(" ",AT35,FIND(" ",AT35)+1)+1,1),"") -> C | AV35: =PROPER(CONCATENATE(AS35," ",AU35,". ",AR35)) -> Kenneth C. Tindungan | AW35: =CONCATENATE(AR35,", ",AS35," ",AT35) -> TINDUNGAN, Kenneth Cuyapi | AX35: Regional Office | AY35: M | AZ35: 29806 | BA35: =DATEDIF(AZ35,TODAY(),"Y") -> 44 | BB35: =IF(BA35<30,"A",IF(BA35<40,"B",IF(BA35<50,"C",IF(BA35<60,"D",IF(BA35<65,"E","VACANT"))))) -> C | BC35: =+IF(AX35="Regional Office",(IF(BB35="A","RA",(IF(BB35="B","RB",IF(BB35="C","RC",IF(BB35="D","RD",IF(BB35="E","RE","VACANT"))))))),IF(AX35="Abra",(IF(BB35="A","AbA",(IF(BB35="B","AbB",IF(BB35="C","AbC",IF(BB35="D","AbD",IF(BB35="E","AbE","VACANT"))))))),IF(AX35="Baguio City",(IF(BB35="A","BCA",(IF(BB35="B","BCB",IF(BB35="C","BCC",IF(BB35="D","BCD",IF(BB35="E","BCE","VACANT"))))))),IF(AX35="Apayao",(IF(BB35="A","ApA",(IF(BB35="B","ApB",IF(BB35="C","ApC",IF(BB35="D","ApD",IF(BB35="E","ApE","VACANT"))))))),IF(AX35="Benguet",(IF(BB35="A","BA",(IF(BB35="B","BB",IF(BB35="C","BC",IF(BB35="D","BD",IF(BB35="E","BE","VACANT"))))))),IF(AX35="Ifugao",(IF(BB35="A","IA",(IF(BB35="B","IB",IF(BB35="C","IC",IF(BB35="D","ID",IF(BB35="E","IE","VACANT"))))))),IF(AX35="Kalinga",(IF(BB35="A","KA",(IF(BB35="B","KB",IF(BB35="C","KC",IF(BB35="D","KD",IF(BB35="E","KE","VACANT"))))))),IF(AX35="Mt. Province",(IF(BB35="A","MPA",(IF(BB35="B","MPB",IF(BB35="C","MPC",IF(BB35="D","MPD",IF(BB35="E","MPE","VACANT"))))))),"XXX")))))))) -> RC | BD35: =CONCATENATE(BC35,AY35) -> RCM | BE35: =CONCATENATE(I35,BD35) -> LGOO5RCM | BF35: 927-934-009 | BG35: 41372 | BH35: 41372 | BI35: =DATEDIF(BG35,TODAY(),"Y") -> 12 | BJ35: =DATEDIF(BH35,TODAY(),"Y") -> 12 | BK35: 43168 | BL35: =DATEDIF(BK35,TODAY(),"Y") -> 8 | BM35: P | BN35: CSP | BO35: MAEM | BQ35: =CONCATENATE(2,AY35,BM35) -> 2MP
A36: OSEC-DILGB-LGOO4-166-1998 | B36: Local Government Operations Officer IV | C36: 18 | I36: LGOO4 | J36: =IF(AX36="Regional Office",CONCATENATE(I36,"R"),IF(AX36="Abra",CONCATENATE(I36,"Ab"),IF(AX36="Apayao",CONCATENATE(I36,"Ap"),IF(AX36="Baguio City",CONCATENATE(I36,"BC"),IF(AX36="Ifugao",CONCATENATE(I36,"I"),IF(AX36="Mt. Province",CONCATENATE(I36,"MP"),IF(AX36="Kalinga",CONCATENATE(I36,"K"),IF(AX36="Benguet",CONCATENATE(I36,"B"),"Vacant")))))))) -> LGOO4R | K36: =CONCATENATE(J36,AY36) -> LGOO4RF | L36: =IF(AX36="Regional Office",(IF(AY36="M","RM","RF")),IF(AX36="Abra",(IF(AY36="M","AbM","AbF")),IF(AX36="Baguio City",(IF(AY36="M","BCM","BCF")),IF(AX36="Apayao",(IF(AY36="M","ApM","ApF")),IF(AX36="Benguet",(IF(AY36="M","BM","BF")),IF(AX36="Ifugao",(IF(AY36="M","IM","IF")),IF(AX36="Kalinga",(IF(AY36="M","KM","KF")),IF(AX36="Mt. Province",(IF(AY36="M","MPM","MPF")),"XXX")))))))) -> RF | M36: 3 | N36: 3 | O36: 3 | P36: 3 | AH36: =VLOOKUP(C36,idica,2,FALSE)*12 -> 487644 | AI36: =(SUMPRODUCT((norman=C36)*(grace=AJ36)*(barnachea)))*12 -> 487644 | AJ36: 1 | AK36: 011 | AL36: R | AM36: T | AN36: 310100100001000 | AO36: Regional Office | AP36: CDD | AQ36: Region | AR36: CANULLAS | AS36: Mary Jheama Rachine | AT36: Esperanzate | AU36: =LEFT(AT36)&IF(ISNUMBER(FIND(" ",AT36)),MID(AT36,FIND(" ",AT36)+1,1),"")&IF(ISNUMBER(FIND(" ",AT36,FIND(" ",AT36)+1)),MID(AT36,FIND(" ",AT36,FIND(" ",AT36)+1)+1,1),"") -> E | AV36: =PROPER(CONCATENATE(AS36," ",AU36,". ",AR36)) -> Mary Jheama Rachine E. Canullas | AW36: =CONCATENATE(AR36,", ",AS36," ",AT36) -> CANULLAS, Mary Jheama Rachine Esperanzate | AX36: Regional Office | AY36: F | AZ36: 30849 | BA36: =DATEDIF(AZ36,TODAY(),"Y") -> 41 | BB36: =IF(BA36<30,"A",IF(BA36<40,"B",IF(BA36<50,"C",IF(BA36<60,"D",IF(BA36<65,"E","VACANT"))))) -> C | BC36: =+IF(AX36="Regional Office",(IF(BB36="A","RA",(IF(BB36="B","RB",IF(BB36="C","RC",IF(BB36="D","RD",IF(BB36="E","RE","VACANT"))))))),IF(AX36="Abra",(IF(BB36="A","AbA",(IF(BB36="B","AbB",IF(BB36="C","AbC",IF(BB36="D","AbD",IF(BB36="E","AbE","VACANT"))))))),IF(AX36="Baguio City",(IF(BB36="A","BCA",(IF(BB36="B","BCB",IF(BB36="C","BCC",IF(BB36="D","BCD",IF(BB36="E","BCE","VACANT"))))))),IF(AX36="Apayao",(IF(BB36="A","ApA",(IF(BB36="B","ApB",IF(BB36="C","ApC",IF(BB36="D","ApD",IF(BB36="E","ApE","VACANT"))))))),IF(AX36="Benguet",(IF(BB36="A","BA",(IF(BB36="B","BB",IF(BB36="C","BC",IF(BB36="D","BD",IF(BB36="E","BE","VACANT"))))))),IF(AX36="Ifugao",(IF(BB36="A","IA",(IF(BB36="B","IB",IF(BB36="C","IC",IF(BB36="D","ID",IF(BB36="E","IE","VACANT"))))))),IF(AX36="Kalinga",(IF(BB36="A","KA",(IF(BB36="B","KB",IF(BB36="C","KC",IF(BB36="D","KD",IF(BB36="E","KE","VACANT"))))))),IF(AX36="Mt. Province",(IF(BB36="A","MPA",(IF(BB36="B","MPB",IF(BB36="C","MPC",IF(BB36="D","MPD",IF(BB36="E","MPE","VACANT"))))))),"XXX")))))))) -> RC | BD36: =CONCATENATE(BC36,AY36) -> RCF | BE36: =CONCATENATE(I36,BD36) -> LGOO4RCF | BF36: 252-831-893 | BG36: 39475 | BH36: 39475 | BI36: =DATEDIF(BG36,TODAY(),"Y") -> 18 | BJ36: =DATEDIF(BH36,TODAY(),"Y") -> 18 | BK36: 43129 | BL36: =DATEDIF(BK36,TODAY(),"Y") -> 8 | BM36: P | BN36: CSP | BO36: BSEd | BP36: Region | BQ36: =CONCATENATE(2,AY36,BM36) -> 2FP
A37: OSEC-DILGB-LGOO4-167-1998 | B37: Local Government Operations Officer IV | C37: 18 | I37: LGOO4 | J37: =IF(AX37="Regional Office",CONCATENATE(I37,"R"),IF(AX37="Abra",CONCATENATE(I37,"Ab"),IF(AX37="Apayao",CONCATENATE(I37,"Ap"),IF(AX37="Baguio City",CONCATENATE(I37,"BC"),IF(AX37="Ifugao",CONCATENATE(I37,"I"),IF(AX37="Mt. Province",CONCATENATE(I37,"MP"),IF(AX37="Kalinga",CONCATENATE(I37,"K"),IF(AX37="Benguet",CONCATENATE(I37,"B"),"Vacant")))))))) -> LGOO4R | K37: =CONCATENATE(J37,AY37) -> LGOO4RF | L37: =IF(AX37="Regional Office",(IF(AY37="M","RM","RF")),IF(AX37="Abra",(IF(AY37="M","AbM","AbF")),IF(AX37="Baguio City",(IF(AY37="M","BCM","BCF")),IF(AX37="Apayao",(IF(AY37="M","ApM","ApF")),IF(AX37="Benguet",(IF(AY37="M","BM","BF")),IF(AX37="Ifugao",(IF(AY37="M","IM","IF")),IF(AX37="Kalinga",(IF(AY37="M","KM","KF")),IF(AX37="Mt. Province",(IF(AY37="M","MPM","MPF")),"XXX")))))))) -> RF | M37: 3 | N37: 3 | O37: 3 | P37: 3 | AH37: =VLOOKUP(C37,idica,2,FALSE)*12 -> 487644 | AI37: =(SUMPRODUCT((norman=C37)*(grace=AJ37)*(barnachea)))*12 -> 499800 | AJ37: 3 | AK37: 011 | AL37: R | AM37: T | AN37: 310100100001000 | AO37: Regional Office | AP37: MED | AQ37: Regional Office | AR37: BUENA | AS37: Maria Consolacion | AT37: Salibad | AU37: =LEFT(AT37)&IF(ISNUMBER(FIND(" ",AT37)),MID(AT37,FIND(" ",AT37)+1,1),"")&IF(ISNUMBER(FIND(" ",AT37,FIND(" ",AT37)+1)),MID(AT37,FIND(" ",AT37,FIND(" ",AT37)+1)+1,1),"") -> S | AV37: =PROPER(CONCATENATE(AS37," ",AU37,". ",AR37)) -> Maria Consolacion S. Buena | AW37: =CONCATENATE(AR37,", ",AS37," ",AT37) -> BUENA, Maria Consolacion Salibad | AX37: Regional Office | AY37: F | AZ37: 29798 | BA37: =DATEDIF(AZ37,TODAY(),"Y") -> 44 | BB37: =IF(BA37<30,"A",IF(BA37<40,"B",IF(BA37<50,"C",IF(BA37<60,"D",IF(BA37<65,"E","VACANT"))))) -> C | BC37: =+IF(AX37="Regional Office",(IF(BB37="A","RA",(IF(BB37="B","RB",IF(BB37="C","RC",IF(BB37="D","RD",IF(BB37="E","RE","VACANT"))))))),IF(AX37="Abra",(IF(BB37="A","AbA",(IF(BB37="B","AbB",IF(BB37="C","AbC",IF(BB37="D","AbD",IF(BB37="E","AbE","VACANT"))))))),IF(AX37="Baguio City",(IF(BB37="A","BCA",(IF(BB37="B","BCB",IF(BB37="C","BCC",IF(BB37="D","BCD",IF(BB37="E","BCE","VACANT"))))))),IF(AX37="Apayao",(IF(BB37="A","ApA",(IF(BB37="B","ApB",IF(BB37="C","ApC",IF(BB37="D","ApD",IF(BB37="E","ApE","VACANT"))))))),IF(AX37="Benguet",(IF(BB37="A","BA",(IF(BB37="B","BB",IF(BB37="C","BC",IF(BB37="D","BD",IF(BB37="E","BE","VACANT"))))))),IF(AX37="Ifugao",(IF(BB37="A","IA",(IF(BB37="B","IB",IF(BB37="C","IC",IF(BB37="D","ID",IF(BB37="E","IE","VACANT"))))))),IF(AX37="Kalinga",(IF(BB37="A","KA",(IF(BB37="B","KB",IF(BB37="C","KC",IF(BB37="D","KD",IF(BB37="E","KE","VACANT"))))))),IF(AX37="Mt. Province",(IF(BB37="A","MPA",(IF(BB37="B","MPB",IF(BB37="C","MPC",IF(BB37="D","MPD",IF(BB37="E","MPE","VACANT"))))))),"XXX")))))))) -> RC | BD37: =CONCATENATE(BC37,AY37) -> RCF | BE37: =CONCATENATE(I37,BD37) -> LGOO4RCF | BF37: 927-999-540 | BG37: 37586 | BH37: 37586 | BI37: =DATEDIF(BG37,TODAY(),"Y") -> 23 | BJ37: =DATEDIF(BH37,TODAY(),"Y") -> 23 | BK37: 41254 | BL37: =DATEDIF(BK37,TODAY(),"Y") -> 13 | BM37: P | BN37: CSP | BO37: BSC-Banking & Fin | BP37: 06/08/16 transfer frm PLO | BQ37: =CONCATENATE(2,AY37,BM37) -> 2FP
A38: OSEC-DILGB-STAT2-101-2010 | B38: Statistician II | C38: 15 | I38: STAT2 | J38: =IF(AX38="Regional Office",CONCATENATE(I38,"R"),IF(AX38="Abra",CONCATENATE(I38,"Ab"),IF(AX38="Apayao",CONCATENATE(I38,"Ap"),IF(AX38="Baguio City",CONCATENATE(I38,"BC"),IF(AX38="Ifugao",CONCATENATE(I38,"I"),IF(AX38="Mt. Province",CONCATENATE(I38,"MP"),IF(AX38="Kalinga",CONCATENATE(I38,"K"),IF(AX38="Benguet",CONCATENATE(I38,"B"),"Vacant")))))))) -> STAT2R | K38: =CONCATENATE(J38,AY38) -> STAT2RM | L38: =IF(AX38="Regional Office",(IF(AY38="M","RM","RF")),IF(AX38="Abra",(IF(AY38="M","AbM","AbF")),IF(AX38="Baguio City",(IF(AY38="M","BCM","BCF")),IF(AX38="Apayao",(IF(AY38="M","ApM","ApF")),IF(AX38="Benguet",(IF(AY38="M","BM","BF")),IF(AX38="Ifugao",(IF(AY38="M","IM","IF")),IF(AX38="Kalinga",(IF(AY38="M","KM","KF")),IF(AX38="Mt. Province",(IF(AY38="M","MPM","MPF")),"XXX")))))))) -> RM | M38: 2 | N38: 2 | O38: 2 | P38: 2 | AH38: =VLOOKUP(C38,idica,2,FALSE)*12 -> 366372 | AI38: =(SUMPRODUCT((norman=C38)*(grace=AJ38)*(barnachea)))*12 -> 366372 | AJ38: 1 | AK38: 011 | AL38: R | AM38: S | AN38: 310100100001000 | AO38: Regional Office | AP38: MED | AQ38: Regional Office | AR38: AZARCON | AS38: Danilo Jr | AT38: Estrella | AU38: =LEFT(AT38)&IF(ISNUMBER(FIND(" ",AT38)),MID(AT38,FIND(" ",AT38)+1,1),"")&IF(ISNUMBER(FIND(" ",AT38,FIND(" ",AT38)+1)),MID(AT38,FIND(" ",AT38,FIND(" ",AT38)+1)+1,1),"") -> E | AV38: =PROPER(CONCATENATE(AS38," ",AU38,". ",AR38)) -> Danilo Jr E. Azarcon | AW38: =CONCATENATE(AR38,", ",AS38," ",AT38) -> AZARCON, Danilo Jr Estrella | AX38: Regional Office | AY38: M | AZ38: 30193 | BA38: =DATEDIF(AZ38,TODAY(),"Y") -> 43 | BB38: =IF(BA38<30,"A",IF(BA38<40,"B",IF(BA38<50,"C",IF(BA38<60,"D",IF(BA38<65,"E","VACANT"))))) -> C | BC38: =+IF(AX38="Regional Office",(IF(BB38="A","RA",(IF(BB38="B","RB",IF(BB38="C","RC",IF(BB38="D","RD",IF(BB38="E","RE","VACANT"))))))),IF(AX38="Abra",(IF(BB38="A","AbA",(IF(BB38="B","AbB",IF(BB38="C","AbC",IF(BB38="D","AbD",IF(BB38="E","AbE","VACANT"))))))),IF(AX38="Baguio City",(IF(BB38="A","BCA",(IF(BB38="B","BCB",IF(BB38="C","BCC",IF(BB38="D","BCD",IF(BB38="E","BCE","VACANT"))))))),IF(AX38="Apayao",(IF(BB38="A","ApA",(IF(BB38="B","ApB",IF(BB38="C","ApC",IF(BB38="D","ApD",IF(BB38="E","ApE","VACANT"))))))),IF(AX38="Benguet",(IF(BB38="A","BA",(IF(BB38="B","BB",IF(BB38="C","BC",IF(BB38="D","BD",IF(BB38="E","BE","VACANT"))))))),IF(AX38="Ifugao",(IF(BB38="A","IA",(IF(BB38="B","IB",IF(BB38="C","IC",IF(BB38="D","ID",IF(BB38="E","IE","VACANT"))))))),IF(AX38="Kalinga",(IF(BB38="A","KA",(IF(BB38="B","KB",IF(BB38="C","KC",IF(BB38="D","KD",IF(BB38="E","KE","VACANT"))))))),IF(AX38="Mt. Province",(IF(BB38="A","MPA",(IF(BB38="B","MPB",IF(BB38="C","MPC",IF(BB38="D","MPD",IF(BB38="E","MPE","VACANT"))))))),"XXX")))))))) -> RC | BD38: =CONCATENATE(BC38,AY38) -> RCM | BE38: =CONCATENATE(I38,BD38) -> STAT2RCM | BF38: 410-034-788 | BG38: 42835 | BH38: 42835 | BI38: =DATEDIF(BG38,TODAY(),"Y") -> 8 | BJ38: =DATEDIF(BH38,TODAY(),"Y") -> 8 | BK38: 42835 | BL38: =DATEDIF(BK38,TODAY(),"Y") -> 8 | BM38: P | BN38: CSP | BO38: MBA 36u | BQ38: =CONCATENATE(2,AY38,BM38) -> 2MP
A39: OSEC-DILGB-STAT1-3-1998 | B39: Statistician I | C39: 11 | I39: STAT1 | J39: =IF(AX39="Regional Office",CONCATENATE(I39,"R"),IF(AX39="Abra",CONCATENATE(I39,"Ab"),IF(AX39="Apayao",CONCATENATE(I39,"Ap"),IF(AX39="Baguio City",CONCATENATE(I39,"BC"),IF(AX39="Ifugao",CONCATENATE(I39,"I"),IF(AX39="Mt. Province",CONCATENATE(I39,"MP"),IF(AX39="Kalinga",CONCATENATE(I39,"K"),IF(AX39="Benguet",CONCATENATE(I39,"B"),"Vacant")))))))) -> STAT1R | K39: =CONCATENATE(J39,AY39) -> STAT1RF | L39: =IF(AX39="Regional Office",(IF(AY39="M","RM","RF")),IF(AX39="Abra",(IF(AY39="M","AbM","AbF")),IF(AX39="Baguio City",(IF(AY39="M","BCM","BCF")),IF(AX39="Apayao",(IF(AY39="M","ApM","ApF")),IF(AX39="Benguet",(IF(AY39="M","BM","BF")),IF(AX39="Ifugao",(IF(AY39="M","IM","IF")),IF(AX39="Kalinga",(IF(AY39="M","KM","KF")),IF(AX39="Mt. Province",(IF(AY39="M","MPM","MPF")),"XXX")))))))) -> RF | M39: 2 | N39: 2 | O39: 2 | P39: 2 | AH39: =VLOOKUP(C39,idica,2,FALSE)*12 -> 249048 | AI39: =(SUMPRODUCT((norman=C39)*(grace=AJ39)*(barnachea)))*12 -> 252456 | AJ39: 2 | AK39: 011 | AL39: R | AM39: S | AN39: 310100100001000 | AO39: Regional Office | AP39: MED | AQ39: Regional Office | AR39: LOPEZ | AS39: Sesvir | AT39: Castañeda | AU39: =LEFT(AT39)&IF(ISNUMBER(FIND(" ",AT39)),MID(AT39,FIND(" ",AT39)+1,1),"")&IF(ISNUMBER(FIND(" ",AT39,FIND(" ",AT39)+1)),MID(AT39,FIND(" ",AT39,FIND(" ",AT39)+1)+1,1),"") -> C | AV39: =PROPER(CONCATENATE(AS39," ",AU39,". ",AR39)) -> Sesvir C. Lopez | AW39: =CONCATENATE(AR39,", ",AS39," ",AT39) -> LOPEZ, Sesvir Castañeda | AX39: Regional Office | AY39: F | AZ39: 29545 | BA39: =DATEDIF(AZ39,TODAY(),"Y") -> 45 | BB39: =IF(BA39<30,"A",IF(BA39<40,"B",IF(BA39<50,"C",IF(BA39<60,"D",IF(BA39<65,"E","VACANT"))))) -> C | BC39: =+IF(AX39="Regional Office",(IF(BB39="A","RA",(IF(BB39="B","RB",IF(BB39="C","RC",IF(BB39="D","RD",IF(BB39="E","RE","VACANT"))))))),IF(AX39="Abra",(IF(BB39="A","AbA",(IF(BB39="B","AbB",IF(BB39="C","AbC",IF(BB39="D","AbD",IF(BB39="E","AbE","VACANT"))))))),IF(AX39="Baguio City",(IF(BB39="A","BCA",(IF(BB39="B","BCB",IF(BB39="C","BCC",IF(BB39="D","BCD",IF(BB39="E","BCE","VACANT"))))))),IF(AX39="Apayao",(IF(BB39="A","ApA",(IF(BB39="B","ApB",IF(BB39="C","ApC",IF(BB39="D","ApD",IF(BB39="E","ApE","VACANT"))))))),IF(AX39="Benguet",(IF(BB39="A","BA",(IF(BB39="B","BB",IF(BB39="C","BC",IF(BB39="D","BD",IF(BB39="E","BE","VACANT"))))))),IF(AX39="Ifugao",(IF(BB39="A","IA",(IF(BB39="B","IB",IF(BB39="C","IC",IF(BB39="D","ID",IF(BB39="E","IE","VACANT"))))))),IF(AX39="Kalinga",(IF(BB39="A","KA",(IF(BB39="B","KB",IF(BB39="C","KC",IF(BB39="D","KD",IF(BB39="E","KE","VACANT"))))))),IF(AX39="Mt. Province",(IF(BB39="A","MPA",(IF(BB39="B","MPB",IF(BB39="C","MPC",IF(BB39="D","MPD",IF(BB39="E","MPE","VACANT"))))))),"XXX")))))))) -> RC | BD39: =CONCATENATE(BC39,AY39) -> RCF | BE39: =CONCATENATE(I39,BD39) -> STAT1RCF | BF39: 285-723-492 | BG39: 41946 | BH39: 41946 | BI39: =DATEDIF(BG39,TODAY(),"Y") -> 11 | BJ39: =DATEDIF(BH39,TODAY(),"Y") -> 11 | BK39: 41967 | BL39: =DATEDIF(BK39,TODAY(),"Y") -> 11 | BM39: P | BN39: CSP | BO39: MBA - 30u | BQ39: =CONCATENATE(2,AY39,BM39) -> 2FP
A40: OSEC-DILGB-ADA6-88-2010 | B40: Administrative Aide VI | C40: 6 | D40: Completion of two years studies in college | E40: None Required | F40: None Required | G40: Career Service (Subprofessional) First Eligibility | H40:  Prepares simple correspondences  Receives and records incoming and outgoing communications, correspondences  Performs highly skilled and responsible clerical work  Makes and receives calls  Maintains log books  Provides administrative support to trainings  Sorts and maintains documents/records (Memos, Circulars, Orders)  Prepares and maintains registry of records  Provides messengerial services  Performs other related duties that may be assigned or delegated. | I40: ADA6 | J40: =IF(AX40="Regional Office",CONCATENATE(I40,"R"),IF(AX40="Abra",CONCATENATE(I40,"Ab"),IF(AX40="Apayao",CONCATENATE(I40,"Ap"),IF(AX40="Baguio City",CONCATENATE(I40,"BC"),IF(AX40="Ifugao",CONCATENATE(I40,"I"),IF(AX40="Mt. Province",CONCATENATE(I40,"MP"),IF(AX40="Kalinga",CONCATENATE(I40,"K"),IF(AX40="Benguet",CONCATENATE(I40,"B"),"Vacant")))))))) -> ADA6I | K40: =CONCATENATE(J40,AY40) -> ADA6IF | L40: =IF(AX40="Regional Office",(IF(AY40="M","RM","RF")),IF(AX40="Abra",(IF(AY40="M","AbM","AbF")),IF(AX40="Baguio City",(IF(AY40="M","BCM","BCF")),IF(AX40="Apayao",(IF(AY40="M","ApM","ApF")),IF(AX40="Benguet",(IF(AY40="M","BM","BF")),IF(AX40="Ifugao",(IF(AY40="M","IM","IF")),IF(AX40="Kalinga",(IF(AY40="M","KM","KF")),IF(AX40="Mt. Province",(IF(AY40="M","MPM","MPF")),"XXX")))))))) -> IF | M40: 1 | N40: 1 | O40: 1 | P40: 1 | AH40: =VLOOKUP(C40,idica,2,FALSE)*12 -> 178164 | AI40: =(SUMPRODUCT((norman=C40)*(grace=AJ40)*(barnachea)))*12 -> 179532 | AJ40: 2 | AK40: 011 | AL40: R | AM40: A | AN40: 310100100001000 | AO40: Regional Office | AP40: MED | AQ40: Regional Office | AR40: MAGCIANO | AS40: Juden Beth | AT40: Uybaan | AU40: =LEFT(AT40)&IF(ISNUMBER(FIND(" ",AT40)),MID(AT40,FIND(" ",AT40)+1,1),"")&IF(ISNUMBER(FIND(" ",AT40,FIND(" ",AT40)+1)),MID(AT40,FIND(" ",AT40,FIND(" ",AT40)+1)+1,1),"") -> U | AV40: =PROPER(CONCATENATE(AS40," ",AU40,". ",AR40)) -> Juden Beth U. Magciano | AW40: =CONCATENATE(AR40,", ",AS40," ",AT40) -> MAGCIANO, Juden Beth Uybaan | AX40: Ifugao | AY40: F | AZ40: 33795 | BA40: =DATEDIF(AZ40,TODAY(),"Y") -> 33 | BB40: =IF(BA40<30,"A",IF(BA40<40,"B",IF(BA40<50,"C",IF(BA40<60,"D",IF(BA40<65,"E","VACANT"))))) -> B | BC40: =+IF(AX40="Regional Office",(IF(BB40="A","RA",(IF(BB40="B","RB",IF(BB40="C","RC",IF(BB40="D","RD",IF(BB40="E","RE","VACANT"))))))),IF(AX40="Abra",(IF(BB40="A","AbA",(IF(BB40="B","AbB",IF(BB40="C","AbC",IF(BB40="D","AbD",IF(BB40="E","AbE","VACANT"))))))),IF(AX40="Baguio City",(IF(BB40="A","BCA",(IF(BB40="B","BCB",IF(BB40="C","BCC",IF(BB40="D","BCD",IF(BB40="E","BCE","VACANT"))))))),IF(AX40="Apayao",(IF(BB40="A","ApA",(IF(BB40="B","ApB",IF(BB40="C","ApC",IF(BB40="D","ApD",IF(BB40="E","ApE","VACANT"))))))),IF(AX40="Benguet",(IF(BB40="A","BA",(IF(BB40="B","BB",IF(BB40="C","BC",IF(BB40="D","BD",IF(BB40="E","BE","VACANT"))))))),IF(AX40="Ifugao",(IF(BB40="A","IA",(IF(BB40="B","IB",IF(BB40="C","IC",IF(BB40="D","ID",IF(BB40="E","IE","VACANT"))))))),IF(AX40="Kalinga",(IF(BB40="A","KA",(IF(BB40="B","KB",IF(BB40="C","KC",IF(BB40="D","KD",IF(BB40="E","KE","VACANT"))))))),IF(AX40="Mt. Province",(IF(BB40="A","MPA",(IF(BB40="B","MPB",IF(BB40="C","MPC",IF(BB40="D","MPD",IF(BB40="E","MPE","VACANT"))))))),"XXX")))))))) -> IB | BD40: =CONCATENATE(BC40,AY40) -> IBF | BE40: =CONCATENATE(I40,BD40) -> ADA6IBF | BF40: 462-398-464 | BG40: 42186 | BH40: 42186 | BI40: =DATEDIF(BG40,TODAY(),"Y") -> 10 | BJ40: =DATEDIF(BH40,TODAY(),"Y") -> 10 | BK40: 42186 | BL40: =DATEDIF(BK40,TODAY(),"Y") -> 10 | BM40: P | BN40: CSP | BO40: BS MA | BQ40: =CONCATENATE(1,AY40,BM40) -> 1FP
A41: Sub-Total | AJ41: =COUNTIF(AJ31:AJ40,"<>") -> 10 | BD41: =CONCATENATE(BC41,AY41)
A42: 64,000 Finance and Administrative Division | BD42: =CONCATENATE(BC42,AY42)
